Workbook

Sheet Oct-23
A1: EMP_AREA_CODE | B1: EMP_REG_SERIAL_NO | C1: EMP_SUB_AREA_CODE | D1: Name | E1: EOBI_NO | F1: CNIC | G1: NIC | H1: DOB | I1: DOJ | J1: DOE | K1: NO_OF_DAYS_WORKED | L1: From_Date | M1: To_Date | N1: Payment | O1: Employer Contribution | P1: Total EOBI
A2: FAA | B2: 4320 | C2: FS | D2: Aamir Nawaz | E2: 4700E637868 | F2: 14301-7981096-7 | H2: 32933 | I2: 45166 | K2: =MAX(0, MIN(M2, J2) - MAX(L2, I2) + 1) -> 31 | L2: 45200 | M2: 45230 | N2: =ROUNDUP(K2/31*320,0) -> 320 | O2: =N2*5 -> 1600 | P2: =N2+O2 -> 1920
A3: FAA | B3: 4320 | C3: FS | D3: Abdullah Bin Rashid | E3: 4700A705194 | F3: 61101-3101618-7 | H3: 36358 | I3: 45027 | K3: =MAX(0, MIN(M3, J3) - MAX(L3, I3) + 1) -> 31 | L3: 45200 | M3: 45230 | N3: =ROUNDUP(K3/31*320,0) -> 320 | O3: =N3*5 -> 1600 | P3: =N3+O3 -> 1920
A4: FAA | B4: 4320 | C4: FS | D4: Abdullah Rasheed | E4: 4700G688671 | F4: 37401-7271621-7 | H4: 36860 | I4: 45124 | K4: =MAX(0, MIN(M4, J4) - MAX(L4, I4) + 1) -> 31 | L4: 45200 | M4: 45230 | N4: =ROUNDUP(K4/31*320,0) -> 320 | O4: =N4*5 -> 1600 | P4: =N4+O4 -> 1920
A5: FAA | B5: 4320 | C5: FS | D5: Abeera Shah | E5: 4700C706554 | F5: 61101-5688667-0 | H5: 36257 | I5: 45019 | K5: =MAX(0, MIN(M5, J5) - MAX(L5, I5) + 1) -> 31 | L5: 45200 | M5: 45230 | N5: =ROUNDUP(K5/31*320,0) -> 320 | O5: =N5*5 -> 1600 | P5: =N5+O5 -> 1920
A6: FAA | B6: 4320 | C6: FS | D6: Ahmad Hassan | E6: 4600D315335 | F6: 37405-4246562-3 | H6: 35997 | I6: 45061 | K6: =MAX(0, MIN(M6, J6) - MAX(L6, I6) + 1) -> 31 | L6: 45200 | M6: 45230 | N6: =ROUNDUP(K6/31*320,0) -> 320 | O6: =N6*5 -> 1600 | P6: =N6+O6 -> 1920
A7: FAA | B7: 4320 | C7: FS | D7: Ali Aziz | E7: 4700J723957 | F7: 81202-8426576-7 | H7: 35053 | I7: 45173 | K7: =MAX(0, MIN(M7, J7) - MAX(L7, I7) + 1) -> 31 | L7: 45200 | M7: 45230 | N7: =ROUNDUP(K7/31*320,0) -> 320 | O7: =N7*5 -> 1600 | P7: =N7+O7 -> 1920
A8: FAA | B8: 4320 | C8: FS | D8: Ali Nawaz Channa | E8: 0800E397265 | F8: 42201-8465990-5 | H8: 33408 | I8: 45078 | K8: =MAX(0, MIN(M8, J8) - MAX(L8, I8) + 1) -> 31 | L8: 45200 | M8: 45230 | N8: =ROUNDUP(K8/31*320,0) -> 320 | O8: =N8*5 -> 1600 | P8: =N8+O8 -> 1920
A9: FAA | B9: 4320 | C9: FS | D9: Alina Mubarik | E9: 4700C710820 | F9: 61101-5318332-4 | H9: 35983 | I9: 45082 | K9: =MAX(0, MIN(M9, J9) - MAX(L9, I9) + 1) -> 31 | L9: 45200 | M9: 45230 | N9: =ROUNDUP(K9/31*320,0) -> 320 | O9: =N9*5 -> 1600 | P9: =N9+O9 -> 1920
A10: FAA | B10: 4320 | C10: FS | D10: Amais Sheikh | E10: 4700D606664 | F10: 37405-5578644-1 | H10: 34684 | I10: 44958 | K10: =MAX(0, MIN(M10, J10) - MAX(L10, I10) + 1) -> 31 | L10: 45200 | M10: 45230 | N10: =ROUNDUP(K10/31*320,0) -> 320 | O10: =N10*5 -> 1600 | P10: =N10+O10 -> 1920
A11: FAA | B11: 4320 | C11: FS | D11: Asim Latif | E11: 4700A658224 | F11: 33302-5158556-5 | H11: 37370 | I11: 44739 | K11: =MAX(0, MIN(M11, J11) - MAX(L11, I11) + 1) -> 31 | L11: 45200 | M11: 45230 | N11: =ROUNDUP(K11/31*320,0) -> 320 | O11: =N11*5 -> 1600 | P11: =N11+O11 -> 1920
A12: FAA | B12: 4320 | C12: FS | D12: Atif Nawaz | E12: 4700E740695 | F12: 38404-7428636-7 | H12: 36399 | I12: 45229 | K12: =MAX(0, MIN(M12, J12) - MAX(L12, I12) + 1) -> 2 | L12: 45200 | M12: 45230 | N12: =ROUNDUP(K12/31*320,0) -> 21 | O12: =N12*5 -> 105 | P12: =N12+O12 -> 126
A13: FAA | B13: 4320 | C13: FS | D13: Basit Afraz | E13: 4700C703310 | F13: 37405-8019865-5 | H13: 34601 | I13: 44986 | K13: =MAX(0, MIN(M13, J13) - MAX(L13, I13) + 1) -> 31 | L13: 45200 | M13: 45230 | N13: =ROUNDUP(K13/31*320,0) -> 320 | O13: =N13*5 -> 1600 | P13: =N13+O13 -> 1920
... A20: FAA | B20: 4320 | C20: FS | D20: Jalees Mukarram | E20: 4700G638367 | F20: 31201-9892348-9 | H20: 37210 | I20: 44125 | K20: =MAX(0, MIN(M20, J20) - MAX(L20, I20) + 1) -> 31 | L20: 45200 | M20: 45230 | N20: =ROUNDUP(K20/31*320,0) -> 320 | O20: =N20*5 -> 1600 | P20: =N20+O20 -> 1920
A21: FAA | B21: 4320 | C21: FS | D21: Javeria Sadia | E21: 0600F209061 | F21: 42101-5324187-2 | H21: 35483 | I21: 45043 | J21: 45230 | K21: =MAX(0, MIN(M21, J21) - MAX(L21, I21) + 1) -> 31 | L21: 45200 | M21: 45230 | N21: =ROUNDUP(K21/31*320,0) -> 320 | O21: =N21*5 -> 1600 | P21: =N21+O21 -> 1920
A22: FAA | B22: 4320 | C22: FS | D22: Khadija Umer | E22: 4700A710848 | F22: 31202-4982058-2 | H22: 36401 | I22: 45096 | K22: =MAX(0, MIN(M22, J22) - MAX(L22, I22) + 1) -> 31 | L22: 45200 | M22: 45230 | N22: =ROUNDUP(K22/31*320,0) -> 320 | O22: =N22*5 -> 1600 | P22: =N22+O22 -> 1920
A23: FAA | B23: 4320 | C23: FS | D23: Laiba Imran | E23: 4700H684977 | F23: 37405-8102020-8 | H23: 36113 | I23: 44866 | K23: =MAX(0, MIN(M23, J23) - MAX(L23, I23) + 1) -> 31 | L23: 45200 | M23: 45230 | N23: =ROUNDUP(K23/31*320,0) -> 320 | O23: =N23*5 -> 1600 | P23: =N23+O23 -> 1920
A24: FAA | B24: 4320 | C24: FS | D24: Mahnoor Farhan khokhar | E24: 4700E720946 | F24: 61101-9447970-2 | H24: 36318 | I24: 45139 | J24: 45224 | K24: =MAX(0, MIN(M24, J24) - MAX(L24, I24) + 1) -> 25 | L24: 45200 | M24: 45230 | N24: =ROUNDUP(K24/31*320,0) -> 259 | O24: =N24*5 -> 1295 | P24: =N24+O24 -> 1554
A25: FAA | B25: 4320 | C25: FS | D25: Mohammad Ehtasham Balland | E25: 4700D711914 | F25: 36302-5494206-1 | H25: 33737 | I25: 45139 | K25: =MAX(0, MIN(M25, J25) - MAX(L25, I25) + 1) -> 31 | L25: 45200 | M25: 45230 | N25: =ROUNDUP(K25/31*320,0) -> 320 | O25: =N25*5 -> 1600 | P25: =N25+O25 -> 1920
A26: FAA | B26: 4320 | C26: FS | D26: Muaaz Arshad | E26: 4100C164358 | F26: 34101-0197233-1 | H26: 33917 | I26: 45166 | K26: =MAX(0, MIN(M26, J26) - MAX(L26, I26) + 1) -> 31 | L26: 45200 | M26: 45230 | N26: =ROUNDUP(K26/31*320,0) -> 320 | O26: =N26*5 -> 1600 | P26: =N26+O26 -> 1920
A27: FAA | B27: 4320 | C27: FS | D27: Muhaimin Khan | E27: 4700E763936 | F27: 34101-6716758-6 | H27: 36502 | I27: 45098 | K27: =MAX(0, MIN(M27, J27) - MAX(L27, I27) + 1) -> 31 | L27: 45200 | M27: 45230 | N27: =ROUNDUP(K27/31*320,0) -> 320 | O27: =N27*5 -> 1600 | P27: =N27+O27 -> 1920
A28: FAA | B28: 4320 | C28: FS | D28: Muhammad Abdullah Salam | E28: 4700G697010 | F28: 17301-7752570-9 | H28: 36690 | I28: 44938 | K28: =MAX(0, MIN(M28, J28) - MAX(L28, I28) + 1) -> 31 | L28: 45200 | M28: 45230 | N28: =ROUNDUP(K28/31*320,0) -> 320 | O28: =N28*5 -> 1600 | P28: =N28+O28 -> 1920
A29: FAA | B29: 4320 | C29: FS | D29: Muhammad Abubakar | E29: 4700H723959 | F29: 35201-8046049-1 | H29: 37240 | I29: 45176 | K29: =MAX(0, MIN(M29, J29) - MAX(L29, I29) + 1) -> 31 | L29: 45200 | M29: 45230 | N29: =ROUNDUP(K29/31*320,0) -> 320 | O29: =N29*5 -> 1600 | P29: =N29+O29 -> 1920
A30: FAA | B30: 4320 | C30: FS | D30: Muhammad Adnan | E30: 4700A638371 | F30: 54401-7578020-9 | H30: 33240 | I30: 44290 | J30: 45230 | K30: =MAX(0, MIN(M30, J30) - MAX(L30, I30) + 1) -> 31 | L30: 45200 | M30: 45230 | N30: =ROUNDUP(K30/31*320,0) -> 320 | O30: =N30*5 -> 1600 | P30: =N30+O30 -> 1920
A31: FAA | B31: 4320 | C31: FS | D31: Muhammad Arham | E31: 4700J673932 | F31: 36103-7439746-1 | H31: 37136 | I31: 45201 | K31: =MAX(0, MIN(M31, J31) - MAX(L31, I31) + 1) -> 30 | L31: 45200 | M31: 45230 | N31: =ROUNDUP(K31/31*320,0) -> 310 | O31: =N31*5 -> 1550 | P31: =N31+O31 -> 1860
A32: FAA | B32: 4320 | C32: FS | D32: Muhammad Asadullah Shahid | E32: 4700G581544 | F32: 36603-1234883-1 | H32: 35943 | I32: 45215 | K32: =MAX(0, MIN(M32, J32) - MAX(L32, I32) + 1) -> 16 | L32: 45200 | M32: 45230 | N32: =ROUNDUP(K32/31*320,0) -> 166 | O32: =N32*5 -> 830 | P32: =N32+O32 -> 996
A33: FAA | B33: 4320 | C33: FS | D33: Muhammad Hammad Maqsood | E33: 4700A703312 | F33: 37405-2794891-9 | H33: 36898 | I33: 44988 | K33: =MAX(0, MIN(M33, J33) - MAX(L33, I33) + 1) -> 31 | L33: 45200 | M33: 45230 | N33: =ROUNDUP(K33/31*320,0) -> 320 | O33: =N33*5 -> 1600 | P33: =N33+O33 -> 1920
A34: FAA | B34: 4320 | C34: FS | D34: Muhammad Hamza | E34: 4600F317513 | F34: 61101-4668132-7 | H34: 35159 | I34: 45078 | K34: =MAX(0, MIN(M34, J34) - MAX(L34, I34) + 1) -> 31 | L34: 45200 | M34: 45230 | N34: =ROUNDUP(K34/31*320,0) -> 320 | O34: =N34*5 -> 1600 | P34: =N34+O34 -> 1920
A35: FAA | B35: 4320 | C35: FS | D35: Muhammad Haris Gul | E35: 4700I638373 | F35: 61101-3389194-7 | H35: 36029 | I35: 45068 | J35: 45207 | K35: =MAX(0, MIN(M35, J35) - MAX(L35, I35) + 1) -> 8 | L35: 45200 | M35: 45230 | N35: =ROUNDUP(K35/31*320,0) -> 83 | O35: =N35*5 -> 415 | P35: =N35+O35 -> 498
A36: FAA | B36: 4320 | C36: FS | D36: Muhammad Hassan Shakeel | E36: 4700H690431 | F36: 35402-2593513-5 | H36: 36794 | I36: 44915 | K36: =MAX(0, MIN(M36, J36) - MAX(L36, I36) + 1) -> 31 | L36: 45200 | M36: 45230 | N36: =ROUNDUP(K36/31*320,0) -> 320 | O36: =N36*5 -> 1600 | P36: =N36+O36 -> 1920
A37: FAA | B37: 4320 | C37: FS | D37: Muhammad Ibrahim | E37: 4700C720948 | F37: 31101-0776303-7 | H37: 37149 | I37: 45124 | K37: =MAX(0, MIN(M37, J37) - MAX(L37, I37) + 1) -> 31 | L37: 45200 | M37: 45230 | N37: =ROUNDUP(K37/31*320,0) -> 320 | O37: =N37*5 -> 1600 | P37: =N37+O37 -> 1920
A38: FAA | B38: 4320 | C38: FS | D38: Muhammad Mutahhar | E38: 3300E326308 | F38: 42301-3092028-3 | H38: 35767 | I38: 45117 | K38: =MAX(0, MIN(M38, J38) - MAX(L38, I38) + 1) -> 31 | L38: 45200 | M38: 45230 | N38: =ROUNDUP(K38/31*320,0) -> 320 | O38: =N38*5 -> 1600 | P38: =N38+O38 -> 1920
A39: FAA | B39: 4320 | C39: FS | D39: Muhammad Saad Tariq | E39: 4700D679730 | F39: 61101-0817777-7 | H39: 36207 | I39: 45054 | K39: =MAX(0, MIN(M39, J39) - MAX(L39, I39) + 1) -> 31 | L39: 45200 | M39: 45230 | N39: =ROUNDUP(K39/31*320,0) -> 320 | O39: =N39*5 -> 1600 | P39: =N39+O39 -> 1920
A40: FAA | B40: 4320 | C40: FS | D40: Muhammad Umair | E40: 4700A700796 | F40: 42501-3911861-7 | H40: 36480 | I40: 44970 | K40: =MAX(0, MIN(M40, 'Nov-23'!J39) - MAX(L40, I40) + 1) -> 31 | L40: 45200 | M40: 45230 | N40: =ROUNDUP(K40/31*320,0) -> 320 | O40: =N40*5 -> 1600 | P40: =N40+O40 -> 1920
A41: FAA | B41: 4320 | C41: FS | D41: Muhammad Wajahat | E41: 4700A618216 | F41: 32203-2007547-1 | H41: 36768 | I41: 44888 | K41: =MAX(0, MIN(M41, J41) - MAX(L41, I41) + 1) -> 31 | L41: 45200 | M41: 45230 | N41: =ROUNDUP(K41/31*320,0) -> 320 | O41: =N41*5 -> 1600 | P41: =N41+O41 -> 1920
A42: FAA | B42: 4320 | C42: FS | D42: Muhammad Waleed Imran | E42: 4700J724945 | F42: 35201-8352529-1 | H42: 36074 | I42: 45180 | K42: =MAX(0, MIN(M42, J42) - MAX(L42, I42) + 1) -> 31 | L42: 45200 | M42: 45230 | N42: =ROUNDUP(K42/31*320,0) -> 320 | O42: =N42*5 -> 1600 | P42: =N42+O42 -> 1920
A43: FAA | B43: 4320 | C43: FS | D43: Muhammad Zahab Ahmed | E43: 3600G329844 | F43: 31102-2135283-9 | H43: 34300 | I43: 45183 | K43: =MAX(0, MIN(M43, J43) - MAX(L43, I43) + 1) -> 31 | L43: 45200 | M43: 45230 | N43: =ROUNDUP(K43/31*320,0) -> 320 | O43: =N43*5 -> 1600 | P43: =N43+O43 -> 1920
A44: FAA | B44: 4320 | C44: FS | D44: Muhammad Zaid | E44: 4700B667971 | F44: 42000-5973098-1 | H44: 36118 | I44: 44783 | K44: =MAX(0, MIN(M44, J44) - MAX(L44, I44) + 1) -> 31 | L44: 45200 | M44: 45230 | N44: =ROUNDUP(K44/31*320,0) -> 320 | O44: =N44*5 -> 1600 | P44: =N44+O44 -> 1920
A45: FAA | B45: 4320 | C45: FS | D45: Naimal Imran | E45: 4700J662127 | F45: 35202-0754928-4 | H45: 36541 | I45: 44755 | K45: =MAX(0, MIN(M45, J45) - MAX(L45, I45) + 1) -> 31 | L45: 45200 | M45: 45230 | N45: =ROUNDUP(K45/31*320,0) -> 320 | O45: =N45*5 -> 1600 | P45: =N45+O45 -> 1920
A46: FAA | B46: 4320 | C46: FS | D46: Namra Akram | E46: 4700F444303 | F46: 61101-4919576-8 | H46: 34335 | I46: 45078 | K46: =MAX(0, MIN(M46, J46) - MAX(L46, I46) + 1) -> 31 | L46: 45200 | M46: 45230 | N46: =ROUNDUP(K46/31*320,0) -> 320 | O46: =N46*5 -> 1600 | P46: =N46+O46 -> 1920
A47: FAA | B47: 4320 | C47: FS | D47: Naveed Ahmed | E47: 4700H679736 | F47: 42201-5462974-9 | H47: 31014 | I47: 44805 | K47: =MAX(0, MIN(M47, J47) - MAX(L47, I47) + 1) -> 31 | L47: 45200 | M47: 45230 | N47: =ROUNDUP(K47/31*320,0) -> 320 | O47: =N47*5 -> 1600 | P47: =N47+O47 -> 1920
A48: FAA | B48: 4320 | C48: FS | D48: Qazi Shayan | E48: 4700A710864 | F48: 15402-0378555-7 | H48: 35150 | I48: 45079 | K48: =MAX(0, MIN(M48, J48) - MAX(L48, I48) + 1) -> 31 | L48: 45200 | M48: 45230 | N48: =ROUNDUP(K48/31*320,0) -> 320 | O48: =N48*5 -> 1600 | P48: =N48+O48 -> 1920
A49: FAA | B49: 4320 | C49: FS | D49: Rana Usair Sohail | E49: 0800H514678 | F49: 35202-2606196-5 | H49: 35779 | I49: 45176 | K49: =MAX(0, MIN(M49, J49) - MAX(L49, I49) + 1) -> 31 | L49: 45200 | M49: 45230 | N49: =ROUNDUP(K49/31*320,0) -> 320 | O49: =N49*5 -> 1600 | P49: =N49+O49 -> 1920
A50: FAA | B50: 4320 | C50: FS | D50: Rashid Iqbal | E50: 4700I703314 | F50: 37405-6880780-7 | H50: 34732 | I50: 44986 | K50: =MAX(0, MIN(M50, J50) - MAX(L50, I50) + 1) -> 31 | L50: 45200 | M50: 45230 | N50: =ROUNDUP(K50/31*320,0) -> 320 | O50: =N50*5 -> 1600 | P50: =N50+O50 -> 1920
A51: FAA | B51: 4320 | C51: FS | D51: Reyan Ahmad | E51: 3100D850990 | F51: 36101-6729437-9 | H51: 35772 | I51: 45222 | K51: =MAX(0, MIN(M51, J51) - MAX(L51, I51) + 1) -> 9 | L51: 45200 | M51: 45230 | N51: =ROUNDUP(K51/31*320,0) -> 93 | O51: =N51*5 -> 465 | P51: =N51+O51 -> 558
A52: FAA | B52: 4320 | C52: FS | D52: Saad Aziz | E52: 4700J700797 | F52: 37405-7429064-1 | H52: 35931 | I52: 44958 | K52: =MAX(0, MIN(M52, J52) - MAX(L52, I52) + 1) -> 31 | L52: 45200 | M52: 45230 | N52: =ROUNDUP(K52/31*320,0) -> 320 | O52: =N52*5 -> 1600 | P52: =N52+O52 -> 1920
... A57: FAA | B57: 4320 | C57: FS | D57: Shahzad Farooq | E57: 4700G690432 | F57: 42501-8133748-7 | H57: 36979 | I57: 44907 | K57: =MAX(0, MIN(M57, J57) - MAX(L57, I57) + 1) -> 31 | L57: 45200 | M57: 45230 | N57: =ROUNDUP(K57/31*320,0) -> 320 | O57: =N57*5 -> 1600 | P57: =N57+O57 -> 1920
A58: FAA | B58: 4320 | C58: FS | D58: Shahzaib Chaudhary | E58: 4700I720950 | F58: 33100-9292576-3 | H58: 36253 | I58: 45159 | J58: 45209 | K58: =MAX(0, MIN(M58, J58) - MAX(L58, I58) + 1) -> 10 | L58: 45200 | M58: 45230 | N58: =ROUNDUP(K58/31*320,0) -> 104 | O58: =N58*5 -> 520 | P58: =N58+O58 -> 624
A59: FAA | B59: 4320 | C59: FS | D59: Shaiq Habib | E59: 0400C579124 | F59: 61101-1388832-7 | H59: 36421 | I59: 45208 | K59: =MAX(0, MIN(M59, J59) - MAX(L59, I59) + 1) -> 23 | L59: 45200 | M59: 45230 | N59: =ROUNDUP(K59/31*320,0) -> 238 | O59: =N59*5 -> 1190 | P59: =N59+O59 -> 1428
A60: FAA | B60: 4320 | C60: FS | D60: Shawal Fida | E60: 4700I700798 | F60: 16202-0438523-4 | H60: 36075 | I60: 44977 | K60: =MAX(0, MIN(M60, J60) - MAX(L60, I60) + 1) -> 31 | L60: 45200 | M60: 45230 | N60: =ROUNDUP(K60/31*320,0) -> 320 | O60: =N60*5 -> 1600 | P60: =N60+O60 -> 1920
A61: FAA | B61: 4320 | C61: FS | D61: Sheikh Muhammad Saad | E61: 3600D516452 | F61: 35202-2211437-9 | H61: 36089 | I61: 45195 | K61: =MAX(0, MIN(M61, J61) - MAX(L61, I61) + 1) -> 31 | L61: 45200 | M61: 45230 | N61: =ROUNDUP(K61/31*320,0) -> 320 | O61: =N61*5 -> 1600 | P61: =N61+O61 -> 1920
A62: FAA | B62: 4320 | C62: FS | D62: Sheraz Ahmad | E62: 4700D645309 | F62: 32304-6599148-9 | H62: 35461 | I62: 44914 | J62: 45210 | K62: =MAX(0, MIN(M62, J62) - MAX(L62, I62) + 1) -> 11 | L62: 45200 | M62: 45230 | N62: =ROUNDUP(K62/31*320,0) -> 114 | O62: =N62*5 -> 570 | P62: =N62+O62 -> 684
A63: FAA | B63: 4320 | C63: FS | D63: Subhana Yasin | E63: 4700E723960 | F63: 36502-1828819-0 | H63: 36574 | I63: 45187 | K63: =MAX(0, MIN(M63, J63) - MAX(L63, I63) + 1) -> 31 | L63: 45200 | M63: 45230 | N63: =ROUNDUP(K63/31*320,0) -> 320 | O63: =N63*5 -> 1600 | P63: =N63+O63 -> 1920
A64: FAA | B64: 4320 | C64: FS | D64: Syed Haider | E64: 3100E941643 | F64: 33102-5032259-9 | H64: 35115 | I64: 45194 | K64: =MAX(0, MIN(M64, J64) - MAX(L64, I64) + 1) -> 31 | L64: 45200 | M64: 45230 | N64: =ROUNDUP(K64/31*320,0) -> 320 | O64: =N64*5 -> 1600 | P64: =N64+O64 -> 1920
A65: FAA | B65: 4320 | C65: FS | D65: Talha Arshad Malik | E65: 3600F372686 | F65: 37405-6378563-1 | H65: 33156 | I65: 44285 | K65: =MAX(0, MIN(M65, J65) - MAX(L65, I65) + 1) -> 31 | L65: 45200 | M65: 45230 | N65: =ROUNDUP(K65/31*320,0) -> 320 | O65: =N65*5 -> 1600 | P65: =N65+O65 -> 1920
A66: FAA | B66: 4320 | C66: FS | D66: Talha Jibran | E66: 4700G718997 | F66: 61101-8798575-7 | H66: 36096 | I66: 45174 | K66: =MAX(0, MIN(M66, J66) - MAX(L66, I66) + 1) -> 31 | L66: 45200 | M66: 45230 | N66: =ROUNDUP(K66/31*320,0) -> 320 | O66: =N66*5 -> 1600 | P66: =N66+O66 -> 1920
A67: FAA | B67: 4320 | C67: FS | D67: Tayyab Abbas | E67: 4700A685051 | F67: 17301-2752063-7 | H67: 36797 | I67: 44886 | K67: =MAX(0, MIN(M67, J67) - MAX(L67, I67) + 1) -> 31 | L67: 45200 | M67: 45230 | N67: =ROUNDUP(K67/31*320,0) -> 320 | O67: =N67*5 -> 1600 | P67: =N67+O67 -> 1920
A68: FAA | B68: 4320 | C68: FS | D68: Umaira Jabeen | E68: 3600J522091 | F68: 37104-5371430-8 | H68: 33769 | I68: 44816 | K68: =MAX(0, MIN(M68, J68) - MAX(L68, I68) + 1) -> 31 | L68: 45200 | M68: 45230 | N68: =ROUNDUP(K68/31*320,0) -> 320 | O68: =N68*5 -> 1600 | P68: =N68+O68 -> 1920
A69: FAA | B69: 4320 | C69: FS | D69: Umar Farooq | E69: 4700D723961 | F69: 36501-4241566-9 | H69: 36408 | I69: 45173 | K69: =MAX(0, MIN(M69, J69) - MAX(L69, I69) + 1) -> 31 | L69: 45200 | M69: 45230 | N69: =ROUNDUP(K69/31*320,0) -> 320 | O69: =N69*5 -> 1600 | P69: =N69+O69 -> 1920
A70: FAA | B70: 4320 | C70: FS | D70: Waleed Sadiq | E70: 4700C710870 | F70: 82101-6085499-3 | H70: 35818 | I70: 45089 | K70: =MAX(0, MIN(M70, J70) - MAX(L70, I70) + 1) -> 31 | L70: 45200 | M70: 45230 | N70: =ROUNDUP(K70/31*320,0) -> 320 | O70: =N70*5 -> 1600 | P70: =N70+O70 -> 1920
A71: FAA | B71: 4320 | C71: FS | D71: Zain Shahid | E71: 4700H700799 | F71: 36401-6591078-1 | H71: 36177 | I71: 44970 | K71: =MAX(0, MIN(M71, J71) - MAX(L71, I71) + 1) -> 31 | L71: 45200 | M71: 45230 | N71: =ROUNDUP(K71/31*320,0) -> 320 | O71: =N71*5 -> 1600 | P71: =N71+O71 -> 1920
A72: FAA | B72: 4320 | C72: FS | D72: Zoha Munir | E72: 0600G182381 | F72: 35202-9887337-8 | H72: 35743 | I72: 45222 | K72: =MAX(0, MIN(M72, J72) - MAX(L72, I72) + 1) -> 9 | L72: 45200 | M72: 45230 | N72: =ROUNDUP(K72/31*320,0) -> 93 | O72: =N72*5 -> 465 | P72: =N72+O72 -> 558
P73: =SUM(P2:P72) -> 126006

Sheet Nov-23
A1: EMP_AREA_CODE | B1: EMP_REG_SERIAL_NO | C1: EMP_SUB_AREA_CODE | D1: Name | E1: EOBI_NO | F1: CNIC | G1: NIC | H1: DOB | I1: DOJ | J1: DOE | K1: NO_OF_DAYS_WORKED | L1: From_Date | M1: To_Date | N1: Payment | O1: Employer Contribution | P1: Total EOBI
A2: FAA | B2: 4320 | C2: FS | D2: Aamir Nawaz | E2: 4700E637868 | F2: 14301-7981096-7 | H2: 32933 | I2: 45166 | K2: =MAX(0, MIN(M2, J2) - MAX(L2, I2) + 1) -> 30 | L2: 45231 | M2: 45260 | N2: =ROUNDUP(K2/30*320,0) -> 320 | O2: =N2*5 -> 1600 | P2: =N2+O2 -> 1920
A3: FAA | B3: 4320 | C3: FS | D3: Abdullah Bin Rashid | E3: 4700A705194 | F3: 61101-3101618-7 | H3: 36358 | I3: 45027 | K3: =MAX(0, MIN(M3, J3) - MAX(L3, I3) + 1) -> 30 | L3: 45231 | M3: 45260 | N3: =ROUNDUP(K3/30*320,0) -> 320 | O3: =N3*5 -> 1600 | P3: =N3+O3 -> 1920
A4: FAA | B4: 4320 | C4: FS | D4: Abdullah Rasheed | E4: 4700G688671 | F4: 37401-7271621-7 | H4: 36860 | I4: 45124 | K4: =MAX(0, MIN(M4, J4) - MAX(L4, I4) + 1) -> 30 | L4: 45231 | M4: 45260 | N4: =ROUNDUP(K4/30*320,0) -> 320 | O4: =N4*5 -> 1600 | P4: =N4+O4 -> 1920
A5: FAA | B5: 4320 | C5: FS | D5: Abeera Shah | E5: 4700C706554 | F5: 61101-5688667-0 | H5: 36257 | I5: 45019 | J5: 45260 | K5: =MAX(0, MIN(M5, J5) - MAX(L5, I5) + 1) -> 30 | L5: 45231 | M5: 45260 | N5: =ROUNDUP(K5/30*320,0) -> 320 | O5: =N5*5 -> 1600 | P5: =N5+O5 -> 1920
A6: FAA | B6: 4320 | C6: FS | D6: Ahmad Hassan | E6: 4600D315335 | F6: 37405-4246562-3 | H6: 35997 | I6: 45061 | K6: =MAX(0, MIN(M6, J6) - MAX(L6, I6) + 1) -> 30 | L6: 45231 | M6: 45260 | N6: =ROUNDUP(K6/30*320,0) -> 320 | O6: =N6*5 -> 1600 | P6: =N6+O6 -> 1920
A7: FAA | B7: 4320 | C7: FS | D7: Ali Aziz | E7: 4700J723957 | F7: 81202-8426576-7 | H7: 35053 | I7: 45173 | K7: =MAX(0, MIN(M7, J7) - MAX(L7, I7) + 1) -> 30 | L7: 45231 | M7: 45260 | N7: =ROUNDUP(K7/30*320,0) -> 320 | O7: =N7*5 -> 1600 | P7: =N7+O7 -> 1920
A8: FAA | B8: 4320 | C8: FS | D8: Ali Irfan | E8: 3100J940197 | F8: 35202-7336402-9 | H8: 36634 | I8: 45251 | K8: =MAX(0, MIN(M8, J8) - MAX(L8, I8) + 1) -> 10 | L8: 45231 | M8: 45260 | N8: =ROUNDUP(K8/30*320,0) -> 107 | O8: =N8*5 -> 535 | P8: =N8+O8 -> 642
A9: FAA | B9: 4320 | C9: FS | D9: Ali Nawaz Channa | E9: 0800E397265 | F9: 42201-8465990-5 | H9: 33408 | I9: 45078 | K9: =MAX(0, MIN(M9, J9) - MAX(L9, I9) + 1) -> 30 | L9: 45231 | M9: 45260 | N9: =ROUNDUP(K9/30*320,0) -> 320 | O9: =N9*5 -> 1600 | P9: =N9+O9 -> 1920
A10: FAA | B10: 4320 | C10: FS | D10: Alina Mubarik | E10: 4700C710820 | F10: 61101-5318332-4 | H10: 35983 | I10: 45082 | K10: =MAX(0, MIN(M10, J10) - MAX(L10, I10) + 1) -> 30 | L10: 45231 | M10: 45260 | N10: =ROUNDUP(K10/30*320,0) -> 320 | O10: =N10*5 -> 1600 | P10: =N10+O10 -> 1920
A11: FAA | B11: 4320 | C11: FS | D11: Altamash Shaban | E11: 4700G469815 | F11: 37405-5322814-9 | H11: 33048 | I11: 45250 | K11: =MAX(0, MIN(M11, J11) - MAX(L11, I11) + 1) -> 11 | L11: 45231 | M11: 45260 | N11: =ROUNDUP(K11/30*320,0) -> 118 | O11: =N11*5 -> 590 | P11: =N11+O11 -> 708
A12: FAA | B12: 4320 | C12: FS | D12: Amais Sheikh | E12: 4700D606664 | F12: 37405-5578644-1 | H12: 34684 | I12: 44958 | J12: 45256 | K12: =MAX(0, MIN(M12, J12) - MAX(L12, I12) + 1) -> 26 | L12: 45231 | M12: 45260 | N12: =ROUNDUP(K12/30*320,0) -> 278 | O12: =N12*5 -> 1390 | P12: =N12+O12 -> 1668
A13: FAA | B13: 4320 | C13: FS | D13: Asim Latif | E13: 4700A658224 | F13: 33302-5158556-5 | H13: 37370 | I13: 44739 | K13: =MAX(0, MIN(M13, J13) - MAX(L13, I13) + 1) -> 30 | L13: 45231 | M13: 45260 | N13: =ROUNDUP(K13/30*320,0) -> 320 | O13: =N13*5 -> 1600 | P13: =N13+O13 -> 1920
A14: FAA | B14: 4320 | C14: FS | D14: Atif Nawaz | E14: 4700E740695 | F14: 38404-7428636-7 | H14: 36399 | I14: 45229 | K14: =MAX(0, MIN(M14, J14) - MAX(L14, I14) + 1) -> 30 | L14: 45231 | M14: 45260 | N14: =ROUNDUP(K14/30*320,0) -> 320 | O14: =N14*5 -> 1600 | P14: =N14+O14 -> 1920
A15: FAA | B15: 4320 | C15: FS | D15: Basit Afraz | E15: 4700C703310 | F15: 37405-8019865-5 | H15: 34601 | I15: 44986 | K15: =MAX(0, MIN(M15, J15) - MAX(L15, I15) + 1) -> 30 | L15: 45231 | M15: 45260 | N15: =ROUNDUP(K15/30*320,0) -> 320 | O15: =N15*5 -> 1600 | P15: =N15+O15 -> 1920
A16: FAA | B16: 4320 | C16: FS | D16: Elaf Hassan | E16: 4700I723958 | F16: 36302-4009333-7 | H16: 37244 | I16: 45173 | K16: =MAX(0, MIN(M16, J16) - MAX(L16, I16) + 1) -> 30 | L16: 45231 | M16: 45260 | N16: =ROUNDUP(K16/30*320,0) -> 320 | O16: =N16*5 -> 1600 | P16: =N16+O16 -> 1920
A17: FAA | B17: 4320 | C17: FS | D17: Faizan Khan | E17: 4700C662124 | F17: 16204-0388636-3 | H17: 35704 | I17: 44760 | K17: =MAX(0, MIN(M17, J17) - MAX(L17, I17) + 1) -> 30 | L17: 45231 | M17: 45260 | N17: =ROUNDUP(K17/30*320,0) -> 320 | O17: =N17*5 -> 1600 | P17: =N17+O17 -> 1920
A18: FAA | B18: 4320 | C18: FS | D18: Hamza Ahmad | E18: 4700I678608 | F18: 37405-6689341-9 | H18: 36246 | I18: 44851 | K18: =MAX(0, MIN(M18, J18) - MAX(L18, I18) + 1) -> 30 | L18: 45231 | M18: 45260 | N18: =ROUNDUP(K18/30*320,0) -> 320 | O18: =N18*5 -> 1600 | P18: =N18+O18 -> 1920
A19: FAA | B19: 4320 | C19: FS | D19: Hamza Ali Khan | E19: 4700B690429 | F19: 37405-5700118-7 | H19: 35606 | I19: 44896 | K19: =MAX(0, MIN(M19, J19) - MAX(L19, I19) + 1) -> 30 | L19: 45231 | M19: 45260 | N19: =ROUNDUP(K19/30*320,0) -> 320 | O19: =N19*5 -> 1600 | P19: =N19+O19 -> 1920
A20: FAA | B20: 4320 | C20: FS | D20: Hira Farooq | E20: 4700B703311 | F20: 61101-2625195-8 | H20: 34973 | I20: 44986 | K20: =MAX(0, MIN(M20, J20) - MAX(L20, I20) + 1) -> 30 | L20: 45231 | M20: 45260 | N20: =ROUNDUP(K20/30*320,0) -> 320 | O20: =N20*5 -> 1600 | P20: =N20+O20 -> 1920
A21: FAA | B21: 4320 | C21: FS | D21: Ibrahim Shah | E21: 4700G658260 | F21: 35201-2147689-9 | H21: 36891 | I21: 44739 | K21: =MAX(0, MIN(M21, J21) - MAX(L21, I21) + 1) -> 30 | L21: 45231 | M21: 45260 | N21: =ROUNDUP(K21/30*320,0) -> 320 | O21: =N21*5 -> 1600 | P21: =N21+O21 -> 1920
A22: FAA | B22: 4320 | C22: FS | D22: Jalees Mukarram | E22: 4700G638367 | F22: 31201-9892348-9 | H22: 37210 | I22: 44125 | K22: =MAX(0, MIN(M22, J22) - MAX(L22, I22) + 1) -> 30 | L22: 45231 | M22: 45260 | N22: =ROUNDUP(K22/30*320,0) -> 320 | O22: =N22*5 -> 1600 | P22: =N22+O22 -> 1920
A23: FAA | B23: 4320 | C23: FS | D23: Khadija Umer | E23: 4700A710848 | F23: 31202-4982058-2 | H23: 36401 | I23: 45096 | K23: =MAX(0, MIN(M23, J23) - MAX(L23, I23) + 1) -> 30 | L23: 45231 | M23: 45260 | N23: =ROUNDUP(K23/30*320,0) -> 320 | O23: =N23*5 -> 1600 | P23: =N23+O23 -> 1920
A24: FAA | B24: 4320 | C24: FS | D24: Laiba Imran | E24: 4700H684977 | F24: 37405-8102020-8 | H24: 36113 | I24: 44866 | K24: =MAX(0, MIN(M24, J24) - MAX(L24, I24) + 1) -> 30 | L24: 45231 | M24: 45260 | N24: =ROUNDUP(K24/30*320,0) -> 320 | O24: =N24*5 -> 1600 | P24: =N24+O24 -> 1920
... A26: FAA | B26: 4320 | C26: FS | D26: Muaaz Arshad | E26: 4100C164358 | F26: 34101-0197233-1 | H26: 33917 | I26: 45166 | K26: =MAX(0, MIN(M26, J26) - MAX(L26, I26) + 1) -> 30 | L26: 45231 | M26: 45260 | N26: =ROUNDUP(K26/30*320,0) -> 320 | O26: =N26*5 -> 1600 | P26: =N26+O26 -> 1920
A27: FAA | B27: 4320 | C27: FS | D27: Muhaimin Khan | E27: 4700E763936 | F27: 34101-6716758-6 | H27: 36502 | I27: 45098 | J27: 45246 | K27: =MAX(0, MIN(M27, J27) - MAX(L27, I27) + 1) -> 16 | L27: 45231 | M27: 45260 | N27: =ROUNDUP(K27/30*320,0) -> 171 | O27: =N27*5 -> 855 | P27: =N27+O27 -> 1026
A28: FAA | B28: 4320 | C28: FS | D28: Muhammad Abdullah Salam | E28: 4700G697010 | F28: 17301-7752570-9 | H28: 36690 | I28: 44938 | K28: =MAX(0, MIN(M28, J28) - MAX(L28, I28) + 1) -> 30 | L28: 45231 | M28: 45260 | N28: =ROUNDUP(K28/30*320,0) -> 320 | O28: =N28*5 -> 1600 | P28: =N28+O28 -> 1920
A29: FAA | B29: 4320 | C29: FS | D29: Muhammad Abubakar | E29: 4700H723959 | F29: 35201-8046049-1 | H29: 37240 | I29: 45176 | K29: =MAX(0, MIN(M29, J29) - MAX(L29, I29) + 1) -> 30 | L29: 45231 | M29: 45260 | N29: =ROUNDUP(K29/30*320,0) -> 320 | O29: =N29*5 -> 1600 | P29: =N29+O29 -> 1920
A30: FAA | B30: 4320 | C30: FS | D30: Muhammad Arham | E30: 4700J673932 | F30: 36103-7439746-1 | H30: 37136 | I30: 45201 | K30: =MAX(0, MIN(M30, J30) - MAX(L30, I30) + 1) -> 30 | L30: 45231 | M30: 45260 | N30: =ROUNDUP(K30/30*320,0) -> 320 | O30: =N30*5 -> 1600 | P30: =N30+O30 -> 1920
A31: FAA | B31: 4320 | C31: FS | D31: Muhammad Asadullah Shahid | E31: 4700G581544 | F31: 36603-1234883-1 | H31: 35943 | I31: 45215 | K31: =MAX(0, MIN(M31, J31) - MAX(L31, I31) + 1) -> 30 | L31: 45231 | M31: 45260 | N31: =ROUNDUP(K31/30*320,0) -> 320 | O31: =N31*5 -> 1600 | P31: =N31+O31 -> 1920
A32: FAA | B32: 4320 | C32: FS | D32: Muhammad Hammad Maqsood | E32: 4700A703312 | F32: 37405-2794891-9 | H32: 36898 | I32: 44988 | K32: =MAX(0, MIN(M32, J32) - MAX(L32, I32) + 1) -> 30 | L32: 45231 | M32: 45260 | N32: =ROUNDUP(K32/30*320,0) -> 320 | O32: =N32*5 -> 1600 | P32: =N32+O32 -> 1920
A33: FAA | B33: 4320 | C33: FS | D33: Muhammad Hamza | E33: 4600F317513 | F33: 61101-4668132-7 | H33: 35159 | I33: 45078 | K33: =MAX(0, MIN(M33, J33) - MAX(L33, I33) + 1) -> 30 | L33: 45231 | M33: 45260 | N33: =ROUNDUP(K33/30*320,0) -> 320 | O33: =N33*5 -> 1600 | P33: =N33+O33 -> 1920
A34: FAA | B34: 4320 | C34: FS | D34: Muhammad Hassan Shakeel | E34: 4700H690431 | F34: 35402-2593513-5 | H34: 36794 | I34: 44915 | K34: =MAX(0, MIN(M34, J34) - MAX(L34, I34) + 1) -> 30 | L34: 45231 | M34: 45260 | N34: =ROUNDUP(K34/30*320,0) -> 320 | O34: =N34*5 -> 1600 | P34: =N34+O34 -> 1920
A35: FAA | B35: 4320 | C35: FS | D35: Muhammad Ibrahim | E35: 4700C720948 | F35: 31101-0776303-7 | H35: 37149 | I35: 45124 | K35: =MAX(0, MIN(M35, J35) - MAX(L35, I35) + 1) -> 30 | L35: 45231 | M35: 45260 | N35: =ROUNDUP(K35/30*320,0) -> 320 | O35: =N35*5 -> 1600 | P35: =N35+O35 -> 1920
A36: FAA | B36: 4320 | C36: FS | D36: Muhammad Mutahhar | E36: 3300E326308 | F36: 42301-3092028-3 | H36: 35767 | I36: 45117 | K36: =MAX(0, MIN(M36, J36) - MAX(L36, I36) + 1) -> 30 | L36: 45231 | M36: 45260 | N36: =ROUNDUP(K36/30*320,0) -> 320 | O36: =N36*5 -> 1600 | P36: =N36+O36 -> 1920
A37: FAA | B37: 4320 | C37: FS | D37: Muhammad Nabeel Asif | E37: 0800I431358 | F37: 42101-1217952-3 | H37: 34503 | I37: 45246 | K37: =MAX(0, MIN(M37, J37) - MAX(L37, I37) + 1) -> 15 | L37: 45231 | M37: 45260 | N37: =ROUNDUP(K37/30*320,0) -> 160 | O37: =N37*5 -> 800 | P37: =N37+O37 -> 960
A38: FAA | B38: 4320 | C38: FS | D38: Muhammad Saad Tariq | E38: 4700D679730 | F38: 61101-0817777-7 | H38: 36207 | I38: 45054 | K38: =MAX(0, MIN(M38, J38) - MAX(L38, I38) + 1) -> 30 | L38: 45231 | M38: 45260 | N38: =ROUNDUP(K38/30*320,0) -> 320 | O38: =N38*5 -> 1600 | P38: =N38+O38 -> 1920
A39: FAA | B39: 4320 | C39: FS | D39: Muhammad Umair | E39: 4700A700796 | F39: 42501-3911861-7 | H39: 36480 | I39: 44970 | J39: 45260 | K39: =MAX(0, MIN(M39, J39) - MAX(L39, I39) + 1) -> 30 | L39: 45231 | M39: 45260 | N39: =ROUNDUP(K39/30*320,0) -> 320 | O39: =N39*5 -> 1600 | P39: =N39+O39 -> 1920
A40: FAA | B40: 4320 | C40: FS | D40: Muhammad Wajahat | E40: 4700A618216 | F40: 32203-2007547-1 | H40: 36768 | I40: 44888 | K40: =MAX(0, MIN(M40, J40) - MAX(L40, I40) + 1) -> 30 | L40: 45231 | M40: 45260 | N40: =ROUNDUP(K40/30*320,0) -> 320 | O40: =N40*5 -> 1600 | P40: =N40+O40 -> 1920
A41: FAA | B41: 4320 | C41: FS | D41: Muhammad Waleed Imran | E41: 4700J724945 | F41: 35201-8352529-1 | H41: 36074 | I41: 45180 | J41: 45247 | K41: =MAX(0, MIN(M41, J41) - MAX(L41, I41) + 1) -> 17 | L41: 45231 | M41: 45260 | N41: =ROUNDUP(K41/30*320,0) -> 182 | O41: =N41*5 -> 910 | P41: =N41+O41 -> 1092
A42: FAA | B42: 4320 | C42: FS | D42: Muhammad Zahab Ahmed | E42: 3600G329844 | F42: 31102-2135283-9 | H42: 34300 | I42: 45183 | K42: =MAX(0, MIN(M42, J42) - MAX(L42, I42) + 1) -> 30 | L42: 45231 | M42: 45260 | N42: =ROUNDUP(K42/30*320,0) -> 320 | O42: =N42*5 -> 1600 | P42: =N42+O42 -> 1920
A43: FAA | B43: 4320 | C43: FS | D43: Muhammad Zaid | E43: 4700B667971 | F43: 42000-5973098-1 | H43: 36118 | I43: 44783 | J43: 45243 | K43: =MAX(0, MIN(M43, J43) - MAX(L43, I43) + 1) -> 13 | L43: 45231 | M43: 45260 | N43: =ROUNDUP(K43/30*320,0) -> 139 | O43: =N43*5 -> 695 | P43: =N43+O43 -> 834
A44: FAA | B44: 4320 | C44: FS | D44: Naimal Imran | E44: 4700J662127 | F44: 35202-0754928-4 | H44: 36541 | I44: 44755 | K44: =MAX(0, MIN(M44, J44) - MAX(L44, I44) + 1) -> 30 | L44: 45231 | M44: 45260 | N44: =ROUNDUP(K44/30*320,0) -> 320 | O44: =N44*5 -> 1600 | P44: =N44+O44 -> 1920
A45: FAA | B45: 4320 | C45: FS | D45: Namra Akram | E45: 4700F444303 | F45: 61101-4919576-8 | H45: 34335 | I45: 45078 | K45: =MAX(0, MIN(M45, J45) - MAX(L45, I45) + 1) -> 30 | L45: 45231 | M45: 45260 | N45: =ROUNDUP(K45/30*320,0) -> 320 | O45: =N45*5 -> 1600 | P45: =N45+O45 -> 1920
A46: FAA | B46: 4320 | C46: FS | D46: Naveed Ahmed | E46: 4700H679736 | F46: 42201-5462974-9 | H46: 31014 | I46: 44805 | K46: =MAX(0, MIN(M46, J46) - MAX(L46, I46) + 1) -> 30 | L46: 45231 | M46: 45260 | N46: =ROUNDUP(K46/30*320,0) -> 320 | O46: =N46*5 -> 1600 | P46: =N46+O46 -> 1920
A47: FAA | B47: 4320 | C47: FS | D47: Qazi Shayan | E47: 4700A710864 | F47: 15402-0378555-7 | H47: 35150 | I47: 45079 | K47: =MAX(0, MIN(M47, J47) - MAX(L47, I47) + 1) -> 30 | L47: 45231 | M47: 45260 | N47: =ROUNDUP(K47/30*320,0) -> 320 | O47: =N47*5 -> 1600 | P47: =N47+O47 -> 1920
A48: FAA | B48: 4320 | C48: FS | D48: Rana Usair Sohail | E48: 0800H514678 | F48: 35202-2606196-5 | H48: 35779 | I48: 45176 | K48: =MAX(0, MIN(M48, J48) - MAX(L48, I48) + 1) -> 30 | L48: 45231 | M48: 45260 | N48: =ROUNDUP(K48/30*320,0) -> 320 | O48: =N48*5 -> 1600 | P48: =N48+O48 -> 1920
A49: FAA | B49: 4320 | C49: FS | D49: Rashid Iqbal | E49: 4700I703314 | F49: 37405-6880780-7 | H49: 34732 | I49: 44986 | K49: =MAX(0, MIN(M49, J49) - MAX(L49, I49) + 1) -> 30 | L49: 45231 | M49: 45260 | N49: =ROUNDUP(K49/30*320,0) -> 320 | O49: =N49*5 -> 1600 | P49: =N49+O49 -> 1920
A50: FAA | B50: 4320 | C50: FS | D50: Reyan Ahmad | E50: 3100D850990 | F50: 36101-6729437-9 | H50: 35772 | I50: 45222 | J50: 45246 | K50: =MAX(0, MIN(M50, J50) - MAX(L50, I50) + 1) -> 16 | L50: 45231 | M50: 45260 | N50: =ROUNDUP(K50/30*320,0) -> 171 | O50: =N50*5 -> 855 | P50: =N50+O50 -> 1026
A51: FAA | B51: 4320 | C51: FS | D51: Saad Ahmed | E51: 0800E406072 | F51: 35202-3107480-5 | H51: 33762 | I51: 45229 | K51: =MAX(0, MIN(M51, J51) - MAX(L51, I51) + 1) -> 31 | L51: 45261 | M51: 45291 | N51: =ROUNDUP(K51/31*320,0) -> 320 | O51: =N51*5 -> 1600 | P51: =N51+O51 -> 1920
A52: FAA | B52: 4320 | C52: FS | D52: Saad Aziz | E52: 4700J700797 | F52: 37405-7429064-1 | H52: 35931 | I52: 44958 | K52: =MAX(0, MIN(M52, J52) - MAX(L52, I52) + 1) -> 30 | L52: 45231 | M52: 45260 | N52: =ROUNDUP(K52/30*320,0) -> 320 | O52: =N52*5 -> 1600 | P52: =N52+O52 -> 1920
A53: FAA | B53: 4320 | C53: FS | D53: Sameet Asadullah | E53: 4700A667972 | F53: 33202-2965962-1 | H53: 37005 | I53: 44802 | K53: =MAX(0, MIN(M53, J53) - MAX(L53, I53) + 1) -> 30 | L53: 45231 | M53: 45260 | N53: =ROUNDUP(K53/30*320,0) -> 320 | O53: =N53*5 -> 1600 | P53: =N53+O53 -> 1920
A54: FAA | B54: 4320 | C54: FS | D54: Samman Mustafa | E54: 4700A688994 | F54: 37405-5204915-8 | H54: 36545 | I54: 45180 | J54: 45250 | K54: =MAX(0, MIN(M54, J54) - MAX(L54, I54) + 1) -> 20 | L54: 45231 | M54: 45260 | N54: =ROUNDUP(K54/30*320,0) -> 214 | O54: =N54*5 -> 1070 | P54: =N54+O54 -> 1284
A55: FAA | B55: 4320 | C55: FS | D55: Sana Sajjad Chaudhary | E55: 4700F740694 | F55: 37301-3885164-8 | H55: 36109 | I55: 45250 | K55: =MAX(0, MIN(M55, J55) - MAX(L55, I55) + 1) -> 11 | L55: 45231 | M55: 45260 | N55: =ROUNDUP(K55/30*320,0) -> 118 | O55: =N55*5 -> 590 | P55: =N55+O55 -> 708
A56: FAA | B56: 4320 | C56: FS | D56: Sana Tahir | E56: 4700D706561 | F56: 37103-2235902-2 | H56: 35976 | I56: 45042 | K56: =MAX(0, MIN(M56, J56) - MAX(L56, I56) + 1) -> 30 | L56: 45231 | M56: 45260 | N56: =ROUNDUP(K56/30*320,0) -> 320 | O56: =N56*5 -> 1600 | P56: =N56+O56 -> 1920
A57: FAA | B57: 4320 | C57: FS | D57: Shahnoor Ejaz | E57: 4700F703333 | F57: 42501-6125083-4 | H57: 36297 | I57: 45001 | K57: =MAX(0, MIN(M57, J57) - MAX(L57, I57) + 1) -> 30 | L57: 45231 | M57: 45260 | N57: =ROUNDUP(K57/30*320,0) -> 320 | O57: =N57*5 -> 1600 | P57: =N57+O57 -> 1920
A58: FAA | B58: 4320 | C58: FS | D58: Shahzad Farooq | E58: 4700G690432 | F58: 42501-8133748-7 | H58: 36979 | I58: 44907 | K58: =MAX(0, MIN(M58, J58) - MAX(L58, I58) + 1) -> 30 | L58: 45231 | M58: 45260 | N58: =ROUNDUP(K58/30*320,0) -> 320 | O58: =N58*5 -> 1600 | P58: =N58+O58 -> 1920
A59: FAA | B59: 4320 | C59: FS | D59: Shaiq Habib | E59: 0400C579124 | F59: 61101-1388832-7 | H59: 36421 | I59: 45208 | K59: =MAX(0, MIN(M59, J59) - MAX(L59, I59) + 1) -> 30 | L59: 45231 | M59: 45260 | N59: =ROUNDUP(K59/30*320,0) -> 320 | O59: =N59*5 -> 1600 | P59: =N59+O59 -> 1920
A60: FAA | B60: 4320 | C60: FS | D60: Shawal Fida | E60: 4700I700798 | F60: 16202-0438523-4 | H60: 36075 | I60: 44977 | K60: =MAX(0, MIN(M60, J60) - MAX(L60, I60) + 1) -> 30 | L60: 45231 | M60: 45260 | N60: =ROUNDUP(K60/30*320,0) -> 320 | O60: =N60*5 -> 1600 | P60: =N60+O60 -> 1920
A61: FAA | B61: 4320 | C61: FS | D61: Sheikh Muhammad Saad | E61: 3600D516452 | F61: 35202-2211437-9 | H61: 36089 | I61: 45195 | K61: =MAX(0, MIN(M61, J61) - MAX(L61, I61) + 1) -> 30 | L61: 45231 | M61: 45260 | N61: =ROUNDUP(K61/30*320,0) -> 320 | O61: =N61*5 -> 1600 | P61: =N61+O61 -> 1920
A62: FAA | B62: 4320 | C62: FS | D62: Subhana Yasin | E62: 4700E723960 | F62: 36502-1828819-0 | H62: 36574 | I62: 45187 | K62: =MAX(0, MIN(M62, J62) - MAX(L62, I62) + 1) -> 30 | L62: 45231 | M62: 45260 | N62: =ROUNDUP(K62/30*320,0) -> 320 | O62: =N62*5 -> 1600 | P62: =N62+O62 -> 1920
A63: FAA | B63: 4320 | C63: FS | D63: Syed Haider | E63: 3100E941643 | F63: 33102-5032259-9 | H63: 35115 | I63: 45194 | J63: 45247 | K63: =MAX(0, MIN(M63, J63) - MAX(L63, I63) + 1) -> 17 | L63: 45231 | M63: 45260 | N63: =ROUNDUP(K63/30*320,0) -> 182 | O63: =N63*5 -> 910 | P63: =N63+O63 -> 1092
A64: FAA | B64: 4320 | C64: FS | D64: Talha Arshad Malik | E64: 3600F372686 | F64: 37405-6378563-1 | H64: 33156 | I64: 44285 | K64: =MAX(0, MIN(M64, J64) - MAX(L64, I64) + 1) -> 30 | L64: 45231 | M64: 45260 | N64: =ROUNDUP(K64/30*320,0) -> 320 | O64: =N64*5 -> 1600 | P64: =N64+O64 -> 1920
A65: FAA | B65: 4320 | C65: FS | D65: Talha Jibran | E65: 4700G718997 | F65: 61101-8798575-7 | H65: 36096 | I65: 45174 | J65: 45251 | K65: =MAX(0, MIN(M65, J65) - MAX(L65, I65) + 1) -> 21 | L65: 45231 | M65: 45260 | N65: =ROUNDUP(K65/30*320,0) -> 224 | O65: =N65*5 -> 1120 | P65: =N65+O65 -> 1344
A66: FAA | B66: 4320 | C66: FS | D66: Tayyab Abbas | E66: 4700A685051 | F66: 17301-2752063-7 | H66: 36797 | I66: 44886 | K66: =MAX(0, MIN(M66, J66) - MAX(L66, I66) + 1) -> 30 | L66: 45231 | M66: 45260 | N66: =ROUNDUP(K66/30*320,0) -> 320 | O66: =N66*5 -> 1600 | P66: =N66+O66 -> 1920
A67: FAA | B67: 4320 | C67: FS | D67: Umaira Jabeen | E67: 3600J522091 | F67: 37104-5371430-8 | H67: 33769 | I67: 44816 | K67: =MAX(0, MIN(M67, J67) - MAX(L67, I67) + 1) -> 30 | L67: 45231 | M67: 45260 | N67: =ROUNDUP(K67/30*320,0) -> 320 | O67: =N67*5 -> 1600 | P67: =N67+O67 -> 1920
A68: FAA | B68: 4320 | C68: FS | D68: Umar Farooq | E68: 4700D723961 | F68: 36501-4241566-9 | H68: 36408 | I68: 45173 | K68: =MAX(0, MIN(M68, J68) - MAX(L68, I68) + 1) -> 30 | L68: 45231 | M68: 45260 | N68: =ROUNDUP(K68/30*320,0) -> 320 | O68: =N68*5 -> 1600 | P68: =N68+O68 -> 1920
A69: FAA | B69: 4320 | C69: FS | D69: Waleed Sadiq | E69: 4700C710870 | F69: 82101-6085499-3 | H69: 35818 | I69: 45089 | K69: =MAX(0, MIN(M69, J69) - MAX(L69, I69) + 1) -> 30 | L69: 45231 | M69: 45260 | N69: =ROUNDUP(K69/30*320,0) -> 320 | O69: =N69*5 -> 1600 | P69: =N69+O69 -> 1920
A70: FAA | B70: 4320 | C70: FS | D70: Zain Shahid | E70: 4700H700799 | F70: 36401-6591078-1 | H70: 36177 | I70: 44970 | K70: =MAX(0, MIN(M70, J70) - MAX(L70, I70) + 1) -> 30 | L70: 45231 | M70: 45260 | N70: =ROUNDUP(K70/30*320,0) -> 320 | O70: =N70*5 -> 1600 | P70: =N70+O70 -> 1920
A71: FAA | B71: 4320 | C71: FS | D71: Zoha Munir | E71: 0600G182381 | F71: 35202-9887337-8 | H71: 35743 | I71: 45222 | K71: =MAX(0, MIN(M71, J71) - MAX(L71, I71) + 1) -> 30 | L71: 45231 | M71: 45260 | N71: =ROUNDUP(K71/30*320,0) -> 320 | O71: =N71*5 -> 1600 | P71: =N71+O71 -> 1920
P72: =SUM(P2:P71) -> 123744

Sheet Dec-23
A1: EMP_AREA_CODE | B1: EMP_REG_SERIAL_NO | C1: EMP_SUB_AREA_CODE | D1: Name | E1: EOBI_NO | F1: CNIC | G1: NIC | H1: DOB | I1: DOJ | J1: DOE | K1: NO_OF_DAYS_WORKED | L1: From_Date | M1: To_Date | N1: Payment | O1: Employer Contribution | P1: Total EOBI
A2: FAA | B2: 4320 | C2: FS | D2: Aamir Nawaz | E2: 4700E637868 | F2: 14301-7981096-7 | H2: 32933 | I2: 45166 | J2: 45282 | K2: =MAX(0, MIN(M2, J2) - MAX(L2, I2) + 1) -> 22 | L2: 45261 | M2: 45291 | N2: =ROUNDUP(K2/31*320,0) -> 228 | O2: =N2*5 -> 1140 | P2: =N2+O2 -> 1368
A3: FAA | B3: 4320 | C3: FS | D3: Abdullah Bin Rashid | E3: 4700A705194 | F3: 61101-3101618-7 | H3: 36358 | I3: 45027 | K3: =MAX(0, MIN(M3, J3) - MAX(L3, I3) + 1) -> 31 | L3: 45261 | M3: 45291 | N3: =ROUNDUP(K3/31*320,0) -> 320 | O3: =N3*5 -> 1600 | P3: =N3+O3 -> 1920
A4: FAA | B4: 4320 | C4: FS | D4: Abdullah Rasheed | E4: 4700G688671 | F4: 37401-7271621-7 | H4: 36860 | I4: 45124 | K4: =MAX(0, MIN(M4, J4) - MAX(L4, I4) + 1) -> 31 | L4: 45261 | M4: 45291 | N4: =ROUNDUP(K4/31*320,0) -> 320 | O4: =N4*5 -> 1600 | P4: =N4+O4 -> 1920
A5: FAA | B5: 4320 | C5: FS | D5: Ahmad Hassan | E5: 4600D315335 | F5: 37405-4246562-3 | H5: 35997 | I5: 45061 | K5: =MAX(0, MIN(M5, J5) - MAX(L5, I5) + 1) -> 31 | L5: 45261 | M5: 45291 | N5: =ROUNDUP(K5/31*320,0) -> 320 | O5: =N5*5 -> 1600 | P5: =N5+O5 -> 1920
A6: FAA | B6: 4320 | C6: FS | D6: Ahmed Hussain | E6: 4800F063920 | F6: 38102-5707136-9 | H6: 36353 | I6: 45278 | K6: =MAX(0, MIN(M6, J6) - MAX(L6, I6) + 1) -> 14 | L6: 45261 | M6: 45291 | N6: =ROUNDUP(K6/31*320,0) -> 145 | O6: =N6*5 -> 725 | P6: =N6+O6 -> 870
A7: FAA | B7: 4320 | C7: FS | D7: Ali Aziz | E7: 4700J723957 | F7: 81202-8426576-7 | H7: 35053 | I7: 45173 | K7: =MAX(0, MIN(M7, J7) - MAX(L7, I7) + 1) -> 31 | L7: 45261 | M7: 45291 | N7: =ROUNDUP(K7/31*320,0) -> 320 | O7: =N7*5 -> 1600 | P7: =N7+O7 -> 1920
A8: FAA | B8: 4320 | C8: FS | D8: Ali Irfan | E8: 3100J940197 | F8: 35202-7336402-9 | H8: 36634 | I8: 45251 | K8: =MAX(0, MIN(M8, J8) - MAX(L8, I8) + 1) -> 31 | L8: 45261 | M8: 45291 | N8: =ROUNDUP(K8/31*320,0) -> 320 | O8: =N8*5 -> 1600 | P8: =N8+O8 -> 1920
A9: FAA | B9: 4320 | C9: FS | D9: Ali Nawaz Channa | E9: 0800E397265 | F9: 42201-8465990-5 | H9: 33408 | I9: 45078 | K9: =MAX(0, MIN(M9, J9) - MAX(L9, I9) + 1) -> 31 | L9: 45261 | M9: 45291 | N9: =ROUNDUP(K9/31*320,0) -> 320 | O9: =N9*5 -> 1600 | P9: =N9+O9 -> 1920
A10: FAA | B10: 4320 | C10: FS | D10: Alina Mubarik | E10: 4700C710820 | F10: 61101-5318332-4 | H10: 35983 | I10: 45082 | K10: =MAX(0, MIN(M10, J10) - MAX(L10, I10) + 1) -> 31 | L10: 45261 | M10: 45291 | N10: =ROUNDUP(K10/31*320,0) -> 320 | O10: =N10*5 -> 1600 | P10: =N10+O10 -> 1920
A11: FAA | B11: 4320 | C11: FS | D11: Altamash Shaban | E11: 4700G469815 | F11: 37405-5322814-9 | H11: 33048 | I11: 45250 | K11: =MAX(0, MIN(M11, J11) - MAX(L11, I11) + 1) -> 31 | L11: 45261 | M11: 45291 | N11: =ROUNDUP(K11/31*320,0) -> 320 | O11: =N11*5 -> 1600 | P11: =N11+O11 -> 1920
A12: FAA | B12: 4320 | C12: FS | D12: Asim Latif | E12: 4700A658224 | F12: 33302-5158556-5 | H12: 37370 | I12: 44739 | K12: =MAX(0, MIN(M12, J12) - MAX(L12, I12) + 1) -> 31 | L12: 45261 | M12: 45291 | N12: =ROUNDUP(K12/31*320,0) -> 320 | O12: =N12*5 -> 1600 | P12: =N12+O12 -> 1920
A13: FAA | B13: 4320 | C13: FS | D13: Atif Nawaz | E13: 4700E740695 | F13: 38404-7428636-7 | H13: 36399 | I13: 45229 | K13: =MAX(0, MIN(M13, J13) - MAX(L13, I13) + 1) -> 31 | L13: 45261 | M13: 45291 | N13: =ROUNDUP(K13/31*320,0) -> 320 | O13: =N13*5 -> 1600 | P13: =N13+O13 -> 1920
A14: FAA | B14: 4320 | C14: FS | D14: Basit Afraz | E14: 4700C703310 | F14: 37405-8019865-5 | H14: 34601 | I14: 44986 | K14: =MAX(0, MIN(M14, J14) - MAX(L14, I14) + 1) -> 31 | L14: 45261 | M14: 45291 | N14: =ROUNDUP(K14/31*320,0) -> 320 | O14: =N14*5 -> 1600 | P14: =N14+O14 -> 1920
A15: FAA | B15: 4320 | C15: FS | D15: Elaf Hassan | E15: 4700I723958 | F15: 36302-4009333-7 | H15: 37244 | I15: 45173 | J15: 45291 | K15: =MAX(0, MIN(M15, J15) - MAX(L15, I15) + 1) -> 31 | L15: 45261 | M15: 45291 | N15: =ROUNDUP(K15/31*320,0) -> 320 | O15: =N15*5 -> 1600 | P15: =N15+O15 -> 1920
A16: FAA | B16: 4320 | C16: FS | D16: Faiza Khan | E16: 4700J710823 | F16: 61101-0776147-2 | H16: 37322 | I16: 45261 | K16: =MAX(0, MIN(M16, J16) - MAX(L16, I16) + 1) -> 31 | L16: 45261 | M16: 45291 | N16: =ROUNDUP(K16/31*320,0) -> 320 | O16: =N16*5 -> 1600 | P16: =N16+O16 -> 1920
A17: FAA | B17: 4320 | C17: FS | D17: Faizan Khan | E17: 4700C662124 | F17: 16204-0388636-3 | H17: 35704 | I17: 44760 | K17: =MAX(0, MIN(M17, J17) - MAX(L17, I17) + 1) -> 31 | L17: 45261 | M17: 45291 | N17: =ROUNDUP(K17/31*320,0) -> 320 | O17: =N17*5 -> 1600 | P17: =N17+O17 -> 1920
A18: FAA | B18: 4320 | C18: FS | D18: Hamza Ahmad | E18: 4700I678608 | F18: 37405-6689341-9 | H18: 36246 | I18: 44851 | K18: =MAX(0, MIN(M18, J18) - MAX(L18, I18) + 1) -> 31 | L18: 45261 | M18: 45291 | N18: =ROUNDUP(K18/31*320,0) -> 320 | O18: =N18*5 -> 1600 | P18: =N18+O18 -> 1920
A19: FAA | B19: 4320 | C19: FS | D19: Hamza Ali Khan | E19: 4700B690429 | F19: 37405-5700118-7 | H19: 35606 | I19: 44896 | K19: =MAX(0, MIN(M19, J19) - MAX(L19, I19) + 1) -> 31 | L19: 45261 | M19: 45291 | N19: =ROUNDUP(K19/31*320,0) -> 320 | O19: =N19*5 -> 1600 | P19: =N19+O19 -> 1920
A20: FAA | B20: 4320 | C20: FS | D20: Hira Farooq | E20: 4700B703311 | F20: 61101-2625195-8 | H20: 34973 | I20: 44986 | K20: =MAX(0, MIN(M20, J20) - MAX(L20, I20) + 1) -> 31 | L20: 45261 | M20: 45291 | N20: =ROUNDUP(K20/31*320,0) -> 320 | O20: =N20*5 -> 1600 | P20: =N20+O20 -> 1920
A21: FAA | B21: 4320 | C21: FS | D21: Ibrahim Shah | E21: 4700G658260 | F21: 35201-2147689-9 | H21: 36891 | I21: 44739 | K21: =MAX(0, MIN(M21, J21) - MAX(L21, I21) + 1) -> 31 | L21: 45261 | M21: 45291 | N21: =ROUNDUP(K21/31*320,0) -> 320 | O21: =N21*5 -> 1600 | P21: =N21+O21 -> 1920
A22: FAA | B22: 4320 | C22: FS | D22: Immar Karim | E22: 4700E720920 | F22: 43203-1564655-3 | H22: 37516 | I22: 45261 | K22: =MAX(0, MIN(M22, J22) - MAX(L22, I22) + 1) -> 31 | L22: 45261 | M22: 45291 | N22: =ROUNDUP(K22/31*320,0) -> 320 | O22: =N22*5 -> 1600 | P22: =N22+O22 -> 1920
A23: FAA | B23: 4320 | C23: FS | D23: Jalees Mukarram | E23: 4700G638367 | F23: 31201-9892348-9 | H23: 37210 | I23: 44125 | K23: =MAX(0, MIN(M23, J23) - MAX(L23, I23) + 1) -> 31 | L23: 45261 | M23: 45291 | N23: =ROUNDUP(K23/31*320,0) -> 320 | O23: =N23*5 -> 1600 | P23: =N23+O23 -> 1920
A24: FAA | B24: 4320 | C24: FS | D24: Khadija Umer | E24: 4700A710848 | F24: 31202-4982058-2 | H24: 36401 | I24: 45096 | K24: =MAX(0, MIN(M24, J24) - MAX(L24, I24) + 1) -> 31 | L24: 45261 | M24: 45291 | N24: =ROUNDUP(K24/31*320,0) -> 320 | O24: =N24*5 -> 1600 | P24: =N24+O24 -> 1920
A25: FAA | B25: 4320 | C25: FS | D25: Laiba Imran | E25: 4700H684977 | F25: 37405-8102020-8 | H25: 36113 | I25: 44866 | K25: =MAX(0, MIN(M25, J25) - MAX(L25, I25) + 1) -> 31 | L25: 45261 | M25: 45291 | N25: =ROUNDUP(K25/31*320,0) -> 320 | O25: =N25*5 -> 1600 | P25: =N25+O25 -> 1920
A26: FAA | B26: 4320 | C26: FS | D26: Mohammad Ehtasham Balland | E26: 4700D711914 | F26: 36302-5494206-1 | H26: 33737 | I26: 45139 | K26: =MAX(0, MIN(M26, J26) - MAX(L26, I26) + 1) -> 31 | L26: 45261 | M26: 45291 | N26: =ROUNDUP(K26/31*320,0) -> 320 | O26: =N26*5 -> 1600 | P26: =N26+O26 -> 1920
A27: FAA | B27: 4320 | C27: FS | D27: Muaaz Arshad | E27: 4100C164358 | F27: 34101-0197233-1 | H27: 33917 | I27: 45166 | K27: =MAX(0, MIN(M27, J27) - MAX(L27, I27) + 1) -> 31 | L27: 45261 | M27: 45291 | N27: =ROUNDUP(K27/31*320,0) -> 320 | O27: =N27*5 -> 1600 | P27: =N27+O27 -> 1920
... A55: FAA | B55: 4320 | C55: FS | D55: Shawal Fida | E55: 4700I700798 | F55: 16202-0438523-4 | H55: 36075 | I55: 44977 | K55: =MAX(0, MIN(M55, J55) - MAX(L55, I55) + 1) -> 31 | L55: 45261 | M55: 45291 | N55: =ROUNDUP(K55/31*320,0) -> 320 | O55: =N55*5 -> 1600 | P55: =N55+O55 -> 1920
A56: FAA | B56: 4320 | C56: FS | D56: Sheikh Muhammad Saad | E56: 3600D516452 | F56: 35202-2211437-9 | H56: 36089 | I56: 45195 | J56: 45282 | K56: =MAX(0, MIN(M56, J56) - MAX(L56, I56) + 1) -> 22 | L56: 45261 | M56: 45291 | N56: =ROUNDUP(K56/31*320,0) -> 228 | O56: =N56*5 -> 1140 | P56: =N56+O56 -> 1368
A57: FAA | B57: 4320 | C57: FS | D57: Subhana Yasin | E57: 4700E723960 | F57: 36502-1828819-0 | H57: 36574 | I57: 45187 | K57: =MAX(0, MIN(M57, J57) - MAX(L57, I57) + 1) -> 31 | L57: 45261 | M57: 45291 | N57: =ROUNDUP(K57/31*320,0) -> 320 | O57: =N57*5 -> 1600 | P57: =N57+O57 -> 1920
A58: FAA | B58: 4320 | C58: FS | D58: Talha Arshad Malik | E58: 3600F372686 | F58: 37405-6378563-1 | H58: 33156 | I58: 44285 | K58: =MAX(0, MIN(M58, J58) - MAX(L58, I58) + 1) -> 31 | L58: 45261 | M58: 45291 | N58: =ROUNDUP(K58/31*320,0) -> 320 | O58: =N58*5 -> 1600 | P58: =N58+O58 -> 1920
A59: FAA | B59: 4320 | C59: FS | D59: Tayyab Abbas | E59: 4700A685051 | F59: 17301-2752063-7 | H59: 36797 | I59: 44886 | K59: =MAX(0, MIN(M59, J59) - MAX(L59, I59) + 1) -> 31 | L59: 45261 | M59: 45291 | N59: =ROUNDUP(K59/31*320,0) -> 320 | O59: =N59*5 -> 1600 | P59: =N59+O59 -> 1920
A60: FAA | B60: 4320 | C60: FS | D60: Umaira Jabeen | E60: 3600J522091 | F60: 37104-5371430-8 | H60: 33769 | I60: 44816 | K60: =MAX(0, MIN(M60, J60) - MAX(L60, I60) + 1) -> 31 | L60: 45261 | M60: 45291 | N60: =ROUNDUP(K60/31*320,0) -> 320 | O60: =N60*5 -> 1600 | P60: =N60+O60 -> 1920
A61: FAA | B61: 4320 | C61: FS | D61: Umar Farooq | E61: 4700D723961 | F61: 36501-4241566-9 | H61: 36408 | I61: 45173 | K61: =MAX(0, MIN(M61, J61) - MAX(L61, I61) + 1) -> 31 | L61: 45261 | M61: 45291 | N61: =ROUNDUP(K61/31*320,0) -> 320 | O61: =N61*5 -> 1600 | P61: =N61+O61 -> 1920
A62: FAA | B62: 4320 | C62: FS | D62: Waleed Sadiq | E62: 4700C710870 | F62: 82101-6085499-3 | H62: 35818 | I62: 45089 | K62: =MAX(0, MIN(M62, J62) - MAX(L62, I62) + 1) -> 31 | L62: 45261 | M62: 45291 | N62: =ROUNDUP(K62/31*320,0) -> 320 | O62: =N62*5 -> 1600 | P62: =N62+O62 -> 1920
A63: FAA | B63: 4320 | C63: FS | D63: Zain Shahid | E63: 4700H700799 | F63: 36401-6591078-1 | H63: 36177 | I63: 44970 | J63: 45291 | K63: =MAX(0, MIN(M63, J63) - MAX(L63, I63) + 1) -> 31 | L63: 45261 | M63: 45291 | N63: =ROUNDUP(K63/31*320,0) -> 320 | O63: =N63*5 -> 1600 | P63: =N63+O63 -> 1920
A64: FAA | B64: 4320 | C64: FS | D64: Zoha Munir | E64: 0600G182381 | F64: 35202-9887337-8 | H64: 35743 | I64: 45222 | K64: =MAX(0, MIN(M64, J64) - MAX(L64, I64) + 1) -> 31 | L64: 45261 | M64: 45291 | N64: =ROUNDUP(K64/31*320,0) -> 320 | O64: =N64*5 -> 1600 | P64: =N64+O64 -> 1920
P65: =SUM(P2:P64) -> 117888

Sheet Jan-24
A1: EMP_AREA_CODE | B1: EMP_REG_SERIAL_NO | C1: EMP_SUB_AREA_CODE | D1: Name | E1: EOBI_NO | F1: CNIC | G1: NIC | H1: DOB | I1: DOJ | J1: DOE | K1: NO_OF_DAYS_WORKED | L1: From_Date | M1: To_Date | N1: Payment | O1: Employer Contribution | P1: Total EOBI
A2: FAA | B2: 4320 | C2: FS | D2: Abdul Hameed | E2: 4700J763957 | F2: 17301-6508006-1 | H2: 36617 | I2: 45299 | K2: =MAX(0, MIN(M2, J2) - MAX(L2, I2) + 1) -> 24 | L2: 45292 | M2: 45322 | N2: =ROUNDUP(K2/31*320,0) -> 248 | O2: =N2*5 -> 1240 | P2: =N2+O2 -> 1488
A3: FAA | B3: 4320 | C3: FS | D3: Abdullah Bin Rashid | E3: 4700A705194 | F3: 61101-3101618-7 | H3: 36358 | I3: 45027 | K3: =MAX(0, MIN(M3, J3) - MAX(L3, I3) + 1) -> 31 | L3: 45292 | M3: 45322 | N3: =ROUNDUP(K3/31*320,0) -> 320 | O3: =N3*5 -> 1600 | P3: =N3+O3 -> 1920
A4: FAA | B4: 4320 | C4: FS | D4: Abdullah Rasheed | E4: 4700G688671 | F4: 37401-7271621-7 | H4: 36860 | I4: 45124 | K4: =MAX(0, MIN(M4, J4) - MAX(L4, I4) + 1) -> 31 | L4: 45292 | M4: 45322 | N4: =ROUNDUP(K4/31*320,0) -> 320 | O4: =N4*5 -> 1600 | P4: =N4+O4 -> 1920
A5: FAA | B5: 4320 | C5: FS | D5: Ahmad Hassan | E5: 4600D315335 | F5: 37405-4246562-3 | H5: 35997 | I5: 45061 | K5: =MAX(0, MIN(M5, J5) - MAX(L5, I5) + 1) -> 31 | L5: 45292 | M5: 45322 | N5: =ROUNDUP(K5/31*320,0) -> 320 | O5: =N5*5 -> 1600 | P5: =N5+O5 -> 1920
A6: FAA | B6: 4320 | C6: FS | D6: Ahmed Hussain | E6: 4800F063920 | F6: 38102-5707136-9 | H6: 36353 | I6: 45278 | K6: =MAX(0, MIN(M6, J6) - MAX(L6, I6) + 1) -> 31 | L6: 45292 | M6: 45322 | N6: =ROUNDUP(K6/31*320,0) -> 320 | O6: =N6*5 -> 1600 | P6: =N6+O6 -> 1920
A7: FAA | B7: 4320 | C7: FS | D7: Ali Aziz | E7: 4700J723957 | F7: 81202-8426576-7 | H7: 35053 | I7: 45173 | J7: 45322 | K7: =MAX(0, MIN(M7, J7) - MAX(L7, I7) + 1) -> 31 | L7: 45292 | M7: 45322 | N7: =ROUNDUP(K7/31*320,0) -> 320 | O7: =N7*5 -> 1600 | P7: =N7+O7 -> 1920
A8: FAA | B8: 4320 | C8: FS | D8: Ali Irfan | E8: 3100J940197 | F8: 35202-7336402-9 | H8: 36634 | I8: 45251 | K8: =MAX(0, MIN(M8, J8) - MAX(L8, I8) + 1) -> 31 | L8: 45292 | M8: 45322 | N8: =ROUNDUP(K8/31*320,0) -> 320 | O8: =N8*5 -> 1600 | P8: =N8+O8 -> 1920
A9: FAA | B9: 4320 | C9: FS | D9: Ali Nawaz Channa | E9: 0800E397265 | F9: 42201-8465990-5 | H9: 33408 | I9: 45078 | K9: =MAX(0, MIN(M9, J9) - MAX(L9, I9) + 1) -> 31 | L9: 45292 | M9: 45322 | N9: =ROUNDUP(K9/31*320,0) -> 320 | O9: =N9*5 -> 1600 | P9: =N9+O9 -> 1920
A10: FAA | B10: 4320 | C10: FS | D10: Alina Mubarik | E10: 4700C710820 | F10: 61101-5318332-4 | H10: 35983 | I10: 45082 | K10: =MAX(0, MIN(M10, J10) - MAX(L10, I10) + 1) -> 31 | L10: 45292 | M10: 45322 | N10: =ROUNDUP(K10/31*320,0) -> 320 | O10: =N10*5 -> 1600 | P10: =N10+O10 -> 1920
A11: FAA | B11: 4320 | C11: FS | D11: Altamash Shaban | E11: 4700G469815 | F11: 37405-5322814-9 | H11: 33048 | I11: 45250 | K11: =MAX(0, MIN(M11, J11) - MAX(L11, I11) + 1) -> 31 | L11: 45292 | M11: 45322 | N11: =ROUNDUP(K11/31*320,0) -> 320 | O11: =N11*5 -> 1600 | P11: =N11+O11 -> 1920
A12: FAA | B12: 4320 | C12: FS | D12: Anamil Mehtab | E12: 4700A710822 | F12: 37103-6819266-4 | H12: 37398 | I12: 45292 | K12: =MAX(0, MIN(M12, J12) - MAX(L12, I12) + 1) -> 31 | L12: 45292 | M12: 45322 | N12: =ROUNDUP(K12/31*320,0) -> 320 | O12: =N12*5 -> 1600 | P12: =N12+O12 -> 1920
A13: FAA | B13: 4320 | C13: FS | D13: Asim Latif | E13: 4700A658224 | F13: 33302-5158556-5 | H13: 37370 | I13: 44739 | K13: =MAX(0, MIN(M13, J13) - MAX(L13, I13) + 1) -> 31 | L13: 45292 | M13: 45322 | N13: =ROUNDUP(K13/31*320,0) -> 320 | O13: =N13*5 -> 1600 | P13: =N13+O13 -> 1920
A14: FAA | B14: 4320 | C14: FS | D14: Atif Nawaz | E14: 4700E740695 | F14: 38404-7428636-7 | H14: 36399 | I14: 45229 | K14: =MAX(0, MIN(M14, J14) - MAX(L14, I14) + 1) -> 31 | L14: 45292 | M14: 45322 | N14: =ROUNDUP(K14/31*320,0) -> 320 | O14: =N14*5 -> 1600 | P14: =N14+O14 -> 1920
A15: FAA | B15: 4320 | C15: FS | D15: Basit Afraz | E15: 4700C703310 | F15: 37405-8019865-5 | H15: 34601 | I15: 44986 | K15: =MAX(0, MIN(M15, J15) - MAX(L15, I15) + 1) -> 31 | L15: 45292 | M15: 45322 | N15: =ROUNDUP(K15/31*320,0) -> 320 | O15: =N15*5 -> 1600 | P15: =N15+O15 -> 1920
A16: FAA | B16: 4320 | C16: FS | D16: Faiza Khan | E16: 4700J710823 | F16: 61101-0776147-2 | H16: 37322 | I16: 45096 | K16: =MAX(0, MIN(M16, J16) - MAX(L16, I16) + 1) -> 31 | L16: 45292 | M16: 45322 | N16: =ROUNDUP(K16/31*320,0) -> 320 | O16: =N16*5 -> 1600 | P16: =N16+O16 -> 1920
A17: FAA | B17: 4320 | C17: FS | D17: Faizan Khan | E17: 4700C662124 | F17: 16204-0388636-3 | H17: 35704 | I17: 44760 | K17: =MAX(0, MIN(M17, J17) - MAX(L17, I17) + 1) -> 31 | L17: 45292 | M17: 45322 | N17: =ROUNDUP(K17/31*320,0) -> 320 | O17: =N17*5 -> 1600 | P17: =N17+O17 -> 1920
A18: FAA | B18: 4320 | C18: FS | D18: Hamza Ahmad | E18: 4700I678608 | F18: 37405-6689341-9 | H18: 36246 | I18: 44851 | K18: =MAX(0, MIN(M18, J18) - MAX(L18, I18) + 1) -> 31 | L18: 45292 | M18: 45322 | N18: =ROUNDUP(K18/31*320,0) -> 320 | O18: =N18*5 -> 1600 | P18: =N18+O18 -> 1920
A19: FAA | B19: 4320 | C19: FS | D19: Hamza Ali Khan | E19: 4700B690429 | F19: 37405-5700118-7 | H19: 35606 | I19: 44896 | K19: =MAX(0, MIN(M19, J19) - MAX(L19, I19) + 1) -> 31 | L19: 45292 | M19: 45322 | N19: =ROUNDUP(K19/31*320,0) -> 320 | O19: =N19*5 -> 1600 | P19: =N19+O19 -> 1920
... A25: FAA | B25: 4320 | C25: FS | D25: Khadija Umer | E25: 4700A710848 | F25: 31202-4982058-2 | H25: 36401 | I25: 45096 | K25: =MAX(0, MIN(M25, J25) - MAX(L25, I25) + 1) -> 31 | L25: 45292 | M25: 45322 | N25: =ROUNDUP(K25/31*320,0) -> 320 | O25: =N25*5 -> 1600 | P25: =N25+O25 -> 1920
A26: FAA | B26: 4320 | C26: FS | D26: Laiba Imran | E26: 4700H684977 | F26: 37405-8102020-8 | H26: 36113 | I26: 44866 | J26: 45299 | K26: =MAX(0, MIN(M26, J26) - MAX(L26, I26) + 1) -> 8 | L26: 45292 | M26: 45322 | N26: =ROUNDUP(K26/31*320,0) -> 83 | O26: =N26*5 -> 415 | P26: =N26+O26 -> 498
A27: FAA | B27: 4320 | C27: FS | D27: Mirza Zain Ali Nasir | E27: 4700I764093 | F27: 35201-1057763-3 | H27: 36769 | I27: 45313 | J27: 45415 | K27: =MAX(0, MIN(M27, J27) - MAX(L27, I27) + 1) -> 10 | L27: 45292 | M27: 45322 | N27: =ROUNDUP(K27/31*320,0) -> 104 | O27: =N27*5 -> 520 | P27: =N27+O27 -> 624
A28: FAA | B28: 4320 | C28: FS | D28: Mohammad Ehtasham Balland | E28: 4700D711914 | F28: 36302-5494206-1 | H28: 33737 | I28: 45139 | K28: =MAX(0, MIN(M28, J28) - MAX(L28, I28) + 1) -> 31 | L28: 45292 | M28: 45322 | N28: =ROUNDUP(K28/31*320,0) -> 320 | O28: =N28*5 -> 1600 | P28: =N28+O28 -> 1920
A29: FAA | B29: 4320 | C29: FS | D29: Muaaz Arshad | E29: 4100C164358 | F29: 34101-0197233-1 | H29: 33917 | I29: 45166 | J29: 45321 | K29: =MAX(0, MIN(M29, J29) - MAX(L29, I29) + 1) -> 30 | L29: 45292 | M29: 45322 | N29: =ROUNDUP(K29/31*320,0) -> 310 | O29: =N29*5 -> 1550 | P29: =N29+O29 -> 1860
A30: FAA | B30: 4320 | C30: FS | D30: Muhammad Abdullah Salam | E30: 4700G697010 | F30: 17301-7752570-9 | H30: 36690 | I30: 44938 | K30: =MAX(0, MIN(M30, J30) - MAX(L30, I30) + 1) -> 31 | L30: 45292 | M30: 45322 | N30: =ROUNDUP(K30/31*320,0) -> 320 | O30: =N30*5 -> 1600 | P30: =N30+O30 -> 1920
A31: FAA | B31: 4320 | C31: FS | D31: Muhammad Abubakar | E31: 4700H723959 | F31: 35201-8046049-1 | H31: 37240 | I31: 45176 | K31: =MAX(0, MIN(M31, J31) - MAX(L31, I31) + 1) -> 31 | L31: 45292 | M31: 45322 | N31: =ROUNDUP(K31/31*320,0) -> 320 | O31: =N31*5 -> 1600 | P31: =N31+O31 -> 1920
A32: FAA | B32: 4320 | C32: FS | D32: Muhammad Ali Kiyani | E32: 4700I483207 | F32: 61101-7478749-3 | H32: 35173 | I32: 45264 | K32: =MAX(0, MIN(M32, J32) - MAX(L32, I32) + 1) -> 31 | L32: 45292 | M32: 45322 | N32: =ROUNDUP(K32/31*320,0) -> 320 | O32: =N32*5 -> 1600 | P32: =N32+O32 -> 1920
A33: FAA | B33: 4320 | C33: FS | D33: Muhammad Arham | E33: 4700J673932 | F33: 36103-7439746-1 | H33: 37136 | I33: 45201 | K33: =MAX(0, MIN(M33, J33) - MAX(L33, I33) + 1) -> 31 | L33: 45292 | M33: 45322 | N33: =ROUNDUP(K33/31*320,0) -> 320 | O33: =N33*5 -> 1600 | P33: =N33+O33 -> 1920
A34: FAA | B34: 4320 | C34: FS | D34: Muhammad Asadullah Shahid | E34: 4700G581544 | F34: 36603-1234883-1 | H34: 35943 | I34: 45215 | K34: =MAX(0, MIN(M34, J34) - MAX(L34, I34) + 1) -> 31 | L34: 45292 | M34: 45322 | N34: =ROUNDUP(K34/31*320,0) -> 320 | O34: =N34*5 -> 1600 | P34: =N34+O34 -> 1920
A35: FAA | B35: 4320 | C35: FS | D35: Muhammad Hammad Maqsood | E35: 4700A703312 | F35: 37405-2794891-9 | H35: 36898 | I35: 44988 | K35: =MAX(0, MIN(M35, J35) - MAX(L35, I35) + 1) -> 31 | L35: 45292 | M35: 45322 | N35: =ROUNDUP(K35/31*320,0) -> 320 | O35: =N35*5 -> 1600 | P35: =N35+O35 -> 1920
A36: FAA | B36: 4320 | C36: FS | D36: Muhammad Hamza | E36: 4600F317513 | F36: 61101-4668132-7 | H36: 35159 | I36: 45078 | J36: 45322 | K36: =MAX(0, MIN(M36, J36) - MAX(L36, I36) + 1) -> 31 | L36: 45292 | M36: 45322 | N36: =ROUNDUP(K36/31*320,0) -> 320 | O36: =N36*5 -> 1600 | P36: =N36+O36 -> 1920
A37: FAA | B37: 4320 | C37: FS | D37: Muhammad Hassan Shakeel | E37: 4700H690431 | F37: 35402-2593513-5 | H37: 36794 | I37: 44915 | K37: =MAX(0, MIN(M37, J37) - MAX(L37, I37) + 1) -> 31 | L37: 45292 | M37: 45322 | N37: =ROUNDUP(K37/31*320,0) -> 320 | O37: =N37*5 -> 1600 | P37: =N37+O37 -> 1920
A38: FAA | B38: 4320 | C38: FS | D38: Muhammad Ibrahim | E38: 4700C720948 | F38: 31101-0776303-7 | H38: 37149 | I38: 45124 | K38: =MAX(0, MIN(M38, J38) - MAX(L38, I38) + 1) -> 31 | L38: 45292 | M38: 45322 | N38: =ROUNDUP(K38/31*320,0) -> 320 | O38: =N38*5 -> 1600 | P38: =N38+O38 -> 1920
A39: FAA | B39: 4320 | C39: FS | D39: Muhammad Nabeel Asif | E39: 0800I431358 | F39: 42101-1217952-3 | H39: 34503 | I39: 45246 | J39: 45338 | K39: =MAX(0, MIN(M39, J39) - MAX(L39, I39) + 1) -> 31 | L39: 45292 | M39: 45322 | N39: =ROUNDUP(K39/31*320,0) -> 320 | O39: =N39*5 -> 1600 | P39: =N39+O39 -> 1920
A40: FAA | B40: 4320 | C40: FS | D40: Muhammad Saad Tariq | E40: 4700D679730 | F40: 61101-0817777-7 | H40: 36207 | I40: 45054 | K40: =MAX(0, MIN(M40, J40) - MAX(L40, I40) + 1) -> 31 | L40: 45292 | M40: 45322 | N40: =ROUNDUP(K40/31*320,0) -> 320 | O40: =N40*5 -> 1600 | P40: =N40+O40 -> 1920
A41: FAA | B41: 4320 | C41: FS | D41: Muhammad Zahab Ahmed | E41: 3600G329844 | F41: 31102-2135283-9 | H41: 34300 | I41: 45183 | K41: =MAX(0, MIN(M41, J41) - MAX(L41, I41) + 1) -> 31 | L41: 45292 | M41: 45322 | N41: =ROUNDUP(K41/31*320,0) -> 320 | O41: =N41*5 -> 1600 | P41: =N41+O41 -> 1920
A42: FAA | B42: 4320 | C42: FS | D42: Naimal Imran | E42: 4700J662127 | F42: 35202-0754928-4 | H42: 36541 | I42: 44755 | K42: =MAX(0, MIN(M42, J42) - MAX(L42, I42) + 1) -> 31 | L42: 45292 | M42: 45322 | N42: =ROUNDUP(K42/31*320,0) -> 320 | O42: =N42*5 -> 1600 | P42: =N42+O42 -> 1920
A43: FAA | B43: 4320 | C43: FS | D43: Namra Akram | E43: 4700F444303 | F43: 61101-4919576-8 | H43: 34335 | I43: 45078 | K43: =MAX(0, MIN(M43, J43) - MAX(L43, I43) + 1) -> 31 | L43: 45292 | M43: 45322 | N43: =ROUNDUP(K43/31*320,0) -> 320 | O43: =N43*5 -> 1600 | P43: =N43+O43 -> 1920
A44: FAA | B44: 4320 | C44: FS | D44: Naveed Ahmed | E44: 4700H679736 | F44: 42201-5462974-9 | H44: 31014 | I44: 44805 | K44: =MAX(0, MIN(M44, J44) - MAX(L44, I44) + 1) -> 31 | L44: 45292 | M44: 45322 | N44: =ROUNDUP(K44/31*320,0) -> 320 | O44: =N44*5 -> 1600 | P44: =N44+O44 -> 1920
A45: FAA | B45: 4320 | C45: FS | D45: Nimra Zahid | E45: 4700G537391 | F45: 42201-1439506-4 | H45: 34522 | I45: 45292 | K45: =MAX(0, MIN(M45, J45) - MAX(L45, I45) + 1) -> 31 | L45: 45292 | M45: 45322 | N45: =ROUNDUP(K45/31*320,0) -> 320 | O45: =N45*5 -> 1600 | P45: =N45+O45 -> 1920
A46: FAA | B46: 4320 | C46: FS | D46: Qazi Shayan | E46: 4700A710864 | F46: 15402-0378555-7 | H46: 35150 | I46: 45079 | J46: 45322 | K46: =MAX(0, MIN(M46, J46) - MAX(L46, I46) + 1) -> 31 | L46: 45292 | M46: 45322 | N46: =ROUNDUP(K46/31*320,0) -> 320 | O46: =N46*5 -> 1600 | P46: =N46+O46 -> 1920
A47: FAA | B47: 4320 | C47: FS | D47: Rana Usair Sohail | E47: 0800H514678 | F47: 35202-2606196-5 | H47: 35779 | I47: 45176 | J47: 45317 | K47: =MAX(0, MIN(M47, J47) - MAX(L47, I47) + 1) -> 26 | L47: 45292 | M47: 45322 | N47: =ROUNDUP(K47/31*320,0) -> 269 | O47: =N47*5 -> 1345 | P47: =N47+O47 -> 1614
A48: FAA | B48: 4320 | C48: FS | D48: Rashid Iqbal | E48: 4700I703314 | F48: 37405-6880780-7 | H48: 34732 | I48: 44986 | K48: =MAX(0, MIN(M48, J48) - MAX(L48, I48) + 1) -> 31 | L48: 45292 | M48: 45322 | N48: =ROUNDUP(K48/31*320,0) -> 320 | O48: =N48*5 -> 1600 | P48: =N48+O48 -> 1920
A49: FAA | B49: 4320 | C49: FS | D49: Saad Ahmed | E49: 0800E406072 | F49: 35202-3107480-5 | H49: 33762 | I49: 45229 | K49: =MAX(0, MIN(M49, J49) - MAX(L49, I49) + 1) -> 31 | L49: 45261 | M49: 45291 | N49: =ROUNDUP(K49/31*320,0) -> 320 | O49: =N49*5 -> 1600 | P49: =N49+O49 -> 1920
A50: FAA | B50: 4320 | C50: FS | D50: Saad Aziz | E50: 4700J700797 | F50: 37405-7429064-1 | H50: 35931 | I50: 44958 | K50: =MAX(0, MIN(M50, J50) - MAX(L50, I50) + 1) -> 31 | L50: 45292 | M50: 45322 | N50: =ROUNDUP(K50/31*320,0) -> 320 | O50: =N50*5 -> 1600 | P50: =N50+O50 -> 1920
A51: FAA | B51: 4320 | C51: FS | D51: Saif Ullah | E51: 4700A764083 | F51: 61101-5764361-9 | H51: 37479 | I51: 45320 | K51: =MAX(0, MIN(M51, J51) - MAX(L51, I51) + 1) -> 3 | L51: 45292 | M51: 45322 | N51: =ROUNDUP(K51/31*320,0) -> 31 | O51: =N51*5 -> 155 | P51: =N51+O51 -> 186
A52: FAA | B52: 4320 | C52: FS | D52: Salman Khalid | E52: 3300B264525 | F52: 34603-0435168-5 | H52: 33003 | I52: 45313 | K52: =MAX(0, MIN(M52, J52) - MAX(L52, I52) + 1) -> 10 | L52: 45292 | M52: 45322 | N52: =ROUNDUP(K52/31*320,0) -> 104 | O52: =N52*5 -> 520 | P52: =N52+O52 -> 624
A53: FAA | B53: 4320 | C53: FS | D53: Sameet Asadullah | E53: 4700A667972 | F53: 33202-2965962-1 | H53: 37005 | I53: 44802 | J53: 45303 | K53: =MAX(0, MIN(M53, J53) - MAX(L53, I53) + 1) -> 12 | L53: 45292 | M53: 45322 | N53: =ROUNDUP(K53/31*320,0) -> 124 | O53: =N53*5 -> 620 | P53: =N53+O53 -> 744
A54: FAA | B54: 4320 | C54: FS | D54: Sana Sajjad Chaudhary | E54: 4700F740694 | F54: 37301-3885164-8 | H54: 36109 | I54: 45250 | K54: =MAX(0, MIN(M54, J54) - MAX(L54, I54) + 1) -> 31 | L54: 45292 | M54: 45322 | N54: =ROUNDUP(K54/31*320,0) -> 320 | O54: =N54*5 -> 1600 | P54: =N54+O54 -> 1920
A55: FAA | B55: 4320 | C55: FS | D55: Sana Tahir | E55: 4700D706561 | F55: 37103-2235902-2 | H55: 35976 | I55: 45042 | K55: =MAX(0, MIN(M55, J55) - MAX(L55, I55) + 1) -> 31 | L55: 45292 | M55: 45322 | N55: =ROUNDUP(K55/31*320,0) -> 320 | O55: =N55*5 -> 1600 | P55: =N55+O55 -> 1920
A56: FAA | B56: 4320 | C56: FS | D56: Shahnoor Ejaz | E56: 4700F703333 | F56: 42501-6125083-4 | H56: 36297 | I56: 45001 | K56: =MAX(0, MIN(M56, J56) - MAX(L56, I56) + 1) -> 31 | L56: 45292 | M56: 45322 | N56: =ROUNDUP(K56/31*320,0) -> 320 | O56: =N56*5 -> 1600 | P56: =N56+O56 -> 1920
A57: FAA | B57: 4320 | C57: FS | D57: Shahzad Farooq | E57: 4700G690432 | F57: 42501-8133748-7 | H57: 36979 | I57: 44907 | K57: =MAX(0, MIN(M57, J57) - MAX(L57, I57) + 1) -> 31 | L57: 45292 | M57: 45322 | N57: =ROUNDUP(K57/31*320,0) -> 320 | O57: =N57*5 -> 1600 | P57: =N57+O57 -> 1920
A58: FAA | B58: 4320 | C58: FS | D58: Shaiq Habib | E58: 0400C579124 | F58: 61101-1388832-7 | H58: 36421 | I58: 45208 | K58: =MAX(0, MIN(M58, J58) - MAX(L58, I58) + 1) -> 31 | L58: 45292 | M58: 45322 | N58: =ROUNDUP(K58/31*320,0) -> 320 | O58: =N58*5 -> 1600 | P58: =N58+O58 -> 1920
A59: FAA | B59: 4320 | C59: FS | D59: Shan Ahmad | E59: 4700C748360 | F59: 35202-9717455-5 | H59: 35447 | I59: 45273 | K59: =MAX(0, MIN(M59, J59) - MAX(L59, I59) + 1) -> 31 | L59: 45292 | M59: 45322 | N59: =ROUNDUP(K59/31*320,0) -> 320 | O59: =N59*5 -> 1600 | P59: =N59+O59 -> 1920
A60: FAA | B60: 4320 | C60: FS | D60: Shawal Fida | E60: 4700I700798 | F60: 16202-0438523-4 | H60: 36075 | I60: 44977 | K60: =MAX(0, MIN(M60, J60) - MAX(L60, I60) + 1) -> 31 | L60: 45292 | M60: 45322 | N60: =ROUNDUP(K60/31*320,0) -> 320 | O60: =N60*5 -> 1600 | P60: =N60+O60 -> 1920
A61: FAA | B61: 4320 | C61: FS | D61: Subhana Yasin | E61: 4700E723960 | F61: 36502-1828819-0 | H61: 36574 | I61: 45187 | K61: =MAX(0, MIN(M61, J61) - MAX(L61, I61) + 1) -> 31 | L61: 45292 | M61: 45322 | N61: =ROUNDUP(K61/31*320,0) -> 320 | O61: =N61*5 -> 1600 | P61: =N61+O61 -> 1920
A62: FAA | B62: 4320 | C62: FS | D62: Talha Arshad Malik | E62: 3600F372686 | F62: 37405-6378563-1 | H62: 33156 | I62: 44285 | K62: =MAX(0, MIN(M62, J62) - MAX(L62, I62) + 1) -> 31 | L62: 45292 | M62: 45322 | N62: =ROUNDUP(K62/31*320,0) -> 320 | O62: =N62*5 -> 1600 | P62: =N62+O62 -> 1920
A63: FAA | B63: 4320 | C63: FS | D63: Tayyab Abbas | E63: 4700A685051 | F63: 17301-2752063-7 | H63: 36797 | I63: 44886 | K63: =MAX(0, MIN(M63, J63) - MAX(L63, I63) + 1) -> 31 | L63: 45292 | M63: 45322 | N63: =ROUNDUP(K63/31*320,0) -> 320 | O63: =N63*5 -> 1600 | P63: =N63+O63 -> 1920
A64: FAA | B64: 4320 | C64: FS | D64: Umaira Jabeen | E64: 3600J522091 | F64: 37104-5371430-8 | H64: 33769 | I64: 44816 | K64: =MAX(0, MIN(M64, J64) - MAX(L64, I64) + 1) -> 31 | L64: 45292 | M64: 45322 | N64: =ROUNDUP(K64/31*320,0) -> 320 | O64: =N64*5 -> 1600 | P64: =N64+O64 -> 1920
A65: FAA | B65: 4320 | C65: FS | D65: Umar Farooq | E65: 4700D723961 | F65: 36501-4241566-9 | H65: 36408 | I65: 45173 | K65: =MAX(0, MIN(M65, J65) - MAX(L65, I65) + 1) -> 31 | L65: 45292 | M65: 45322 | N65: =ROUNDUP(K65/31*320,0) -> 320 | O65: =N65*5 -> 1600 | P65: =N65+O65 -> 1920
... A68: FAA | B68: 4320 | C68: FS | D68: Zoha Munir | E68: 0600G182381 | F68: 35202-9887337-8 | H68: 35743 | I68: 45222 | K68: =MAX(0, MIN(M68, J68) - MAX(L68, I68) + 1) -> 31 | L68: 45292 | M68: 45322 | N68: =ROUNDUP(K68/31*320,0) -> 320 | O68: =N68*5 -> 1600 | P68: =N68+O68 -> 1920
P69: =SUM(P2:P68) -> 117888

Sheet Feb-24
A1: EMP_AREA_CODE | B1: EMP_REG_SERIAL_NO | C1: EMP_SUB_AREA_CODE | D1: Name | E1: EOBI_NO | F1: CNIC | G1: NIC | H1: DOB | I1: DOJ | J1: DOE | K1: NO_OF_DAYS_WORKED | L1: From_Date | M1: To_Date | N1: Payment | O1: Employer Contribution | P1: Total EOBI
A2: FAA | B2: 4320 | C2: FS | D2: Abdul Hameed | E2: 4700J763957 | F2: 17301-6508006-1 | H2: 36617 | I2: 45299 | K2: =MAX(0, MIN(M2, J2) - MAX(L2, I2) + 1) -> 29 | L2: 45323 | M2: 45351 | N2: =ROUNDUP(K2/29*320,0) -> 320 | O2: =N2*5 -> 1600 | P2: =N2+O2 -> 1920
A3: FAA | B3: 4320 | C3: FS | D3: Abdullah Bin Rashid | E3: 4700A705194 | F3: 61101-3101618-7 | H3: 36358 | I3: 45027 | K3: =MAX(0, MIN(M3, J3) - MAX(L3, I3) + 1) -> 29 | L3: 45323 | M3: 45351 | N3: =ROUNDUP(K3/29*320,0) -> 320 | O3: =N3*5 -> 1600 | P3: =N3+O3 -> 1920
A4: FAA | B4: 4320 | C4: FS | D4: Abdullah Rasheed | E4: 4700G688671 | F4: 37401-7271621-7 | H4: 36860 | I4: 45124 | K4: =MAX(0, MIN(M4, J4) - MAX(L4, I4) + 1) -> 29 | L4: 45323 | M4: 45351 | N4: =ROUNDUP(K4/29*320,0) -> 320 | O4: =N4*5 -> 1600 | P4: =N4+O4 -> 1920
A5: FAA | B5: 4320 | C5: FS | D5: Ahmad Hassan | E5: 4600D315335 | F5: 37405-4246562-3 | H5: 35997 | I5: 45061 | K5: =MAX(0, MIN(M5, J5) - MAX(L5, I5) + 1) -> 29 | L5: 45323 | M5: 45351 | N5: =ROUNDUP(K5/29*320,0) -> 320 | O5: =N5*5 -> 1600 | P5: =N5+O5 -> 1920
A6: FAA | B6: 4320 | C6: FS | D6: Ahmed Hussain | E6: 4800F063920 | F6: 38102-5707136-9 | H6: 36353 | I6: 45278 | K6: =MAX(0, MIN(M6, J6) - MAX(L6, I6) + 1) -> 29 | L6: 45323 | M6: 45351 | N6: =ROUNDUP(K6/29*320,0) -> 320 | O6: =N6*5 -> 1600 | P6: =N6+O6 -> 1920
A7: FAA | B7: 4320 | C7: FS | D7: Ali Irfan | E7: 3100J940197 | F7: 35202-7336402-9 | H7: 36634 | I7: 45251 | K7: =MAX(0, MIN(M7, J7) - MAX(L7, I7) + 1) -> 29 | L7: 45323 | M7: 45351 | N7: =ROUNDUP(K7/29*320,0) -> 320 | O7: =N7*5 -> 1600 | P7: =N7+O7 -> 1920
A8: FAA | B8: 4320 | C8: FS | D8: Ali Nawaz Channa | E8: 0800E397265 | F8: 42201-8465990-5 | H8: 33408 | I8: 45078 | K8: =MAX(0, MIN(M8, J8) - MAX(L8, I8) + 1) -> 29 | L8: 45323 | M8: 45351 | N8: =ROUNDUP(K8/29*320,0) -> 320 | O8: =N8*5 -> 1600 | P8: =N8+O8 -> 1920
A9: FAA | B9: 4320 | C9: FS | D9: Alina Mubarik | E9: 4700C710820 | F9: 61101-5318332-4 | H9: 35983 | I9: 45082 | K9: =MAX(0, MIN(M9, J9) - MAX(L9, I9) + 1) -> 29 | L9: 45323 | M9: 45351 | N9: =ROUNDUP(K9/29*320,0) -> 320 | O9: =N9*5 -> 1600 | P9: =N9+O9 -> 1920
A10: FAA | B10: 4320 | C10: FS | D10: Altamash Shaban | E10: 4700G469815 | F10: 37405-5322814-9 | H10: 33048 | I10: 45250 | J10: 45329 | K10: =MAX(0, MIN(M10, J10) - MAX(L10, I10) + 1) -> 7 | L10: 45323 | M10: 45351 | N10: =ROUNDUP(K10/29*320,0) -> 78 | O10: =N10*5 -> 390 | P10: =N10+O10 -> 468
A11: FAA | B11: 4320 | C11: FS | D11: Anamil Mehtab | E11: 4700A710822 | F11: 37103-6819266-4 | H11: 37398 | I11: 45096 | K11: =MAX(0, MIN(M11, J11) - MAX(L11, I11) + 1) -> 29 | L11: 45323 | M11: 45351 | N11: =ROUNDUP(K11/29*320,0) -> 320 | O11: =N11*5 -> 1600 | P11: =N11+O11 -> 1920
A12: FAA | B12: 4320 | C12: FS | D12: Asad Ullah | E12: 4700C748792 | F12: 34401-8557347-3 | H12: 35047 | I12: 45257 | K12: =MAX(0, MIN(M12, J12) - MAX(L12, I12) + 1) -> 29 | L12: 45323 | M12: 45351 | N12: =ROUNDUP(K12/29*320,0) -> 320 | O12: =N12*5 -> 1600 | P12: =N12+O12 -> 1920
A13: FAA | B13: 4320 | C13: FS | D13: Asim Latif | E13: 4700A658224 | F13: 33302-5158556-5 | H13: 37370 | I13: 44739 | K13: =MAX(0, MIN(M13, J13) - MAX(L13, I13) + 1) -> 29 | L13: 45323 | M13: 45351 | N13: =ROUNDUP(K13/29*320,0) -> 320 | O13: =N13*5 -> 1600 | P13: =N13+O13 -> 1920
A14: FAA | B14: 4320 | C14: FS | D14: Atif Nawaz | E14: 4700E740695 | F14: 38404-7428636-7 | H14: 36399 | I14: 45229 | K14: =MAX(0, MIN(M14, J14) - MAX(L14, I14) + 1) -> 29 | L14: 45323 | M14: 45351 | N14: =ROUNDUP(K14/29*320,0) -> 320 | O14: =N14*5 -> 1600 | P14: =N14+O14 -> 1920
A15: FAA | B15: 4320 | C15: FS | D15: Ayesha Syed | E15: 4700E763960 | F15: 37405-5537896-0 | H15: 37377 | I15: 45334 | K15: =MAX(0, MIN(M15, J15) - MAX(L15, I15) + 1) -> 18 | L15: 45323 | M15: 45351 | N15: =ROUNDUP(K15/29*320,0) -> 199 | O15: =N15*5 -> 995 | P15: =N15+O15 -> 1194
A16: FAA | B16: 4320 | C16: FS | D16: Ayesha Tahir | E16: 4700A748794 | F16: 13101-5843018-0 | H16: 37047 | I16: 45257 | K16: =MAX(0, MIN(M16, J16) - MAX(L16, I16) + 1) -> 29 | L16: 45323 | M16: 45351 | N16: =ROUNDUP(K16/29*320,0) -> 320 | O16: =N16*5 -> 1600 | P16: =N16+O16 -> 1920
A17: FAA | B17: 4320 | C17: FS | D17: Basit Afraz | E17: 4700C703310 | F17: 37405-8019865-5 | H17: 34601 | I17: 44986 | K17: =MAX(0, MIN(M17, J17) - MAX(L17, I17) + 1) -> 29 | L17: 45323 | M17: 45351 | N17: =ROUNDUP(K17/29*320,0) -> 320 | O17: =N17*5 -> 1600 | P17: =N17+O17 -> 1920
A18: FAA | B18: 4320 | C18: FS | D18: Faiza Khan | E18: 4700J710823 | F18: 61101-0776147-2 | H18: 37322 | I18: 45096 | K18: =MAX(0, MIN(M18, J18) - MAX(L18, I18) + 1) -> 29 | L18: 45323 | M18: 45351 | N18: =ROUNDUP(K18/29*320,0) -> 320 | O18: =N18*5 -> 1600 | P18: =N18+O18 -> 1920
A19: FAA | B19: 4320 | C19: FS | D19: Faizan Khan | E19: 4700C662124 | F19: 16204-0388636-3 | H19: 35704 | I19: 44760 | K19: =MAX(0, MIN(M19, J19) - MAX(L19, I19) + 1) -> 29 | L19: 45323 | M19: 45351 | N19: =ROUNDUP(K19/29*320,0) -> 320 | O19: =N19*5 -> 1600 | P19: =N19+O19 -> 1920
A20: FAA | B20: 4320 | C20: FS | D20: Farzam Habib Khan | E20: 4700B748793 | F20: 12101-9669033-4 | H20: 37219 | I20: 45257 | K20: =MAX(0, MIN(M20, J20) - MAX(L20, I20) + 1) -> 29 | L20: 45323 | M20: 45351 | N20: =ROUNDUP(K20/29*320,0) -> 320 | O20: =N20*5 -> 1600 | P20: =N20+O20 -> 1920
A21: FAA | B21: 4320 | C21: FS | D21: Hamza Ahmad | E21: 4700I678608 | F21: 37405-6689341-9 | H21: 36246 | I21: 44851 | K21: =MAX(0, MIN(M21, J21) - MAX(L21, I21) + 1) -> 29 | L21: 45323 | M21: 45351 | N21: =ROUNDUP(K21/29*320,0) -> 320 | O21: =N21*5 -> 1600 | P21: =N21+O21 -> 1920
A22: FAA | B22: 4320 | C22: FS | D22: Hamza Ali Khan | E22: 4700B690429 | F22: 37405-5700118-7 | H22: 35606 | I22: 44896 | K22: =MAX(0, MIN(M22, J22) - MAX(L22, I22) + 1) -> 29 | L22: 45323 | M22: 45351 | N22: =ROUNDUP(K22/29*320,0) -> 320 | O22: =N22*5 -> 1600 | P22: =N22+O22 -> 1920
... A41: FAA | B41: 4320 | C41: FS | D41: Muhammad Ibrahim | E41: 4700C720948 | F41: 31101-0776303-7 | H41: 37149 | I41: 45124 | K41: =MAX(0, MIN(M41, J41) - MAX(L41, I41) + 1) -> 29 | L41: 45323 | M41: 45351 | N41: =ROUNDUP(K41/29*320,0) -> 320 | O41: =N41*5 -> 1600 | P41: =N41+O41 -> 1920
A42: FAA | B42: 4320 | C42: FS | D42: Muhammad Nabeel Asif | E42: 0800I431358 | F42: 42101-1217952-3 | H42: 34503 | I42: 45246 | J42: 45338 | K42: =MAX(0, MIN(M42, J42) - MAX(L42, I42) + 1) -> 16 | L42: 45323 | M42: 45351 | N42: =ROUNDUP(K42/29*320,0) -> 177 | O42: =N42*5 -> 885 | P42: =N42+O42 -> 1062
A43: FAA | B43: 4320 | C43: FS | D43: Muhammad Saad Tariq | E43: 4700D679730 | F43: 61101-0817777-7 | H43: 36207 | I43: 45054 | J43: 45351 | K43: =MAX(0, MIN(M43, J43) - MAX(L43, I43) + 1) -> 29 | L43: 45323 | M43: 45351 | N43: =ROUNDUP(K43/29*320,0) -> 320 | O43: =N43*5 -> 1600 | P43: =N43+O43 -> 1920
A44: FAA | B44: 4320 | C44: FS | D44: Muhammad Zahab Ahmed | E44: 3600G329844 | F44: 31102-2135283-9 | H44: 34300 | I44: 45183 | K44: =MAX(0, MIN(M44, J44) - MAX(L44, I44) + 1) -> 29 | L44: 45323 | M44: 45351 | N44: =ROUNDUP(K44/29*320,0) -> 320 | O44: =N44*5 -> 1600 | P44: =N44+O44 -> 1920
A45: FAA | B45: 4320 | C45: FS | D45: Musa Naqvi
A46: FAA | B46: 4320 | C46: FS | D46: Naimal Imran | E46: 4700J662127 | F46: 35202-0754928-4 | H46: 36541 | I46: 44755 | K46: =MAX(0, MIN(M46, J46) - MAX(L46, I46) + 1) -> 29 | L46: 45323 | M46: 45351 | N46: =ROUNDUP(K46/29*320,0) -> 320 | O46: =N46*5 -> 1600 | P46: =N46+O46 -> 1920
A47: FAA | B47: 4320 | C47: FS | D47: Namra Akram | E47: 4700F444303 | F47: 61101-4919576-8 | H47: 34335 | I47: 45078 | K47: =MAX(0, MIN(M47, J47) - MAX(L47, I47) + 1) -> 29 | L47: 45323 | M47: 45351 | N47: =ROUNDUP(K47/29*320,0) -> 320 | O47: =N47*5 -> 1600 | P47: =N47+O47 -> 1920
A48: FAA | B48: 4320 | C48: FS | D48: Naveed Ahmed | E48: 4700H679736 | F48: 42201-5462974-9 | H48: 31014 | I48: 44805 | K48: =MAX(0, MIN(M48, J48) - MAX(L48, I48) + 1) -> 29 | L48: 45323 | M48: 45351 | N48: =ROUNDUP(K48/29*320,0) -> 320 | O48: =N48*5 -> 1600 | P48: =N48+O48 -> 1920
A49: FAA | B49: 4320 | C49: FS | D49: Nimra Zahid | E49: 4700G537391 | F49: 42201-1439506-4 | H49: 34522 | I49: 45292 | K49: =MAX(0, MIN(M49, J49) - MAX(L49, I49) + 1) -> 29 | L49: 45323 | M49: 45351 | N49: =ROUNDUP(K49/29*320,0) -> 320 | O49: =N49*5 -> 1600 | P49: =N49+O49 -> 1920
A50: FAA | B50: 4320 | C50: FS | D50: Rashid Iqbal | E50: 4700I703314 | F50: 37405-6880780-7 | H50: 34732 | I50: 44986 | K50: =MAX(0, MIN(M50, J50) - MAX(L50, I50) + 1) -> 29 | L50: 45323 | M50: 45351 | N50: =ROUNDUP(K50/29*320,0) -> 320 | O50: =N50*5 -> 1600 | P50: =N50+O50 -> 1920
A51: FAA | B51: 4320 | C51: FS | D51: Saad Ahmed | E51: 0800E406072 | F51: 35202-3107480-5 | H51: 33762 | I51: 45229 | K51: =MAX(0, MIN(M51, J51) - MAX(L51, I51) + 1) -> 31 | L51: 45261 | M51: 45291 | N51: =ROUNDUP(K51/31*320,0) -> 320 | O51: =N51*5 -> 1600 | P51: =N51+O51 -> 1920
A52: FAA | B52: 4320 | C52: FS | D52: Saif Ullah | E52: 4700A764083 | F52: 61101-5764361-9 | H52: 37479 | I52: 45320 | K52: =MAX(0, MIN(M52, J52) - MAX(L52, I52) + 1) -> 29 | L52: 45323 | M52: 45351 | N52: =ROUNDUP(K52/29*320,0) -> 320 | O52: =N52*5 -> 1600 | P52: =N52+O52 -> 1920
A53: FAA | B53: 4320 | C53: FS | D53: Salman Khalid | E53: 3300B264525 | F53: 34603-0435168-5 | H53: 33003 | I53: 45313 | K53: =MAX(0, MIN(M53, J53) - MAX(L53, I53) + 1) -> 29 | L53: 45323 | M53: 45351 | N53: =ROUNDUP(K53/29*320,0) -> 320 | O53: =N53*5 -> 1600 | P53: =N53+O53 -> 1920
A54: FAA | B54: 4320 | C54: FS | D54: Sana Sajjad Chaudhary | E54: 4700F740694 | F54: 37301-3885164-8 | H54: 36109 | I54: 45250 | K54: =MAX(0, MIN(M54, J54) - MAX(L54, I54) + 1) -> 29 | L54: 45323 | M54: 45351 | N54: =ROUNDUP(K54/29*320,0) -> 320 | O54: =N54*5 -> 1600 | P54: =N54+O54 -> 1920
A55: FAA | B55: 4320 | C55: FS | D55: Sana Tahir | E55: 4700D706561 | F55: 37103-2235902-2 | H55: 35976 | I55: 45042 | K55: =MAX(0, MIN(M55, J55) - MAX(L55, I55) + 1) -> 29 | L55: 45323 | M55: 45351 | N55: =ROUNDUP(K55/29*320,0) -> 320 | O55: =N55*5 -> 1600 | P55: =N55+O55 -> 1920
A56: FAA | B56: 4320 | C56: FS | D56: Shahnoor Ejaz | E56: 4700F703333 | F56: 42501-6125083-4 | H56: 36297 | I56: 45001 | K56: =MAX(0, MIN(M56, J56) - MAX(L56, I56) + 1) -> 29 | L56: 45323 | M56: 45351 | N56: =ROUNDUP(K56/29*320,0) -> 320 | O56: =N56*5 -> 1600 | P56: =N56+O56 -> 1920
A57: FAA | B57: 4320 | C57: FS | D57: Shahzad Farooq | E57: 4700G690432 | F57: 42501-8133748-7 | H57: 36979 | I57: 44907 | K57: =MAX(0, MIN(M57, J57) - MAX(L57, I57) + 1) -> 29 | L57: 45323 | M57: 45351 | N57: =ROUNDUP(K57/29*320,0) -> 320 | O57: =N57*5 -> 1600 | P57: =N57+O57 -> 1920
A58: FAA | B58: 4320 | C58: FS | D58: Shaiq Habib | E58: 0400C579124 | F58: 61101-1388832-7 | H58: 36421 | I58: 45208 | K58: =MAX(0, MIN(M58, J58) - MAX(L58, I58) + 1) -> 29 | L58: 45323 | M58: 45351 | N58: =ROUNDUP(K58/29*320,0) -> 320 | O58: =N58*5 -> 1600 | P58: =N58+O58 -> 1920
A59: FAA | B59: 4320 | C59: FS | D59: Shan Ahmad | E59: 4700C748360 | F59: 35202-9717455-5 | H59: 35447 | I59: 45273 | K59: =MAX(0, MIN(M59, J59) - MAX(L59, I59) + 1) -> 29 | L59: 45323 | M59: 45351 | N59: =ROUNDUP(K59/29*320,0) -> 320 | O59: =N59*5 -> 1600 | P59: =N59+O59 -> 1920
A60: FAA | B60: 4320 | C60: FS | D60: Shawal Fida | E60: 4700I700798 | F60: 16202-0438523-4 | H60: 36075 | I60: 44977 | K60: =MAX(0, MIN(M60, J60) - MAX(L60, I60) + 1) -> 29 | L60: 45323 | M60: 45351 | N60: =ROUNDUP(K60/29*320,0) -> 320 | O60: =N60*5 -> 1600 | P60: =N60+O60 -> 1920
A61: FAA | B61: 4320 | C61: FS | D61: Subhana Yasin | E61: 4700E723960 | F61: 36502-1828819-0 | H61: 36574 | I61: 45187 | K61: =MAX(0, MIN(M61, J61) - MAX(L61, I61) + 1) -> 29 | L61: 45323 | M61: 45351 | N61: =ROUNDUP(K61/29*320,0) -> 320 | O61: =N61*5 -> 1600 | P61: =N61+O61 -> 1920
A62: FAA | B62: 4320 | C62: FS | D62: Sukaina Ali | E62: 4700C688544 | F62: 37405-6240250-8 | H62: 36991 | I62: 45323 | K62: =MAX(0, MIN(M62, J62) - MAX(L62, I62) + 1) -> 29 | L62: 45323 | M62: 45351 | N62: =ROUNDUP(K62/29*320,0) -> 320 | O62: =N62*5 -> 1600 | P62: =N62+O62 -> 1920
A63: FAA | B63: 4320 | C63: FS | D63: Talha Arshad Malik | E63: 3600F372686 | F63: 37405-6378563-1 | H63: 33156 | I63: 44285 | K63: =MAX(0, MIN(M63, J63) - MAX(L63, I63) + 1) -> 29 | L63: 45323 | M63: 45351 | N63: =ROUNDUP(K63/29*320,0) -> 320 | O63: =N63*5 -> 1600 | P63: =N63+O63 -> 1920
... A71: FAA | B71: 4320 | C71: FS | D71: Zoha Munir | E71: 0600G182381 | F71: 35202-9887337-8 | H71: 35743 | I71: 45222 | K71: =MAX(0, MIN(M71, J71) - MAX(L71, I71) + 1) -> 29 | L71: 45323 | M71: 45351 | N71: =ROUNDUP(K71/29*320,0) -> 320 | O71: =N71*5 -> 1600 | P71: =N71+O71 -> 1920
P72: =SUM(P2:P71) -> 127134

Sheet Mar-24
A1: EMP_AREA_CODE | B1: EMP_REG_SERIAL_NO | C1: EMP_SUB_AREA_CODE | D1: Name | E1: EOBI_NO | F1: CNIC | G1: NIC | H1: DOB | I1: DOJ | J1: DOE | K1: NO_OF_DAYS_WORKED | L1: From_Date | M1: To_Date | N1: Payment | O1: Employer Contribution | P1: Total EOBI
A2: FAA | B2: 4320 | C2: FS | D2: Abdul Hameed | E2: 4700J763957 | F2: 17301-6508006-1 | H2: 36617 | I2: 45299 | K2: =MAX(0, MIN(M2, J2) - MAX(L2, I2) + 1) -> 31 | L2: 45352 | M2: 45382 | N2: =ROUNDUP(K2/31*320,0) -> 320 | O2: =N2*5 -> 1600 | P2: =N2+O2 -> 1920
A3: FAA | B3: 4320 | C3: FS | D3: Abdul Rehan Najam | E3: 4700H764086 | F3: 61101-8333683-7 | H3: 37282 | I3: 45362 | K3: =MAX(0, MIN(M3, J3) - MAX(L3, I3) + 1) -> 21 | L3: 45352 | M3: 45382 | N3: =ROUNDUP(K3/31*320,0) -> 217 | O3: =N3*5 -> 1085 | P3: =N3+O3 -> 1302
A4: FAA | B4: 4320 | C4: FS | D4: Abdullah Bin Rashid | E4: 4700A705194 | F4: 61101-3101618-7 | H4: 36358 | I4: 45027 | K4: =MAX(0, MIN(M4, J4) - MAX(L4, I4) + 1) -> 31 | L4: 45352 | M4: 45382 | N4: =ROUNDUP(K4/31*320,0) -> 320 | O4: =N4*5 -> 1600 | P4: =N4+O4 -> 1920
A5: FAA | B5: 4320 | C5: FS | D5: Abdullah Rasheed | E5: 4700G688671 | F5: 37401-7271621-7 | H5: 36860 | I5: 45124 | K5: =MAX(0, MIN(M5, J5) - MAX(L5, I5) + 1) -> 31 | L5: 45352 | M5: 45382 | N5: =ROUNDUP(K5/31*320,0) -> 320 | O5: =N5*5 -> 1600 | P5: =N5+O5 -> 1920
A6: FAA | B6: 4320 | C6: FS | D6: Abu Usama | E6: 4700G764087 | F6: 36501-7651414-9 | H6: 35619 | I6: 45369 | K6: =MAX(0, MIN(M6, J6) - MAX(L6, I6) + 1) -> 14 | L6: 45352 | M6: 45382 | N6: =ROUNDUP(K6/31*320,0) -> 145 | O6: =N6*5 -> 725 | P6: =N6+O6 -> 870
A7: FAA | B7: 4320 | C7: FS | D7: Ahmad Hassan | E7: 4600D315335 | F7: 37405-4246562-3 | H7: 35997 | I7: 45061 | K7: =MAX(0, MIN(M7, J7) - MAX(L7, I7) + 1) -> 31 | L7: 45352 | M7: 45382 | N7: =ROUNDUP(K7/31*320,0) -> 320 | O7: =N7*5 -> 1600 | P7: =N7+O7 -> 1920
A8: FAA | B8: 4320 | C8: FS | D8: Ahmed Hussain | E8: 4800F063920 | F8: 38102-5707136-9 | H8: 36353 | I8: 45278 | K8: =MAX(0, MIN(M8, J8) - MAX(L8, I8) + 1) -> 31 | L8: 45352 | M8: 45382 | N8: =ROUNDUP(K8/31*320,0) -> 320 | O8: =N8*5 -> 1600 | P8: =N8+O8 -> 1920
A9: FAA | B9: 4320 | C9: FS | D9: Ali Irfan | E9: 3100J940197 | F9: 35202-7336402-9 | H9: 36634 | I9: 45251 | K9: =MAX(0, MIN(M9, J9) - MAX(L9, I9) + 1) -> 31 | L9: 45352 | M9: 45382 | N9: =ROUNDUP(K9/31*320,0) -> 320 | O9: =N9*5 -> 1600 | P9: =N9+O9 -> 1920
A10: FAA | B10: 4320 | C10: FS | D10: Ali Nawaz Channa | E10: 0800E397265 | F10: 42201-8465990-5 | H10: 33408 | I10: 45078 | J10: 45366 | K10: =MAX(0, MIN(M10, J10) - MAX(L10, I10) + 1) -> 15 | L10: 45352 | M10: 45382 | N10: =ROUNDUP(K10/31*320,0) -> 155 | O10: =N10*5 -> 775 | P10: =N10+O10 -> 930
A11: FAA | B11: 4320 | C11: FS | D11: Alina Mubarik | E11: 4700C710820 | F11: 61101-5318332-4 | H11: 35983 | I11: 45082 | J11: 45362 | K11: =MAX(0, MIN(M11, J11) - MAX(L11, I11) + 1) -> 11 | L11: 45352 | M11: 45382 | N11: =ROUNDUP(K11/31*320,0) -> 114 | O11: =N11*5 -> 570 | P11: =N11+O11 -> 684
A12: FAA | B12: 4320 | C12: FS | D12: Amish Tufail | E12: 4700H764094 | F12: 13302-2902324-3 | H12: 37274 | I12: 45362 | K12: =MAX(0, MIN(M12, J12) - MAX(L12, I12) + 1) -> 21 | L12: 45352 | M12: 45382 | N12: =ROUNDUP(K12/31*320,0) -> 217 | O12: =N12*5 -> 1085 | P12: =N12+O12 -> 1302
A13: FAA | B13: 4320 | C13: FS | D13: Anamil Mehtab | E13: 4700A710822 | F13: 37103-6819266-4 | H13: 37398 | I13: 45096 | K13: =MAX(0, MIN(M13, J13) - MAX(L13, I13) + 1) -> 31 | L13: 45352 | M13: 45382 | N13: =ROUNDUP(K13/31*320,0) -> 320 | O13: =N13*5 -> 1600 | P13: =N13+O13 -> 1920
A14: FAA | B14: 4320 | C14: FS | D14: Anas Hanif Attas | E14: 4700B665806 | F14: 38403-3251146-3 | H14: 36360 | I14: 45355 | K14: =MAX(0, MIN(M14, J14) - MAX(L14, I14) + 1) -> 28 | L14: 45352 | M14: 45382 | N14: =ROUNDUP(K14/31*320,0) -> 290 | O14: =N14*5 -> 1450 | P14: =N14+O14 -> 1740
A15: FAA | B15: 4320 | C15: FS | D15: Arsal Sher Khan | E15: 4700F764096 | F15: 35201-5498096-5 | H15: 37100 | I15: 45376 | K15: =MAX(0, MIN(M15, J15) - MAX(L15, I15) + 1) -> 7 | L15: 45352 | M15: 45382 | N15: =ROUNDUP(K15/31*320,0) -> 73 | O15: =N15*5 -> 365 | P15: =N15+O15 -> 438
A16: FAA | B16: 4320 | C16: FS | D16: Asad Ullah | E16: 4700C748792 | F16: 34401-8557347-3 | H16: 35047 | I16: 45257 | K16: =MAX(0, MIN(M16, J16) - MAX(L16, I16) + 1) -> 31 | L16: 45352 | M16: 45382 | N16: =ROUNDUP(K16/31*320,0) -> 320 | O16: =N16*5 -> 1600 | P16: =N16+O16 -> 1920
A17: FAA | B17: 4320 | C17: FS | D17: Asim Latif | E17: 4700A658224 | F17: 33302-5158556-5 | H17: 37370 | I17: 44739 | K17: =MAX(0, MIN(M17, J17) - MAX(L17, I17) + 1) -> 31 | L17: 45352 | M17: 45382 | N17: =ROUNDUP(K17/31*320,0) -> 320 | O17: =N17*5 -> 1600 | P17: =N17+O17 -> 1920
A18: FAA | B18: 4320 | C18: FS | D18: Atif Nawaz | E18: 4700E740695 | F18: 38404-7428636-7 | H18: 36399 | I18: 45229 | K18: =MAX(0, MIN(M18, J18) - MAX(L18, I18) + 1) -> 31 | L18: 45352 | M18: 45382 | N18: =ROUNDUP(K18/31*320,0) -> 320 | O18: =N18*5 -> 1600 | P18: =N18+O18 -> 1920
A19: FAA | B19: 4320 | C19: FS | D19: Ayesha Shakeel | E19: 4700H763959 | F19: 42301-1838144-6 | H19: 36962 | I19: 45376 | K19: =MAX(0, MIN(M19, J19) - MAX(L19, I19) + 1) -> 7 | L19: 45352 | M19: 45382 | N19: =ROUNDUP(K19/31*320,0) -> 73 | O19: =N19*5 -> 365 | P19: =N19+O19 -> 438
A20: FAA | B20: 4320 | C20: FS | D20: Ayesha Syed | E20: 4700E763960 | F20: 37405-5537896-0 | H20: 37377 | I20: 45334 | K20: =MAX(0, MIN(M20, J20) - MAX(L20, I20) + 1) -> 31 | L20: 45352 | M20: 45382 | N20: =ROUNDUP(K20/31*320,0) -> 320 | O20: =N20*5 -> 1600 | P20: =N20+O20 -> 1920
A21: FAA | B21: 4320 | C21: FS | D21: Basit Afraz | E21: 4700C703310 | F21: 37405-8019865-5 | H21: 34601 | I21: 44986 | K21: =MAX(0, MIN(M21, J21) - MAX(L21, I21) + 1) -> 31 | L21: 45352 | M21: 45382 | N21: =ROUNDUP(K21/31*320,0) -> 320 | O21: =N21*5 -> 1600 | P21: =N21+O21 -> 1920
A22: FAA | B22: 4320 | C22: FS | D22: Faiza Khan | E22: 4700J710823 | F22: 61101-0776147-2 | H22: 37322 | I22: 45096 | K22: =MAX(0, MIN(M22, J22) - MAX(L22, I22) + 1) -> 31 | L22: 45352 | M22: 45382 | N22: =ROUNDUP(K22/31*320,0) -> 320 | O22: =N22*5 -> 1600 | P22: =N22+O22 -> 1920
A23: FAA | B23: 4320 | C23: FS | D23: Faizan Khan | E23: 4700C662124 | F23: 16204-0388636-3 | H23: 35704 | I23: 44760 | K23: =MAX(0, MIN(M23, J23) - MAX(L23, I23) + 1) -> 31 | L23: 45352 | M23: 45382 | N23: =ROUNDUP(K23/31*320,0) -> 320 | O23: =N23*5 -> 1600 | P23: =N23+O23 -> 1920
... A53: FAA | B53: 4320 | C53: FS | D53: Muiz Hussain | E53: 4600F352555 | F53: 42301-8666708-3 | H53: 36412 | I53: 45355 | K53: =MAX(0, MIN(M53, J53) - MAX(L53, I53) + 1) -> 28 | L53: 45352 | M53: 45382 | N53: =ROUNDUP(K53/31*320,0) -> 290 | O53: =N53*5 -> 1450 | P53: =N53+O53 -> 1740
A54: FAA | B54: 4320 | C54: FS | D54: Musa Naqvi
A55: FAA | B55: 4320 | C55: FS | D55: Naimal Imran | E55: 4700J662127 | F55: 35202-0754928-4 | H55: 36541 | I55: 44755 | K55: =MAX(0, MIN(M55, J55) - MAX(L55, I55) + 1) -> 31 | L55: 45352 | M55: 45382 | N55: =ROUNDUP(K55/31*320,0) -> 320 | O55: =N55*5 -> 1600 | P55: =N55+O55 -> 1920
A56: FAA | B56: 4320 | C56: FS | D56: Namra Akram | E56: 4700F444303 | F56: 61101-4919576-8 | H56: 34335 | I56: 45078 | K56: =MAX(0, MIN(M56, J56) - MAX(L56, I56) + 1) -> 31 | L56: 45352 | M56: 45382 | N56: =ROUNDUP(K56/31*320,0) -> 320 | O56: =N56*5 -> 1600 | P56: =N56+O56 -> 1920
A57: FAA | B57: 4320 | C57: FS | D57: Naveed Ahmed | E57: 4700H679736 | F57: 42201-5462974-9 | H57: 31014 | I57: 44805 | K57: =MAX(0, MIN(M57, J57) - MAX(L57, I57) + 1) -> 31 | L57: 45352 | M57: 45382 | N57: =ROUNDUP(K57/31*320,0) -> 320 | O57: =N57*5 -> 1600 | P57: =N57+O57 -> 1920
A58: FAA | B58: 4320 | C58: FS | D58: Nimra Zahid | E58: 4700G537391 | F58: 42201-1439506-4 | H58: 34522 | I58: 45292 | K58: =MAX(0, MIN(M58, J58) - MAX(L58, I58) + 1) -> 31 | L58: 45352 | M58: 45382 | N58: =ROUNDUP(K58/31*320,0) -> 320 | O58: =N58*5 -> 1600 | P58: =N58+O58 -> 1920
A59: FAA | B59: 4320 | C59: FS | D59: Rashid Iqbal | E59: 4700I703314 | F59: 37405-6880780-7 | H59: 34732 | I59: 44986 | K59: =MAX(0, MIN(M59, J59) - MAX(L59, I59) + 1) -> 31 | L59: 45352 | M59: 45382 | N59: =ROUNDUP(K59/31*320,0) -> 320 | O59: =N59*5 -> 1600 | P59: =N59+O59 -> 1920
A60: FAA | B60: 4320 | C60: FS | D60: Saad Ahmed | E60: 0800E406072 | F60: 35202-3107480-5 | H60: 33762 | I60: 45229 | K60: =MAX(0, MIN(M60, J60) - MAX(L60, I60) + 1) -> 31 | L60: 45261 | M60: 45291 | N60: =ROUNDUP(K60/31*320,0) -> 320 | O60: =N60*5 -> 1600 | P60: =N60+O60 -> 1920
A61: FAA | B61: 4320 | C61: FS | D61: Sabdezar Irfan | E61: 3600G465789 | F61: 35201-1547140-8 | H61: 35395 | I61: 45376 | K61: =MAX(0, MIN(M61, J61) - MAX(L61, I61) + 1) -> 7 | L61: 45352 | M61: 45382 | N61: =ROUNDUP(K61/31*320,0) -> 73 | O61: =N61*5 -> 365 | P61: =N61+O61 -> 438
A62: FAA | B62: 4320 | C62: FS | D62: Saboor Ahmad | E62: 4700D763937 | F62: 61101-8448365-1 | H62: 37397 | I62: 45377 | K62: =MAX(0, MIN(M62, J62) - MAX(L62, I62) + 1) -> 6 | L62: 45352 | M62: 45382 | N62: =ROUNDUP(K62/31*320,0) -> 62 | O62: =N62*5 -> 310 | P62: =N62+O62 -> 372
A63: FAA | B63: 4320 | C63: FS | D63: Saif Ullah | E63: 4700A764083 | F63: 61101-5764361-9 | H63: 37479 | I63: 45320 | K63: =MAX(0, MIN(M63, J63) - MAX(L63, I63) + 1) -> 31 | L63: 45352 | M63: 45382 | N63: =ROUNDUP(K63/31*320,0) -> 320 | O63: =N63*5 -> 1600 | P63: =N63+O63 -> 1920
A64: FAA | B64: 4320 | C64: FS | D64: Salman Khalid | E64: 3300B264525 | F64: 34603-0435168-5 | H64: 33003 | I64: 45313 | K64: =MAX(0, MIN(M64, J64) - MAX(L64, I64) + 1) -> 31 | L64: 45352 | M64: 45382 | N64: =ROUNDUP(K64/31*320,0) -> 320 | O64: =N64*5 -> 1600 | P64: =N64+O64 -> 1920
A65: FAA | B65: 4320 | C65: FS | D65: Sana Sajjad Chaudhary | E65: 4700F740694 | F65: 37301-3885164-8 | H65: 36109 | I65: 45250 | K65: =MAX(0, MIN(M65, J65) - MAX(L65, I65) + 1) -> 31 | L65: 45352 | M65: 45382 | N65: =ROUNDUP(K65/31*320,0) -> 320 | O65: =N65*5 -> 1600 | P65: =N65+O65 -> 1920
A66: FAA | B66: 4320 | C66: FS | D66: Sana Tahir | E66: 4700D706561 | F66: 37103-2235902-2 | H66: 35976 | I66: 45042 | K66: =MAX(0, MIN(M66, J66) - MAX(L66, I66) + 1) -> 31 | L66: 45352 | M66: 45382 | N66: =ROUNDUP(K66/31*320,0) -> 320 | O66: =N66*5 -> 1600 | P66: =N66+O66 -> 1920
A67: FAA | B67: 4320 | C67: FS | D67: Shahnoor Ejaz | E67: 4700F703333 | F67: 42501-6125083-4 | H67: 36297 | I67: 45001 | J67: 45359 | K67: =MAX(0, MIN(M67, J67) - MAX(L67, I67) + 1) -> 8 | L67: 45352 | M67: 45382 | N67: =ROUNDUP(K67/31*320,0) -> 83 | O67: =N67*5 -> 415 | P67: =N67+O67 -> 498
A68: FAA | B68: 4320 | C68: FS | D68: Shahzad Farooq | E68: 4700G690432 | F68: 42501-8133748-7 | H68: 36979 | I68: 44907 | K68: =MAX(0, MIN(M68, J68) - MAX(L68, I68) + 1) -> 31 | L68: 45352 | M68: 45382 | N68: =ROUNDUP(K68/31*320,0) -> 320 | O68: =N68*5 -> 1600 | P68: =N68+O68 -> 1920
A69: FAA | B69: 4320 | C69: FS | D69: Shaiq Habib | E69: 0400C579124 | F69: 61101-1388832-7 | H69: 36421 | I69: 45208 | K69: =MAX(0, MIN(M69, J69) - MAX(L69, I69) + 1) -> 31 | L69: 45352 | M69: 45382 | N69: =ROUNDUP(K69/31*320,0) -> 320 | O69: =N69*5 -> 1600 | P69: =N69+O69 -> 1920
A70: FAA | B70: 4320 | C70: FS | D70: Shan Ahmad | E70: 4700C748360 | F70: 35202-9717455-5 | H70: 35447 | I70: 45273 | K70: =MAX(0, MIN(M70, J70) - MAX(L70, I70) + 1) -> 31 | L70: 45352 | M70: 45382 | N70: =ROUNDUP(K70/31*320,0) -> 320 | O70: =N70*5 -> 1600 | P70: =N70+O70 -> 1920
A71: FAA | B71: 4320 | C71: FS | D71: Subhana Yasin | E71: 4700E723960 | F71: 36502-1828819-0 | H71: 36574 | I71: 45187 | K71: =MAX(0, MIN(M71, J71) - MAX(L71, I71) + 1) -> 31 | L71: 45352 | M71: 45382 | N71: =ROUNDUP(K71/31*320,0) -> 320 | O71: =N71*5 -> 1600 | P71: =N71+O71 -> 1920
A72: FAA | B72: 4320 | C72: FS | D72: Sukaina Ali | E72: 4700C688544 | F72: 37405-6240250-8 | H72: 36991 | I72: 45205 | K72: =MAX(0, MIN(M72, J72) - MAX(L72, I72) + 1) -> 31 | L72: 45352 | M72: 45382 | N72: =ROUNDUP(K72/31*320,0) -> 320 | O72: =N72*5 -> 1600 | P72: =N72+O72 -> 1920
A73: FAA | B73: 4320 | C73: FS | D73: Talha Arshad Malik | E73: 3600F372686 | F73: 37405-6378563-1 | H73: 33156 | I73: 44285 | K73: =MAX(0, MIN(M73, J73) - MAX(L73, I73) + 1) -> 31 | L73: 45352 | M73: 45382 | N73: =ROUNDUP(K73/31*320,0) -> 320 | O73: =N73*5 -> 1600 | P73: =N73+O73 -> 1920
A74: FAA | B74: 4320 | C74: FS | D74: Tauqeer Ahmed | E74: 4700H764078 | F74: 35201-5043196-1 | H74: 35697 | I74: 45348 | K74: =MAX(0, MIN(M74, J74) - MAX(L74, I74) + 1) -> 31 | L74: 45352 | M74: 45382 | N74: =ROUNDUP(K74/31*320,0) -> 320 | O74: =N74*5 -> 1600 | P74: =N74+O74 -> 1920
A75: FAA | B75: 4320 | C75: FS | D75: Tayyab Abbas | E75: 4700A685051 | F75: 17301-2752063-7 | H75: 36797 | I75: 44886 | K75: =MAX(0, MIN(M75, J75) - MAX(L75, I75) + 1) -> 31 | L75: 45352 | M75: 45382 | N75: =ROUNDUP(K75/31*320,0) -> 320 | O75: =N75*5 -> 1600 | P75: =N75+O75 -> 1920
A76: FAA | B76: 4320 | C76: FS | D76: Umaira Jabeen | E76: 3600J522091 | F76: 37104-5371430-8 | H76: 33769 | I76: 44816 | K76: =MAX(0, MIN(M76, J76) - MAX(L76, I76) + 1) -> 31 | L76: 45352 | M76: 45382 | N76: =ROUNDUP(K76/31*320,0) -> 320 | O76: =N76*5 -> 1600 | P76: =N76+O76 -> 1920
A77: FAA | B77: 4320 | C77: FS | D77: Umar Farooq | E77: 4700D723961 | F77: 36501-4241566-9 | H77: 36408 | I77: 45173 | K77: =MAX(0, MIN(M77, J77) - MAX(L77, I77) + 1) -> 31 | L77: 45352 | M77: 45382 | N77: =ROUNDUP(K77/31*320,0) -> 320 | O77: =N77*5 -> 1600 | P77: =N77+O77 -> 1920
A78: FAA | B78: 4320 | C78: FS | D78: Waleed Sadiq | E78: 4700C710870 | F78: 82101-6085499-3 | H78: 35818 | I78: 45089 | K78: =MAX(0, MIN(M78, J78) - MAX(L78, I78) + 1) -> 31 | L78: 45352 | M78: 45382 | N78: =ROUNDUP(K78/31*320,0) -> 320 | O78: =N78*5 -> 1600 | P78: =N78+O78 -> 1920
A79: FAA | B79: 4320 | C79: FS | D79: Zain Shahid | E79: 4700H700799 | F79: 36401-6591078-1 | H79: 36177 | I79: 45320 | K79: =MAX(0, MIN(M79, J79) - MAX(L79, I79) + 1) -> 31 | L79: 45352 | M79: 45382 | N79: =ROUNDUP(K79/31*320,0) -> 320 | O79: =N79*5 -> 1600 | P79: =N79+O79 -> 1920
... A81: FAA | B81: 4320 | C81: FS | D81: Zoha Munir | E81: 0600G182381 | F81: 35202-9887337-8 | H81: 35743 | I81: 45222 | K81: =MAX(0, MIN(M81, J81) - MAX(L81, I81) + 1) -> 31 | L81: 45352 | M81: 45382 | N81: =ROUNDUP(K81/31*320,0) -> 320 | O81: =N81*5 -> 1600 | P81: =N81+O81 -> 1920
P82: =sum(P2:P81) -> 134466

Sheet Apr-24
A1: EMP_AREA_CODE | B1: EMP_REG_SERIAL_NO | C1: EMP_SUB_AREA_CODE | D1: Name | E1: EOBI_NO | F1: CNIC | G1: NIC | H1: DOB | I1: DOJ | J1: DOE | K1: NO_OF_DAYS_WORKED | L1: From_Date | M1: To_Date | N1: Payment | O1: Employer Contribution | P1: Total EOBI
A2: FAA | B2: 4320 | C2: FS | D2: Abdul Hameed | E2: 4700J763957 | F2: 17301-6508006-1 | H2: 36617 | I2: 45299 | K2: =MAX(0, MIN(M2, J2) - MAX(L2, I2) + 1) -> 30 | L2: 45383 | M2: 45412 | N2: =ROUNDUP(K2/30*320,0) -> 320 | O2: =N2*5 -> 1600 | P2: =N2+O2 -> 1920
A3: FAA | B3: 4320 | C3: FS | D3: Abdul Moiez Akhtar | E3: 4700I763958 | F3: 34201-8434498-9 | H3: 37149 | I3: 45397 | K3: =MAX(0, MIN(M3, J3) - MAX(L3, I3) + 1) -> 16 | L3: 45383 | M3: 45412 | N3: =ROUNDUP(K3/30*320,0) -> 171 | O3: =N3*5 -> 855 | P3: =N3+O3 -> 1026
A4: FAA | B4: 4320 | C4: FS | D4: Abdul Rehan Najam | E4: 4700H764086 | F4: 61101-8333683-7 | H4: 37282 | I4: 45362 | K4: =MAX(0, MIN(M4, J4) - MAX(L4, I4) + 1) -> 30 | L4: 45383 | M4: 45412 | N4: =ROUNDUP(K4/30*320,0) -> 320 | O4: =N4*5 -> 1600 | P4: =N4+O4 -> 1920
A5: FAA | B5: 4320 | C5: FS | D5: Abdullah Bin Rashid | E5: 4700A705194 | F5: 61101-3101618-7 | H5: 36358 | I5: 45027 | K5: =MAX(0, MIN(M5, J5) - MAX(L5, I5) + 1) -> 30 | L5: 45383 | M5: 45412 | N5: =ROUNDUP(K5/30*320,0) -> 320 | O5: =N5*5 -> 1600 | P5: =N5+O5 -> 1920
A6: FAA | B6: 4320 | C6: FS | D6: Abdullah Rasheed | E6: 4700G688671 | F6: 37401-7271621-7 | H6: 36860 | I6: 45124 | K6: =MAX(0, MIN(M6, J6) - MAX(L6, I6) + 1) -> 30 | L6: 45383 | M6: 45412 | N6: =ROUNDUP(K6/30*320,0) -> 320 | O6: =N6*5 -> 1600 | P6: =N6+O6 -> 1920
A7: FAA | B7: 4320 | C7: FS | D7: Abu Usama | E7: 4700G764087 | F7: 36501-7651414-9 | H7: 35619 | I7: 45369 | J7: 45399 | K7: =MAX(0, MIN(M7, J7) - MAX(L7, I7) + 1) -> 17 | L7: 45383 | M7: 45412 | N7: =ROUNDUP(K7/30*320,0) -> 182 | O7: =N7*5 -> 910 | P7: =N7+O7 -> 1092
A8: FAA | B8: 4320 | C8: FS | D8: Ahmad Hassan | E8: 4600D315335 | F8: 37405-4246562-3 | H8: 35997 | I8: 45061 | K8: =MAX(0, MIN(M8, J8) - MAX(L8, I8) + 1) -> 30 | L8: 45383 | M8: 45412 | N8: =ROUNDUP(K8/30*320,0) -> 320 | O8: =N8*5 -> 1600 | P8: =N8+O8 -> 1920
A9: FAA | B9: 4320 | C9: FS | D9: Ahmed Hussain | E9: 4800F063920 | F9: 38102-5707136-9 | H9: 36353 | I9: 45278 | K9: =MAX(0, MIN(M9, J9) - MAX(L9, I9) + 1) -> 30 | L9: 45383 | M9: 45412 | N9: =ROUNDUP(K9/30*320,0) -> 320 | O9: =N9*5 -> 1600 | P9: =N9+O9 -> 1920
A10: FAA | B10: 4320 | C10: FS | D10: Ali Irfan | E10: 3100J940197 | F10: 35202-7336402-9 | H10: 36634 | I10: 45251 | K10: =MAX(0, MIN(M10, J10) - MAX(L10, I10) + 1) -> 30 | L10: 45383 | M10: 45412 | N10: =ROUNDUP(K10/30*320,0) -> 320 | O10: =N10*5 -> 1600 | P10: =N10+O10 -> 1920
A11: FAA | B11: 4320 | C11: FS | D11: Alina Shoaib | E11: 4700G764095 | F11: 37401-2006672-6 | H11: 36703 | I11: 45411 | J11: 45432 | K11: =MAX(0, MIN(M11, J11) - MAX(L11, I11) + 1) -> 2 | L11: 45383 | M11: 45412 | N11: =ROUNDUP(K11/30*320,0) -> 22 | O11: =N11*5 -> 110 | P11: =N11+O11 -> 132
A12: FAA | B12: 4320 | C12: FS | D12: Amish Tufail | E12: 4700H764094 | F12: 13302-2902324-3 | H12: 37274 | I12: 45362 | K12: =MAX(0, MIN(M12, J12) - MAX(L12, I12) + 1) -> 30 | L12: 45383 | M12: 45412 | N12: =ROUNDUP(K12/30*320,0) -> 320 | O12: =N12*5 -> 1600 | P12: =N12+O12 -> 1920
A13: FAA | B13: 4320 | C13: FS | D13: Anamil Mehtab | E13: 4700A710822 | F13: 37103-6819266-4 | H13: 37398 | I13: 45096 | K13: =MAX(0, MIN(M13, J13) - MAX(L13, I13) + 1) -> 30 | L13: 45383 | M13: 45412 | N13: =ROUNDUP(K13/30*320,0) -> 320 | O13: =N13*5 -> 1600 | P13: =N13+O13 -> 1920
A14: FAA | B14: 4320 | C14: FS | D14: Anas Hanif Attas | E14: 4700B665806 | F14: 38403-3251146-3 | H14: 36360 | I14: 45355 | K14: =MAX(0, MIN(M14, J14) - MAX(L14, I14) + 1) -> 30 | L14: 45383 | M14: 45412 | N14: =ROUNDUP(K14/30*320,0) -> 320 | O14: =N14*5 -> 1600 | P14: =N14+O14 -> 1920
A15: FAA | B15: 4320 | C15: FS | D15: Arsal Sher Khan | E15: 4700F764096 | F15: 35201-5498096-5 | H15: 37100 | I15: 45376 | J15: 45425 | K15: =MAX(0, MIN(M15, J15) - MAX(L15, I15) + 1) -> 30 | L15: 45383 | M15: 45412 | N15: =ROUNDUP(K15/30*320,0) -> 320 | O15: =N15*5 -> 1600 | P15: =N15+O15 -> 1920
A16: FAA | B16: 4320 | C16: FS | D16: Asad Ullah | E16: 4700C748792 | F16: 34401-8557347-3 | H16: 35047 | I16: 45257 | K16: =MAX(0, MIN(M16, J16) - MAX(L16, I16) + 1) -> 30 | L16: 45383 | M16: 45412 | N16: =ROUNDUP(K16/30*320,0) -> 320 | O16: =N16*5 -> 1600 | P16: =N16+O16 -> 1920
A17: FAA | B17: 4320 | C17: FS | D17: Asim Latif | E17: 4700A658224 | F17: 33302-5158556-5 | H17: 37370 | I17: 44739 | K17: =MAX(0, MIN(M17, J17) - MAX(L17, I17) + 1) -> 30 | L17: 45383 | M17: 45412 | N17: =ROUNDUP(K17/30*320,0) -> 320 | O17: =N17*5 -> 1600 | P17: =N17+O17 -> 1920
A18: FAA | B18: 4320 | C18: FS | D18: Atif Nawaz | E18: 4700E740695 | F18: 38404-7428636-7 | H18: 36399 | I18: 45229 | K18: =MAX(0, MIN(M18, J18) - MAX(L18, I18) + 1) -> 30 | L18: 45383 | M18: 45412 | N18: =ROUNDUP(K18/30*320,0) -> 320 | O18: =N18*5 -> 1600 | P18: =N18+O18 -> 1920
A19: FAA | B19: 4320 | C19: FS | D19: Ayesha Shakeel | E19: 4700H763959 | F19: 42301-1838144-6 | H19: 36962 | I19: 45376 | K19: =MAX(0, MIN(M19, J19) - MAX(L19, I19) + 1) -> 30 | L19: 45383 | M19: 45412 | N19: =ROUNDUP(K19/30*320,0) -> 320 | O19: =N19*5 -> 1600 | P19: =N19+O19 -> 1920
A20: FAA | B20: 4320 | C20: FS | D20: Ayesha Syed | E20: 4700E763960 | F20: 37405-5537896-0 | H20: 37377 | I20: 45334 | K20: =MAX(0, MIN(M20, J20) - MAX(L20, I20) + 1) -> 30 | L20: 45383 | M20: 45412 | N20: =ROUNDUP(K20/30*320,0) -> 320 | O20: =N20*5 -> 1600 | P20: =N20+O20 -> 1920
A21: FAA | B21: 4320 | C21: FS | D21: Basit Afraz | E21: 4700C703310 | F21: 37405-8019865-5 | H21: 34601 | I21: 44986 | K21: =MAX(0, MIN(M21, J21) - MAX(L21, I21) + 1) -> 30 | L21: 45383 | M21: 45412 | N21: =ROUNDUP(K21/30*320,0) -> 320 | O21: =N21*5 -> 1600 | P21: =N21+O21 -> 1920
A22: FAA | B22: 4320 | C22: FS | D22: Faiza Khan | E22: 4700J710823 | F22: 61101-0776147-2 | H22: 37322 | I22: 45096 | K22: =MAX(0, MIN(M22, J22) - MAX(L22, I22) + 1) -> 30 | L22: 45383 | M22: 45412 | N22: =ROUNDUP(K22/30*320,0) -> 320 | O22: =N22*5 -> 1600 | P22: =N22+O22 -> 1920
A23: FAA | B23: 4320 | C23: FS | D23: Faizan Khan | E23: 4700C662124 | F23: 16204-0388636-3 | H23: 35704 | I23: 44760 | K23: =MAX(0, MIN(M23, J23) - MAX(L23, I23) + 1) -> 30 | L23: 45383 | M23: 45412 | N23: =ROUNDUP(K23/30*320,0) -> 320 | O23: =N23*5 -> 1600 | P23: =N23+O23 -> 1920
A24: FAA | B24: 4320 | C24: FS | D24: Farzam Habib Khan | E24: 4700B748793 | F24: 12101-9669033-4 | H24: 37219 | I24: 45257 | K24: =MAX(0, MIN(M24, J24) - MAX(L24, I24) + 1) -> 30 | L24: 45383 | M24: 45412 | N24: =ROUNDUP(K24/30*320,0) -> 320 | O24: =N24*5 -> 1600 | P24: =N24+O24 -> 1920
A25: FAA | B25: 4320 | C25: FS | D25: Ghassan Sarfraz | E25: 3600I526143 | F25: 35202-4814639-9 | H25: 35871 | I25: 45369 | J25: 45419 | K25: =MAX(0, MIN(M25, J25) - MAX(L25, I25) + 1) -> 30 | L25: 45383 | M25: 45412 | N25: =ROUNDUP(K25/30*320,0) -> 320 | O25: =N25*5 -> 1600 | P25: =N25+O25 -> 1920
A26: FAA | B26: 4320 | C26: FS | D26: Hafsa Hassan | E26: 4700B764090 | F26: 37406-2194723-0 | H26: 36718 | I26: 45397 | K26: =MAX(0, MIN(M26, J26) - MAX(L26, I26) + 1) -> 16 | L26: 45383 | M26: 45412 | N26: =ROUNDUP(K26/30*320,0) -> 171 | O26: =N26*5 -> 855 | P26: =N26+O26 -> 1026
A27: FAA | B27: 4320 | C27: FS | D27: Hamza Ahmad | E27: 4700I678608 | F27: 37405-6689341-9 | H27: 36246 | I27: 44851 | K27: =MAX(0, MIN(M27, J27) - MAX(L27, I27) + 1) -> 30 | L27: 45383 | M27: 45412 | N27: =ROUNDUP(K27/30*320,0) -> 320 | O27: =N27*5 -> 1600 | P27: =N27+O27 -> 1920
A28: FAA | B28: 4320 | C28: FS | D28: Hamza Ali Khan | E28: 4700B690429 | F28: 37405-5700118-7 | H28: 35606 | I28: 44896 | K28: =MAX(0, MIN(M28, J28) - MAX(L28, I28) + 1) -> 30 | L28: 45383 | M28: 45412 | N28: =ROUNDUP(K28/30*320,0) -> 320 | O28: =N28*5 -> 1600 | P28: =N28+O28 -> 1920
A29: FAA | B29: 4320 | C29: FS | D29: Hira Farooq | E29: 4700B703311 | F29: 61101-2625195-8 | H29: 34973 | I29: 44986 | K29: =MAX(0, MIN(M29, J29) - MAX(L29, I29) + 1) -> 30 | L29: 45383 | M29: 45412 | N29: =ROUNDUP(K29/30*320,0) -> 320 | O29: =N29*5 -> 1600 | P29: =N29+O29 -> 1920
A30: FAA | B30: 4320 | C30: FS | D30: Humaira Amjad | E30: 4700A764091 | F30: 36302-7205229-8 | H30: 34590 | I30: 45313 | K30: =MAX(0, MIN(M30, J30) - MAX(L30, I30) + 1) -> 30 | L30: 45383 | M30: 45412 | N30: =ROUNDUP(K30/30*320,0) -> 320 | O30: =N30*5 -> 1600 | P30: =N30+O30 -> 1920
A31: FAA | B31: 4320 | C31: FS | D31: Ibrahim Shah | E31: 4700G658260 | F31: 35201-2147689-9 | H31: 36891 | I31: 44739 | K31: =MAX(0, MIN(M31, J31) - MAX(L31, I31) + 1) -> 30 | L31: 45383 | M31: 45412 | N31: =ROUNDUP(K31/30*320,0) -> 320 | O31: =N31*5 -> 1600 | P31: =N31+O31 -> 1920
A32: FAA | B32: 4320 | C32: FS | D32: Immar Karim | E32: 4700E720920 | F32: 43203-1564655-3 | H32: 37516 | I32: 45159 | K32: =MAX(0, MIN(M32, J32) - MAX(L32, I32) + 1) -> 30 | L32: 45383 | M32: 45412 | N32: =ROUNDUP(K32/30*320,0) -> 320 | O32: =N32*5 -> 1600 | P32: =N32+O32 -> 1920
A33: FAA | B33: 4320 | C33: FS | D33: Jalees Mukarram | E33: 4700G638367 | F33: 31201-9892348-9 | H33: 37210 | I33: 44125 | K33: =MAX(0, MIN(M33, J33) - MAX(L33, I33) + 1) -> 30 | L33: 45383 | M33: 45412 | N33: =ROUNDUP(K33/30*320,0) -> 320 | O33: =N33*5 -> 1600 | P33: =N33+O33 -> 1920
A34: FAA | B34: 4320 | C34: FS | D34: Khadija Umer | E34: 4700A710848 | F34: 31202-4982058-2 | H34: 36401 | I34: 45096 | K34: =MAX(0, MIN(M34, J34) - MAX(L34, I34) + 1) -> 30 | L34: 45383 | M34: 45412 | N34: =ROUNDUP(K34/30*320,0) -> 320 | O34: =N34*5 -> 1600 | P34: =N34+O34 -> 1920
A35: FAA | B35: 4320 | C35: FS | D35: Lamees Zafar | E35: 4700C763962 | F35: 36304-3814800-4 | H35: 37958 | I35: 45369 | K35: =MAX(0, MIN(M35, J35) - MAX(L35, I35) + 1) -> 30 | L35: 45383 | M35: 45412 | N35: =ROUNDUP(K35/30*320,0) -> 320 | O35: =N35*5 -> 1600 | P35: =N35+O35 -> 1920
A36: FAA | B36: 4320 | C36: FS | D36: Mirza Zain Ali Nasir | E36: 4700I764093 | F36: 35201-1057763-3 | H36: 36769 | I36: 45313 | J36: 45415 | K36: =MAX(0, MIN(M36, J36) - MAX(L36, I36) + 1) -> 30 | L36: 45383 | M36: 45412 | N36: =ROUNDUP(K36/30*320,0) -> 320 | O36: =N36*5 -> 1600 | P36: =N36+O36 -> 1920
A37: FAA | B37: 4320 | C37: FS | D37: Mohammad Ehtasham Balland | E37: 4700D711914 | F37: 36302-5494206-1 | H37: 33737 | I37: 45139 | K37: =MAX(0, MIN(M37, J37) - MAX(L37, I37) + 1) -> 30 | L37: 45383 | M37: 45412 | N37: =ROUNDUP(K37/30*320,0) -> 320 | O37: =N37*5 -> 1600 | P37: =N37+O37 -> 1920
A38: FAA | B38: 4320 | C38: FS | D38: Mohsin Ali Anjum | E38: 4700A763964 | F38: 37402-3744622-3 | H38: 35272 | I38: 45355 | K38: =MAX(0, MIN(M38, J38) - MAX(L38, I38) + 1) -> 30 | L38: 45383 | M38: 45412 | N38: =ROUNDUP(K38/30*320,0) -> 320 | O38: =N38*5 -> 1600 | P38: =N38+O38 -> 1920
A39: FAA | B39: 4320 | C39: FS | D39: Muawiz Umer | E39: 4700I763966 | F39: 31202-0967091-9 | H39: 37539 | I39: 45362 | K39: =MAX(0, MIN(M39, J39) - MAX(L39, I39) + 1) -> 30 | L39: 45383 | M39: 45412 | N39: =ROUNDUP(K39/30*320,0) -> 320 | O39: =N39*5 -> 1600 | P39: =N39+O39 -> 1920
A40: FAA | B40: 4320 | C40: FS | D40: Muhammad Abdullah Salam | E40: 4700G697010 | F40: 17301-7752570-9 | H40: 36690 | I40: 44938 | K40: =MAX(0, MIN(M40, J40) - MAX(L40, I40) + 1) -> 30 | L40: 45383 | M40: 45412 | N40: =ROUNDUP(K40/30*320,0) -> 320 | O40: =N40*5 -> 1600 | P40: =N40+O40 -> 1920
A41: FAA | B41: 4320 | C41: FS | D41: Muhammad Abubakar | E41: 4700H723959 | F41: 35201-8046049-1 | H41: 37240 | I41: 45176 | K41: =MAX(0, MIN(M41, J41) - MAX(L41, I41) + 1) -> 30 | L41: 45383 | M41: 45412 | N41: =ROUNDUP(K41/30*320,0) -> 320 | O41: =N41*5 -> 1600 | P41: =N41+O41 -> 1920
A42: FAA | B42: 4320 | C42: FS | D42: Muhammad Adnan | E42: 4700A638371 | F42: 54401-7578020-9 | H42: 33240 | I42: 44287 | K42: =MAX(0, MIN(M42, J42) - MAX(L42, I42) + 1) -> 30 | L42: 45383 | M42: 45412 | N42: =ROUNDUP(K42/30*320,0) -> 320 | O42: =N42*5 -> 1600 | P42: =N42+O42 -> 1920
A43: FAA | B43: 4320 | C43: FS | D43: Muhammad Ali Kiyani | E43: 4700I483207 | F43: 61101-7478749-3 | H43: 35173 | I43: 45264 | K43: =MAX(0, MIN(M43, J43) - MAX(L43, I43) + 1) -> 30 | L43: 45383 | M43: 45412 | N43: =ROUNDUP(K43/30*320,0) -> 320 | O43: =N43*5 -> 1600 | P43: =N43+O43 -> 1920
A44: FAA | B44: 4320 | C44: FS | D44: Muhammad Anas Khan | E44: 4700J764084 | F44: 31202-1004575-1 | H44: 37964 | I44: 45355 | K44: =MAX(0, MIN(M44, J44) - MAX(L44, I44) + 1) -> 30 | L44: 45383 | M44: 45412 | N44: =ROUNDUP(K44/30*320,0) -> 320 | O44: =N44*5 -> 1600 | P44: =N44+O44 -> 1920
A45: FAA | B45: 4320 | C45: FS | D45: Muhammad Arham | E45: 4700J673932 | F45: 36103-7439746-1 | H45: 37136 | I45: 45201 | J45: 45390 | K45: =MAX(0, MIN(M45, J45) - MAX(L45, I45) + 1) -> 8 | L45: 45383 | M45: 45412 | N45: =ROUNDUP(K45/30*320,0) -> 86 | O45: =N45*5 -> 430 | P45: =N45+O45 -> 516
A46: FAA | B46: 4320 | C46: FS | D46: Muhammad Asadullah Shahid | E46: 4700G581544 | F46: 36603-1234883-1 | H46: 35943 | I46: 45215 | K46: =MAX(0, MIN(M46, J46) - MAX(L46, I46) + 1) -> 30 | L46: 45383 | M46: 45412 | N46: =ROUNDUP(K46/30*320,0) -> 320 | O46: =N46*5 -> 1600 | P46: =N46+O46 -> 1920
A47: FAA | B47: 4320 | C47: FS | D47: Muhammad Bilal Tanveer | E47: 4700D763961 | F47: 82203-3459651-7 | H47: 35551 | I47: 45383 | K47: =MAX(0, MIN(M47, J47) - MAX(L47, I47) + 1) -> 30 | L47: 45383 | M47: 45412 | N47: =ROUNDUP(K47/30*320,0) -> 320 | O47: =N47*5 -> 1600 | P47: =N47+O47 -> 1920
A48: FAA | B48: 4320 | C48: FS | D48: Muhammad Hammad Maqsood | E48: 4700A703312 | F48: 37405-2794891-9 | H48: 36898 | I48: 44988 | K48: =MAX(0, MIN(M48, J48) - MAX(L48, I48) + 1) -> 30 | L48: 45383 | M48: 45412 | N48: =ROUNDUP(K48/30*320,0) -> 320 | O48: =N48*5 -> 1600 | P48: =N48+O48 -> 1920
A49: FAA | B49: 4320 | C49: FS | D49: Muhammad Hassan Shakeel | E49: 4700H690431 | F49: 35402-2593513-5 | H49: 36794 | I49: 44915 | K49: =MAX(0, MIN(M49, J49) - MAX(L49, I49) + 1) -> 30 | L49: 45383 | M49: 45412 | N49: =ROUNDUP(K49/30*320,0) -> 320 | O49: =N49*5 -> 1600 | P49: =N49+O49 -> 1920
A50: FAA | B50: 4320 | C50: FS | D50: Muhammad Ibrahim | E50: 4700C720948 | F50: 31101-0776303-7 | H50: 37149 | I50: 45124 | K50: =MAX(0, MIN(M50, J50) - MAX(L50, I50) + 1) -> 30 | L50: 45383 | M50: 45412 | N50: =ROUNDUP(K50/30*320,0) -> 320 | O50: =N50*5 -> 1600 | P50: =N50+O50 -> 1920
A51: FAA | B51: 4320 | C51: FS | D51: Muhammad Osama Ehsaan | E51: 4700B764082 | F51: 31203-9951845-1 | H51: 36821 | I51: 45362 | K51: =MAX(0, MIN(M51, J51) - MAX(L51, I51) + 1) -> 30 | L51: 45383 | M51: 45412 | N51: =ROUNDUP(K51/30*320,0) -> 320 | O51: =N51*5 -> 1600 | P51: =N51+O51 -> 1920
A52: FAA | B52: 4320 | C52: FS | D52: Muhammad Umair Nasar | E52: 4700G764079 | F52: 35202-7433048-7 | H52: 36778 | I52: 45369 | K52: =MAX(0, MIN(M52, J52) - MAX(L52, I52) + 1) -> 30 | L52: 45383 | M52: 45412 | N52: =ROUNDUP(K52/30*320,0) -> 320 | O52: =N52*5 -> 1600 | P52: =N52+O52 -> 1920
A53: FAA | B53: 4320 | C53: FS | D53: Muhammad Uzaimah Mushtaq | E53: 4700J764076 | F53: 38201-8328241-1 | H53: 37085 | I53: 45400 | K53: =MAX(0, MIN(M53, J53) - MAX(L53, I53) + 1) -> 13 | L53: 45383 | M53: 45412 | N53: =ROUNDUP(K53/30*320,0) -> 139 | O53: =N53*5 -> 695 | P53: =N53+O53 -> 834
A54: FAA | B54: 4320 | C54: FS | D54: Muhammad Waleed Abdullah | E54: 4700I764077 | F54: 36601-1635702-5 | H54: 37647 | I54: 45355 | K54: =MAX(0, MIN(M54, J54) - MAX(L54, I54) + 1) -> 30 | L54: 45383 | M54: 45412 | N54: =ROUNDUP(K54/30*320,0) -> 320 | O54: =N54*5 -> 1600 | P54: =N54+O54 -> 1920
A55: FAA | B55: 4320 | C55: FS | D55: Muhammad Zahab Ahmed | E55: 3600G329844 | F55: 31102-2135283-9 | H55: 34300 | I55: 45183 | K55: =MAX(0, MIN(M55, J55) - MAX(L55, I55) + 1) -> 30 | L55: 45383 | M55: 45412 | N55: =ROUNDUP(K55/30*320,0) -> 320 | O55: =N55*5 -> 1600 | P55: =N55+O55 -> 1920
A56: FAA | B56: 4320 | C56: FS | D56: Muiz Hussain | E56: 4600F352555 | F56: 42301-8666708-3 | H56: 36412 | I56: 45355 | K56: =MAX(0, MIN(M56, J56) - MAX(L56, I56) + 1) -> 30 | L56: 45383 | M56: 45412 | N56: =ROUNDUP(K56/30*320,0) -> 320 | O56: =N56*5 -> 1600 | P56: =N56+O56 -> 1920
A57: FAA | B57: 4320 | C57: FS | D57: Musa Naqvi
A58: FAA | B58: 4320 | C58: FS | D58: Naimal Imran | E58: 4700J662127 | F58: 35202-0754928-4 | H58: 36541 | I58: 44755 | J58: 45386 | K58: =MAX(0, MIN(M58, J58) - MAX(L58, I58) + 1) -> 4 | L58: 45383 | M58: 45412 | N58: =ROUNDUP(K58/30*320,0) -> 43 | O58: =N58*5 -> 215 | P58: =N58+O58 -> 258
A59: FAA | B59: 4320 | C59: FS | D59: Namra Akram | E59: 4700F444303 | F59: 61101-4919576-8 | H59: 34335 | I59: 45078 | J59: 45400 | K59: =MAX(0, MIN(M59, J59) - MAX(L59, I59) + 1) -> 18 | L59: 45383 | M59: 45412 | N59: =ROUNDUP(K59/30*320,0) -> 192 | O59: =N59*5 -> 960 | P59: =N59+O59 -> 1152
A60: FAA | B60: 4320 | C60: FS | D60: Naveed Ahmed | E60: 4700H679736 | F60: 42201-5462974-9 | H60: 31014 | I60: 44805 | K60: =MAX(0, MIN(M60, J60) - MAX(L60, I60) + 1) -> 30 | L60: 45383 | M60: 45412 | N60: =ROUNDUP(K60/30*320,0) -> 320 | O60: =N60*5 -> 1600 | P60: =N60+O60 -> 1920
A61: FAA | B61: 4320 | C61: FS | D61: Nimra Zahid | E61: 4700G537391 | F61: 42201-1439506-4 | H61: 34522 | I61: 45292 | K61: =MAX(0, MIN(M61, J61) - MAX(L61, I61) + 1) -> 30 | L61: 45383 | M61: 45412 | N61: =ROUNDUP(K61/30*320,0) -> 320 | O61: =N61*5 -> 1600 | P61: =N61+O61 -> 1920
A62: FAA | B62: 4320 | C62: FS | D62: Rashid Iqbal | E62: 4700I703314 | F62: 37405-6880780-7 | H62: 34732 | I62: 44986 | K62: =MAX(0, MIN(M62, J62) - MAX(L62, I62) + 1) -> 30 | L62: 45383 | M62: 45412 | N62: =ROUNDUP(K62/30*320,0) -> 320 | O62: =N62*5 -> 1600 | P62: =N62+O62 -> 1920
A63: FAA | B63: 4320 | C63: FS | D63: Saad Ahmed | E63: 0800E406072 | F63: 35202-3107480-5 | H63: 33762 | I63: 45229 | K63: =MAX(0, MIN(M63, J63) - MAX(L63, I63) + 1) -> 31 | L63: 45261 | M63: 45291 | N63: =ROUNDUP(K63/31*320,0) -> 320 | O63: =N63*5 -> 1600 | P63: =N63+O63 -> 1920
A64: FAA | B64: 4320 | C64: FS | D64: Sabdezar Irfan | E64: 3600G465789 | F64: 35201-1547140-8 | H64: 35395 | I64: 45376 | K64: =MAX(0, MIN(M64, J64) - MAX(L64, I64) + 1) -> 30 | L64: 45383 | M64: 45412 | N64: =ROUNDUP(K64/30*320,0) -> 320 | O64: =N64*5 -> 1600 | P64: =N64+O64 -> 1920
A65: FAA | B65: 4320 | C65: FS | D65: Saboor Ahmad | E65: 4700D763937 | F65: 61101-8448365-1 | H65: 37397 | I65: 45377 | K65: =MAX(0, MIN(M65, J65) - MAX(L65, I65) + 1) -> 30 | L65: 45383 | M65: 45412 | N65: =ROUNDUP(K65/30*320,0) -> 320 | O65: =N65*5 -> 1600 | P65: =N65+O65 -> 1920
A66: FAA | B66: 4320 | C66: FS | D66: Saif Ullah | E66: 4700A764083 | F66: 61101-5764361-9 | H66: 37479 | I66: 45320 | K66: =MAX(0, MIN(M66, J66) - MAX(L66, I66) + 1) -> 30 | L66: 45383 | M66: 45412 | N66: =ROUNDUP(K66/30*320,0) -> 320 | O66: =N66*5 -> 1600 | P66: =N66+O66 -> 1920
A67: FAA | B67: 4320 | C67: FS | D67: Salman Khalid | E67: 3300B264525 | F67: 34603-0435168-5 | H67: 33003 | I67: 45313 | K67: =MAX(0, MIN(M67, J67) - MAX(L67, I67) + 1) -> 30 | L67: 45383 | M67: 45412 | N67: =ROUNDUP(K67/30*320,0) -> 320 | O67: =N67*5 -> 1600 | P67: =N67+O67 -> 1920
A68: FAA | B68: 4320 | C68: FS | D68: Sana Sajjad Chaudhary | E68: 4700F740694 | F68: 37301-3885164-8 | H68: 36109 | I68: 45250 | K68: =MAX(0, MIN(M68, J68) - MAX(L68, I68) + 1) -> 30 | L68: 45383 | M68: 45412 | N68: =ROUNDUP(K68/30*320,0) -> 320 | O68: =N68*5 -> 1600 | P68: =N68+O68 -> 1920
A69: FAA | B69: 4320 | C69: FS | D69: Sana Tahir | E69: 4700D706561 | F69: 37103-2235902-2 | H69: 35976 | I69: 45042 | K69: =MAX(0, MIN(M69, J69) - MAX(L69, I69) + 1) -> 30 | L69: 45383 | M69: 45412 | N69: =ROUNDUP(K69/30*320,0) -> 320 | O69: =N69*5 -> 1600 | P69: =N69+O69 -> 1920
A70: FAA | B70: 4320 | C70: FS | D70: Shaheryar Ehsan I Haque | E70: 4700C763938 | F70: 37405-6028477-3 | H70: 36289 | I70: 45383 | K70: =MAX(0, MIN(M70, J70) - MAX(L70, I70) + 1) -> 30 | L70: 45383 | M70: 45412 | N70: =ROUNDUP(K70/30*320,0) -> 320 | O70: =N70*5 -> 1600 | P70: =N70+O70 -> 1920
A71: FAA | B71: 4320 | C71: FS | D71: Shahzad Farooq | E71: 4700G690432 | F71: 42501-8133748-7 | H71: 36979 | I71: 44907 | K71: =MAX(0, MIN(M71, J71) - MAX(L71, I71) + 1) -> 30 | L71: 45383 | M71: 45412 | N71: =ROUNDUP(K71/30*320,0) -> 320 | O71: =N71*5 -> 1600 | P71: =N71+O71 -> 1920
A72: FAA | B72: 4320 | C72: FS | D72: Shaiq Habib | E72: 0400C579124 | F72: 61101-1388832-7 | H72: 36421 | I72: 45208 | K72: =MAX(0, MIN(M72, J72) - MAX(L72, I72) + 1) -> 30 | L72: 45383 | M72: 45412 | N72: =ROUNDUP(K72/30*320,0) -> 320 | O72: =N72*5 -> 1600 | P72: =N72+O72 -> 1920
A73: FAA | B73: 4320 | C73: FS | D73: Shan Ahmad | E73: 4700C748360 | F73: 35202-9717455-5 | H73: 35447 | I73: 45273 | K73: =MAX(0, MIN(M73, J73) - MAX(L73, I73) + 1) -> 30 | L73: 45383 | M73: 45412 | N73: =ROUNDUP(K73/30*320,0) -> 320 | O73: =N73*5 -> 1600 | P73: =N73+O73 -> 1920
A74: FAA | B74: 4320 | C74: FS | D74: Subhana Yasin | E74: 4700E723960 | F74: 36502-1828819-0 | H74: 36574 | I74: 45187 | K74: =MAX(0, MIN(M74, J74) - MAX(L74, I74) + 1) -> 30 | L74: 45383 | M74: 45412 | N74: =ROUNDUP(K74/30*320,0) -> 320 | O74: =N74*5 -> 1600 | P74: =N74+O74 -> 1920
A75: FAA | B75: 4320 | C75: FS | D75: Sukaina Ali | E75: 4700C688544 | F75: 37405-6240250-8 | H75: 36991 | I75: 45205 | K75: =MAX(0, MIN(M75, J75) - MAX(L75, I75) + 1) -> 30 | L75: 45383 | M75: 45412 | N75: =ROUNDUP(K75/30*320,0) -> 320 | O75: =N75*5 -> 1600 | P75: =N75+O75 -> 1920
... A79: FAA | B79: 4320 | C79: FS | D79: Umaira Jabeen | E79: 3600J522091 | F79: 37104-5371430-8 | H79: 33769 | I79: 44816 | K79: =MAX(0, MIN(M79, J79) - MAX(L79, I79) + 1) -> 30 | L79: 45383 | M79: 45412 | N79: =ROUNDUP(K79/30*320,0) -> 320 | O79: =N79*5 -> 1600 | P79: =N79+O79 -> 1920
A80: FAA | B80: 4320 | C80: FS | D80: Umar Farooq | E80: 4700D723961 | F80: 36501-4241566-9 | H80: 36408 | I80: 45173 | J80: 45412 | K80: =MAX(0, MIN(M80, J80) - MAX(L80, I80) + 1) -> 30 | L80: 45383 | M80: 45412 | N80: =ROUNDUP(K80/30*320,0) -> 320 | O80: =N80*5 -> 1600 | P80: =N80+O80 -> 1920
A81: FAA | B81: 4320 | C81: FS | D81: Waleed Sadiq | E81: 4700C710870 | F81: 82101-6085499-3 | H81: 35818 | I81: 45089 | K81: =MAX(0, MIN(M81, J81) - MAX(L81, I81) + 1) -> 30 | L81: 45383 | M81: 45412 | N81: =ROUNDUP(K81/30*320,0) -> 320 | O81: =N81*5 -> 1600 | P81: =N81+O81 -> 1920
A82: FAA | B82: 4320 | C82: FS | D82: Zain Shahid | E82: 4700H700799 | F82: 36401-6591078-1 | H82: 36177 | I82: 45320 | K82: =MAX(0, MIN(M82, J82) - MAX(L82, I82) + 1) -> 30 | L82: 45383 | M82: 45412 | N82: =ROUNDUP(K82/30*320,0) -> 320 | O82: =N82*5 -> 1600 | P82: =N82+O82 -> 1920
A83: FAA | B83: 4320 | C83: FS | D83: Zeeshan Nasir | E83: 4700J764092 | F83: 37405-3360545-9 | H83: 36522 | I83: 45328 | K83: =MAX(0, MIN(M83, J83) - MAX(L83, I83) + 1) -> 30 | L83: 45383 | M83: 45412 | N83: =ROUNDUP(K83/30*320,0) -> 320 | O83: =N83*5 -> 1600 | P83: =N83+O83 -> 1920
A84: FAA | B84: 4320 | C84: FS | D84: Zoha Munir | E84: 0600G182381 | F84: 35202-9887337-8 | H84: 35743 | I84: 45222 | K84: =MAX(0, MIN(M84, J84) - MAX(L84, I84) + 1) -> 30 | L84: 45383 | M84: 45412 | N84: =ROUNDUP(K84/30*320,0) -> 320 | O84: =N84*5 -> 1600 | P84: =N84+O84 -> 1920
P85: =SUM(P2:P84) -> 148116

Sheet May-24
A1: EMP_AREA_CODE | B1: EMP_REG_SERIAL_NO | C1: EMP_SUB_AREA_CODE | D1: Name | E1: EOBI_NO | F1: CNIC | G1: NIC | H1: DOB | I1: DOJ | J1: DOE | K1: NO_OF_DAYS_WORKED | L1: From_Date | M1: To_Date | N1: Employee Contribution | P1: Employer Contribution | Q1: Total EOBI
A2: FAA | B2: 4320 | C2: FS | D2: Abdul Hameed | E2: 4700J763957 | F2: 17301-6508006-1 | H2: 36617 | I2: 45299 | K2: =MAX(0, MIN(M2, J2) - MAX(L2, I2) + 1) -> 31 | L2: 45413 | M2: 45443 | N2: =ROUNDUP(K2/31*320,0) -> 320 | O2: 320 | P2: =N2*5 -> 1600 | Q2: =N2+P2 -> 1920
A3: FAA | B3: 4320 | C3: FS | D3: Abdul Moiez Akhtar | E3: 4700I763958 | F3: 34201-8434498-9 | H3: 37149 | I3: 45397 | K3: =MAX(0, MIN(M3, J3) - MAX(L3, I3) + 1) -> 31 | L3: 45413 | M3: 45443 | N3: =ROUNDUP(K3/31*320,0) -> 320 | O3: 320 | P3: =N3*5 -> 1600 | Q3: =N3+P3 -> 1920
A4: FAA | B4: 4320 | C4: FS | D4: Abdul Rehan Najam | E4: 4700H764086 | F4: 61101-8333683-7 | H4: 37282 | I4: 45362 | K4: =MAX(0, MIN(M4, J4) - MAX(L4, I4) + 1) -> 31 | L4: 45413 | M4: 45443 | N4: =ROUNDUP(K4/31*320,0) -> 320 | O4: 320 | P4: =N4*5 -> 1600 | Q4: =N4+P4 -> 1920
A5: FAA | B5: 4320 | C5: FS | D5: Abdullah Bin Rashid | E5: 4700A705194 | F5: 61101-3101618-7 | H5: 36358 | I5: 45027 | K5: =MAX(0, MIN(M5, J5) - MAX(L5, I5) + 1) -> 31 | L5: 45413 | M5: 45443 | N5: =ROUNDUP(K5/31*320,0) -> 320 | O5: 320 | P5: =N5*5 -> 1600 | Q5: =N5+P5 -> 1920
A6: FAA | B6: 4320 | C6: FS | D6: Abdullah Rasheed | E6: 4700G688671 | F6: 37401-7271621-7 | H6: 36860 | I6: 45124 | K6: =MAX(0, MIN(M6, J6) - MAX(L6, I6) + 1) -> 31 | L6: 45413 | M6: 45443 | N6: =ROUNDUP(K6/31*320,0) -> 320 | O6: 320 | P6: =N6*5 -> 1600 | Q6: =N6+P6 -> 1920
A7: FAA | B7: 4320 | C7: FS | D7: Ahmad Hassan | E7: 4600D315335 | F7: 37405-4246562-3 | H7: 35997 | I7: 45061 | K7: =MAX(0, MIN(M7, J7) - MAX(L7, I7) + 1) -> 31 | L7: 45413 | M7: 45443 | N7: =ROUNDUP(K7/31*320,0) -> 320 | O7: 320 | P7: =N7*5 -> 1600 | Q7: =N7+P7 -> 1920
A8: FAA | B8: 4320 | C8: FS | D8: Ahmed Hussain | E8: 4800F063920 | F8: 38102-5707136-9 | H8: 36353 | I8: 45278 | K8: =MAX(0, MIN(M8, J8) - MAX(L8, I8) + 1) -> 31 | L8: 45413 | M8: 45443 | N8: =ROUNDUP(K8/31*320,0) -> 320 | O8: 320 | P8: =N8*5 -> 1600 | Q8: =N8+P8 -> 1920
A9: FAA | B9: 4320 | C9: FS | D9: Aiman Daud | E9: 4700C764099 | F9: 37404-5596830-8 | H9: 35669 | I9: 45418 | K9: =MAX(0, MIN(M9, J9) - MAX(L9, I9) + 1) -> 26 | L9: 45413 | M9: 45443 | N9: =ROUNDUP(K9/31*320,0) -> 269 | O9: 268.3871 | P9: =N9*5 -> 1345 | Q9: =N9+P9 -> 1614
A10: FAA | B10: 4320 | C10: FS | D10: Ali Irfan | E10: 3100J940197 | F10: 35202-7336402-9 | H10: 36634 | I10: 45251 | J10: 45422 | K10: =MAX(0, MIN(M10, J10) - MAX(L10, I10) + 1) -> 10 | L10: 45413 | M10: 45443 | N10: =ROUNDUP(K10/31*320,0) -> 104 | O10: 103.22581 | P10: =N10*5 -> 520 | Q10: =N10+P10 -> 624
A11: FAA | B11: 4320 | C11: FS | D11: Alina Shoaib | E11: 4700G764095 | F11: 37401-2006672-6 | H11: 36703 | I11: 45411 | J11: 45434 | K11: =MAX(0, MIN(M11, J11) - MAX(L11, I11) + 1) -> 22 | L11: 45413 | M11: 45443 | N11: 227 | O11: 227.09677 | P11: =N11*5 -> 1135 | Q11: =N11+P11 -> 1362
A12: FAA | B12: 4320 | C12: FS | D12: Amish Tufail | E12: 4700H764094 | F12: 13302-2902324-3 | H12: 37274 | I12: 45362 | K12: =MAX(0, MIN(M12, J12) - MAX(L12, I12) + 1) -> 31 | L12: 45413 | M12: 45443 | N12: =ROUNDUP(K12/31*320,0) -> 320 | O12: 320 | P12: =N12*5 -> 1600 | Q12: =N12+P12 -> 1920
A13: FAA | B13: 4320 | C13: FS | D13: Anamil Mehtab | E13: 4700A710822 | F13: 37103-6819266-4 | H13: 37398 | I13: 45096 | K13: =MAX(0, MIN(M13, J13) - MAX(L13, I13) + 1) -> 31 | L13: 45413 | M13: 45443 | N13: =ROUNDUP(K13/31*320,0) -> 320 | O13: 320 | P13: =N13*5 -> 1600 | Q13: =N13+P13 -> 1920
A14: FAA | B14: 4320 | C14: FS | D14: Anas Hanif Attas | E14: 4700B665806 | F14: 38403-3251146-3 | H14: 36360 | I14: 45355 | K14: =MAX(0, MIN(M14, J14) - MAX(L14, I14) + 1) -> 31 | L14: 45413 | M14: 45443 | N14: =ROUNDUP(K14/31*320,0) -> 320 | O14: 320 | P14: =N14*5 -> 1600 | Q14: =N14+P14 -> 1920
A15: FAA | B15: 4320 | C15: FS | D15: Arsal Sher Khan | E15: 4700F764096 | F15: 35201-5498096-5 | H15: 37100 | I15: 45376 | J15: 45425 | K15: =MAX(0, MIN(M15, J15) - MAX(L15, I15) + 1) -> 13 | L15: 45413 | M15: 45443 | N15: =ROUNDUP(K15/31*320,0) -> 135 | O15: 134.19355 | P15: =N15*5 -> 675 | Q15: =N15+P15 -> 810
A16: FAA | B16: 4320 | C16: FS | D16: Asad Ullah | E16: 4700C748792 | F16: 34401-8557347-3 | H16: 35047 | I16: 45257 | K16: =MAX(0, MIN(M16, J16) - MAX(L16, I16) + 1) -> 31 | L16: 45413 | M16: 45443 | N16: =ROUNDUP(K16/31*320,0) -> 320 | O16: 320 | P16: =N16*5 -> 1600 | Q16: =N16+P16 -> 1920
A17: FAA | B17: 4320 | C17: FS | D17: Asim Latif | E17: 4700A658224 | F17: 33302-5158556-5 | H17: 37370 | I17: 44739 | K17: =MAX(0, MIN(M17, J17) - MAX(L17, I17) + 1) -> 31 | L17: 45413 | M17: 45443 | N17: =ROUNDUP(K17/31*320,0) -> 320 | O17: 320 | P17: =N17*5 -> 1600 | Q17: =N17+P17 -> 1920
A18: FAA | B18: 4320 | C18: FS | D18: Atif Nawaz | E18: 4700E740695 | F18: 38404-7428636-7 | H18: 36399 | I18: 45229 | K18: =MAX(0, MIN(M18, J18) - MAX(L18, I18) + 1) -> 31 | L18: 45413 | M18: 45443 | N18: =ROUNDUP(K18/31*320,0) -> 320 | O18: 320 | P18: =N18*5 -> 1600 | Q18: =N18+P18 -> 1920
A19: FAA | B19: 4320 | C19: FS | D19: Aun Ishfaq | E19: 4700E764097 | F19: 90403-0143681-7 | H19: 36183 | I19: 45413 | K19: =MAX(0, MIN(M19, J19) - MAX(L19, I19) + 1) -> 31 | L19: 45413 | M19: 45443 | N19: =ROUNDUP(K19/31*320,0) -> 320 | O19: 320 | P19: =N19*5 -> 1600 | Q19: =N19+P19 -> 1920
A20: FAA | B20: 4320 | C20: FS | D20: Ayesha Nasir | E20: 4700G764100 | F20: 37405-8603058-0 | H20: 37144 | I20: 45418 | K20: =MAX(0, MIN(M20, J20) - MAX(L20, I20) + 1) -> 26 | L20: 45413 | M20: 45443 | N20: =ROUNDUP(K20/31*320,0) -> 269 | O20: 268.3871 | P20: =N20*5 -> 1345 | Q20: =N20+P20 -> 1614
A21: FAA | B21: 4320 | C21: FS | D21: Ayesha Shakeel | E21: 4700H763959 | F21: 42301-1838144-6 | H21: 36962 | I21: 45376 | K21: =MAX(0, MIN(M21, J21) - MAX(L21, I21) + 1) -> 31 | L21: 45413 | M21: 45443 | N21: =ROUNDUP(K21/31*320,0) -> 320 | O21: 320 | P21: =N21*5 -> 1600 | Q21: =N21+P21 -> 1920
A22: FAA | B22: 4320 | C22: FS | D22: Ayesha Syed | E22: 4700E763960 | F22: 37405-5537896-0 | H22: 37377 | I22: 45334 | K22: =MAX(0, MIN(M22, J22) - MAX(L22, I22) + 1) -> 31 | L22: 45413 | M22: 45443 | N22: =ROUNDUP(K22/31*320,0) -> 320 | O22: 320 | P22: =N22*5 -> 1600 | Q22: =N22+P22 -> 1920
A23: FAA | B23: 4320 | C23: FS | D23: Basit Afraz | E23: 4700C703310 | F23: 37405-8019865-5 | H23: 34601 | I23: 44986 | K23: =MAX(0, MIN(M23, J23) - MAX(L23, I23) + 1) -> 31 | L23: 45413 | M23: 45443 | N23: =ROUNDUP(K23/31*320,0) -> 320 | O23: 320 | P23: =N23*5 -> 1600 | Q23: =N23+P23 -> 1920
A24: FAA | B24: 4320 | C24: FS | D24: Faiza Khan | E24: 4700J710823 | F24: 61101-0776147-2 | H24: 37322 | I24: 45096 | K24: =MAX(0, MIN(M24, J24) - MAX(L24, I24) + 1) -> 31 | L24: 45413 | M24: 45443 | N24: =ROUNDUP(K24/31*320,0) -> 320 | O24: 320 | P24: =N24*5 -> 1600 | Q24: =N24+P24 -> 1920
A25: FAA | B25: 4320 | C25: FS | D25: Faizan Khan | E25: 4700C662124 | F25: 16204-0388636-3 | H25: 35704 | I25: 44760 | K25: =MAX(0, MIN(M25, J25) - MAX(L25, I25) + 1) -> 31 | L25: 45413 | M25: 45443 | N25: =ROUNDUP(K25/31*320,0) -> 320 | O25: 320 | P25: =N25*5 -> 1600 | Q25: =N25+P25 -> 1920
A26: FAA | B26: 4320 | C26: FS | D26: Farzam Habib Khan | E26: 4700B748793 | F26: 12101-9669033-4 | H26: 37219 | I26: 45257 | K26: =MAX(0, MIN(M26, J26) - MAX(L26, I26) + 1) -> 31 | L26: 45413 | M26: 45443 | N26: =ROUNDUP(K26/31*320,0) -> 320 | O26: 320 | P26: =N26*5 -> 1600 | Q26: =N26+P26 -> 1920
A27: FAA | B27: 4320 | C27: FS | D27: Ghassan Sarfraz | E27: 3600I526143 | F27: 35202-4814639-9 | H27: 35871 | I27: 45369 | J27: 45419 | K27: =MAX(0, MIN(M27, J27) - MAX(L27, I27) + 1) -> 7 | L27: 45413 | M27: 45443 | N27: =ROUNDUP(K27/31*320,0) -> 73 | O27: 72.258065 | P27: =N27*5 -> 365 | Q27: =N27+P27 -> 438
A28: FAA | B28: 4320 | C28: FS | D28: Hafsa Hassan | E28: 4700B764090 | F28: 37406-2194723-0 | H28: 36718 | I28: 45397 | K28: =MAX(0, MIN(M28, J28) - MAX(L28, I28) + 1) -> 31 | L28: 45413 | M28: 45443 | N28: =ROUNDUP(K28/31*320,0) -> 320 | O28: 320 | P28: =N28*5 -> 1600 | Q28: =N28+P28 -> 1920
A29: FAA | B29: 4320 | C29: FS | D29: Hamza Ahmad | E29: 4700I678608 | F29: 37405-6689341-9 | H29: 36246 | I29: 44851 | K29: =MAX(0, MIN(M29, J29) - MAX(L29, I29) + 1) -> 31 | L29: 45413 | M29: 45443 | N29: =ROUNDUP(K29/31*320,0) -> 320 | O29: 320 | P29: =N29*5 -> 1600 | Q29: =N29+P29 -> 1920
A30: FAA | B30: 4320 | C30: FS | D30: Hamza Ali Khan | E30: 4700B690429 | F30: 37405-5700118-7 | H30: 35606 | I30: 44896 | K30: =MAX(0, MIN(M30, J30) - MAX(L30, I30) + 1) -> 31 | L30: 45413 | M30: 45443 | N30: =ROUNDUP(K30/31*320,0) -> 320 | O30: 320 | P30: =N30*5 -> 1600 | Q30: =N30+P30 -> 1920
A31: FAA | B31: 4320 | C31: FS | D31: Hamza Mughal | E31: 4700F739740 | F31: 13501-9345271-1 | H31: 36111 | I31: 45418 | K31: =MAX(0, MIN(M31, J31) - MAX(L31, I31) + 1) -> 26 | L31: 45413 | M31: 45443 | N31: =ROUNDUP(K31/31*320,0) -> 269 | O31: 268.3871 | P31: =N31*5 -> 1345 | Q31: =N31+P31 -> 1614
A32: FAA | B32: 4320 | C32: FS | D32: Hira Farooq | E32: 4700B703311 | F32: 61101-2625195-8 | H32: 34973 | I32: 44986 | K32: =MAX(0, MIN(M32, J32) - MAX(L32, I32) + 1) -> 31 | L32: 45413 | M32: 45443 | N32: =ROUNDUP(K32/31*320,0) -> 320 | O32: 320 | P32: =N32*5 -> 1600 | Q32: =N32+P32 -> 1920
A33: FAA | B33: 4320 | C33: FS | D33: Humaira Amjad | E33: 4700A764091 | F33: 36302-7205229-8 | H33: 34590 | I33: 45313 | K33: =MAX(0, MIN(M33, J33) - MAX(L33, I33) + 1) -> 31 | L33: 45413 | M33: 45443 | N33: =ROUNDUP(K33/31*320,0) -> 320 | O33: 320 | P33: =N33*5 -> 1600 | Q33: =N33+P33 -> 1920
A34: FAA | B34: 4320 | C34: FS | D34: Ibrahim Shah | E34: 4700G658260 | F34: 35201-2147689-9 | H34: 36891 | I34: 44739 | K34: =MAX(0, MIN(M34, J34) - MAX(L34, I34) + 1) -> 31 | L34: 45413 | M34: 45443 | N34: =ROUNDUP(K34/31*320,0) -> 320 | O34: 320 | P34: =N34*5 -> 1600 | Q34: =N34+P34 -> 1920
A35: FAA | B35: 4320 | C35: FS | D35: Immar Karim | E35: 4700E720920 | F35: 43203-1564655-3 | H35: 37516 | I35: 45159 | K35: =MAX(0, MIN(M35, J35) - MAX(L35, I35) + 1) -> 31 | L35: 45413 | M35: 45443 | N35: =ROUNDUP(K35/31*320,0) -> 320 | O35: 320 | P35: =N35*5 -> 1600 | Q35: =N35+P35 -> 1920
A36: FAA | B36: 4320 | C36: FS | D36: Jalees Mukarram | E36: 4700G638367 | F36: 31201-9892348-9 | H36: 37210 | I36: 44125 | J36: 45442 | K36: =MAX(0, MIN(M36, J36) - MAX(L36, I36) + 1) -> 30 | L36: 45413 | M36: 45443 | N36: =ROUNDUP(K36/31*320,0) -> 310 | O36: 309.67742 | P36: =N36*5 -> 1550 | Q36: =N36+P36 -> 1860
A37: FAA | B37: 4320 | C37: FS | D37: Khadija Umer | E37: 4700A710848 | F37: 31202-4982058-2 | H37: 36401 | I37: 45096 | K37: =MAX(0, MIN(M37, J37) - MAX(L37, I37) + 1) -> 31 | L37: 45413 | M37: 45443 | N37: =ROUNDUP(K37/31*320,0) -> 320 | O37: 320 | P37: =N37*5 -> 1600 | Q37: =N37+P37 -> 1920
A38: FAA | B38: 4320 | C38: FS | D38: Lamees Zafar | E38: 4700C763962 | F38: 36304-3814800-4 | H38: 37958 | I38: 45369 | K38: =MAX(0, MIN(M38, J38) - MAX(L38, I38) + 1) -> 31 | L38: 45413 | M38: 45443 | N38: =ROUNDUP(K38/31*320,0) -> 320 | O38: 320 | P38: =N38*5 -> 1600 | Q38: =N38+P38 -> 1920
A39: FAA | B39: 4320 | C39: FS | D39: Luqman Ahmed | E39: 4700D764098 | F39: 37102-2088988-7 | H39: 34922 | I39: 45418 | K39: =MAX(0, MIN(M39, J39) - MAX(L39, I39) + 1) -> 26 | L39: 45413 | M39: 45443 | N39: =ROUNDUP(K39/31*320,0) -> 269 | O39: 268.3871 | P39: =N39*5 -> 1345 | Q39: =N39+P39 -> 1614
A40: FAA | B40: 4320 | C40: FS | D40: Mirza Zain Ali Nasir | E40: 4700I764093 | F40: 35201-1057763-3 | H40: 36769 | I40: 45313 | J40: 45415 | K40: =MAX(0, MIN(M40, J40) - MAX(L40, I40) + 1) -> 3 | L40: 45413 | M40: 45443 | N40: =ROUNDUP(K40/31*320,0) -> 31 | O40: 30.967742 | P40: =N40*5 -> 155 | Q40: =N40+P40 -> 186
A41: FAA | B41: 4320 | C41: FS | D41: Mohammad Ehtasham Balland | E41: 4700D711914 | F41: 36302-5494206-1 | H41: 33737 | I41: 45139 | K41: =MAX(0, MIN(M41, J41) - MAX(L41, I41) + 1) -> 31 | L41: 45413 | M41: 45443 | N41: =ROUNDUP(K41/31*320,0) -> 320 | O41: 320 | P41: =N41*5 -> 1600 | Q41: =N41+P41 -> 1920
A42: FAA | B42: 4320 | C42: FS | D42: Mohsin Ali Anjum | E42: 4700A763964 | F42: 37402-3744622-3 | H42: 35272 | I42: 45355 | K42: =MAX(0, MIN(M42, J42) - MAX(L42, I42) + 1) -> 31 | L42: 45413 | M42: 45443 | N42: =ROUNDUP(K42/31*320,0) -> 320 | O42: 320 | P42: =N42*5 -> 1600 | Q42: =N42+P42 -> 1920
A43: FAA | B43: 4320 | C43: FS | D43: Muawiz Umer | E43: 4700I763966 | F43: 31202-0967091-9 | H43: 37539 | I43: 45362 | K43: =MAX(0, MIN(M43, J43) - MAX(L43, I43) + 1) -> 31 | L43: 45413 | M43: 45443 | N43: =ROUNDUP(K43/31*320,0) -> 320 | O43: 320 | P43: =N43*5 -> 1600 | Q43: =N43+P43 -> 1920
A44: FAA | B44: 4320 | C44: FS | D44: Muhammad Abdullah Salam | E44: 4700G697010 | F44: 17301-7752570-9 | H44: 36690 | I44: 44938 | K44: =MAX(0, MIN(M44, J44) - MAX(L44, I44) + 1) -> 31 | L44: 45413 | M44: 45443 | N44: =ROUNDUP(K44/31*320,0) -> 320 | O44: 320 | P44: =N44*5 -> 1600 | Q44: =N44+P44 -> 1920
A45: FAA | B45: 4320 | C45: FS | D45: Muhammad Abubakar | E45: 4700H723959 | F45: 35201-8046049-1 | H45: 37240 | I45: 45176 | K45: =MAX(0, MIN(M45, J45) - MAX(L45, I45) + 1) -> 31 | L45: 45413 | M45: 45443 | N45: =ROUNDUP(K45/31*320,0) -> 320 | O45: 320 | P45: =N45*5 -> 1600 | Q45: =N45+P45 -> 1920
A46: FAA | B46: 4320 | C46: FS | D46: Muhammad Adnan | E46: 4700A638371 | F46: 54401-7578020-9 | H46: 33240 | I46: 44287 | K46: =MAX(0, MIN(M46, J46) - MAX(L46, I46) + 1) -> 31 | L46: 45413 | M46: 45443 | N46: =ROUNDUP(K46/31*320,0) -> 320 | O46: 320 | P46: =N46*5 -> 1600 | Q46: =N46+P46 -> 1920
A47: FAA | B47: 4320 | C47: FS | D47: Muhammad Ali Kiyani | E47: 4700I483207 | F47: 61101-7478749-3 | H47: 35173 | I47: 45264 | K47: =MAX(0, MIN(M47, J47) - MAX(L47, I47) + 1) -> 31 | L47: 45413 | M47: 45443 | N47: =ROUNDUP(K47/31*320,0) -> 320 | O47: 320 | P47: =N47*5 -> 1600 | Q47: =N47+P47 -> 1920
A48: FAA | B48: 4320 | C48: FS | D48: Muhammad Anas Khan | E48: 4700J764084 | F48: 31202-1004575-1 | H48: 37964 | I48: 45355 | K48: =MAX(0, MIN(M48, J48) - MAX(L48, I48) + 1) -> 31 | L48: 45413 | M48: 45443 | N48: =ROUNDUP(K48/31*320,0) -> 320 | O48: 320 | P48: =N48*5 -> 1600 | Q48: =N48+P48 -> 1920
A49: FAA | B49: 4320 | C49: FS | D49: Muhammad Asadullah Shahid | E49: 4700G581544 | F49: 36603-1234883-1 | H49: 35943 | I49: 45215 | K49: =MAX(0, MIN(M49, J49) - MAX(L49, I49) + 1) -> 31 | L49: 45413 | M49: 45443 | N49: =ROUNDUP(K49/31*320,0) -> 320 | O49: 320 | P49: =N49*5 -> 1600 | Q49: =N49+P49 -> 1920
A50: FAA | B50: 4320 | C50: FS | D50: Muhammad Ayan Baig | E50: 4700E764102 | F50: 36302-5170382-5 | H50: 36557 | I50: 45432 | K50: =MAX(0, MIN(M50, J50) - MAX(L50, I50) + 1) -> 12 | L50: 45413 | M50: 45443 | N50: =ROUNDUP(K50/31*320,0) -> 124 | O50: 123.87097 | P50: =N50*5 -> 620 | Q50: =N50+P50 -> 744
A51: FAA | B51: 4320 | C51: FS | D51: Muhammad Bilal Tanveer | E51: 4700D763961 | F51: 82203-3459651-7 | H51: 35551 | I51: 45383 | K51: =MAX(0, MIN(M51, J51) - MAX(L51, I51) + 1) -> 31 | L51: 45413 | M51: 45443 | N51: =ROUNDUP(K51/31*320,0) -> 320 | O51: 320 | P51: =N51*5 -> 1600 | Q51: =N51+P51 -> 1920
A52: FAA | B52: 4320 | C52: FS | D52: Muhammad Hassan Shakeel | E52: 4700H690431 | F52: 35402-2593513-5 | H52: 36794 | I52: 44915 | K52: =MAX(0, MIN(M52, J52) - MAX(L52, I52) + 1) -> 31 | L52: 45413 | M52: 45443 | N52: =ROUNDUP(K52/31*320,0) -> 320 | O52: 320 | P52: =N52*5 -> 1600 | Q52: =N52+P52 -> 1920
... A66: FAA | B66: 4320 | C66: FS | D66: Saif Ullah | E66: 4700A764083 | F66: 61101-5764361-9 | H66: 37479 | I66: 45320 | K66: =MAX(0, MIN(M66, J66) - MAX(L66, I66) + 1) -> 31 | L66: 45413 | M66: 45443 | N66: =ROUNDUP(K66/31*320,0) -> 320 | O66: 320 | P66: =N66*5 -> 1600 | Q66: =N66+P66 -> 1920
A67: FAA | B67: 4320 | C67: FS | D67: Salman Khalid | E67: 3300B264525 | F67: 34603-0435168-5 | H67: 33003 | I67: 45313 | J67: 45434 | K67: =MAX(0, MIN(M67, J67) - MAX(L67, I67) + 1) -> 22 | L67: 45413 | M67: 45443 | N67: =ROUNDUP(K67/31*320,0) -> 228 | O67: 227.09677 | P67: =N67*5 -> 1140 | Q67: =N67+P67 -> 1368
A68: FAA | B68: 4320 | C68: FS | D68: Sana Sajjad Chaudhary | E68: 4700F740694 | F68: 37301-3885164-8 | H68: 36109 | I68: 45250 | J68: 45416 | K68: =MAX(0, MIN(M68, J68) - MAX(L68, I68) + 1) -> 4 | L68: 45413 | M68: 45443 | N68: =ROUNDUP(K68/31*320,0) -> 42 | O68: 41.290323 | P68: =N68*5 -> 210 | Q68: =N68+P68 -> 252
A69: FAA | B69: 4320 | C69: FS | D69: Sana Tahir | E69: 4700D706561 | F69: 37103-2235902-2 | H69: 35976 | I69: 45042 | K69: =MAX(0, MIN(M69, J69) - MAX(L69, I69) + 1) -> 31 | L69: 45413 | M69: 45443 | N69: =ROUNDUP(K69/31*320,0) -> 320 | O69: 320 | P69: =N69*5 -> 1600 | Q69: =N69+P69 -> 1920
A70: FAA | B70: 4320 | C70: FS | D70: Shaheryar Ehsan I Haque | E70: 4700C763938 | F70: 37405-6028477-3 | H70: 36289 | I70: 45383 | J70: 45433 | K70: =MAX(0, MIN(M70, J70) - MAX(L70, I70) + 1) -> 21 | L70: 45413 | M70: 45443 | N70: =ROUNDUP(K70/31*320,0) -> 217 | O70: 216.77419 | P70: =N70*5 -> 1085 | Q70: =N70+P70 -> 1302
A71: FAA | B71: 4320 | C71: FS | D71: Shahzad Farooq | E71: 4700G690432 | F71: 42501-8133748-7 | H71: 36979 | I71: 44907 | K71: =MAX(0, MIN(M71, J71) - MAX(L71, I71) + 1) -> 31 | L71: 45413 | M71: 45443 | N71: =ROUNDUP(K71/31*320,0) -> 320 | O71: 320 | P71: =N71*5 -> 1600 | Q71: =N71+P71 -> 1920
A72: FAA | B72: 4320 | C72: FS | D72: Shaiq Habib | E72: 0400C579124 | F72: 61101-1388832-7 | H72: 36421 | I72: 45208 | K72: =MAX(0, MIN(M72, J72) - MAX(L72, I72) + 1) -> 31 | L72: 45413 | M72: 45443 | N72: =ROUNDUP(K72/31*320,0) -> 320 | O72: 320 | P72: =N72*5 -> 1600 | Q72: =N72+P72 -> 1920
A73: FAA | B73: 4320 | C73: FS | D73: Shan Ahmad | E73: 4700C748360 | F73: 35202-9717455-5 | H73: 35447 | I73: 45273 | K73: =MAX(0, MIN(M73, J73) - MAX(L73, I73) + 1) -> 31 | L73: 45413 | M73: 45443 | N73: =ROUNDUP(K73/31*320,0) -> 320 | O73: 320 | P73: =N73*5 -> 1600 | Q73: =N73+P73 -> 1920
A74: FAA | B74: 4320 | C74: FS | D74: Subhana Yasin | E74: 4700E723960 | F74: 36502-1828819-0 | H74: 36574 | I74: 45187 | K74: =MAX(0, MIN(M74, J74) - MAX(L74, I74) + 1) -> 31 | L74: 45413 | M74: 45443 | N74: =ROUNDUP(K74/31*320,0) -> 320 | O74: 320 | P74: =N74*5 -> 1600 | Q74: =N74+P74 -> 1920
A75: FAA | B75: 4320 | C75: FS | D75: Sukaina Ali | E75: 4700C688544 | F75: 37405-6240250-8 | H75: 36991 | I75: 45205 | K75: =MAX(0, MIN(M75, J75) - MAX(L75, I75) + 1) -> 31 | L75: 45413 | M75: 45443 | N75: =ROUNDUP(K75/31*320,0) -> 320 | O75: 320 | P75: =N75*5 -> 1600 | Q75: =N75+P75 -> 1920
A76: FAA | B76: 4320 | C76: FS | D76: Syed Maaz Ahmed | E76: 0500A167653 | F76: 42101-8025278-5 | H76: 36433 | I76: 45432 | K76: =MAX(0, MIN(M76, J76) - MAX(L76, I76) + 1) -> 12 | L76: 45413 | M76: 45443 | N76: =ROUNDUP(K76/31*320,0) -> 124 | O76: 123.87097 | P76: =N76*5 -> 620 | Q76: =N76+P76 -> 744
A77: FAA | B77: 4320 | C77: FS | D77: Talha Arshad Malik | E77: 3600F372686 | F77: 37405-6378563-1 | H77: 33156 | I77: 44285 | K77: =MAX(0, MIN(M77, J77) - MAX(L77, I77) + 1) -> 31 | L77: 45413 | M77: 45443 | N77: =ROUNDUP(K77/31*320,0) -> 320 | O77: 320 | P77: =N77*5 -> 1600 | Q77: =N77+P77 -> 1920
A78: FAA | B78: 4320 | C78: FS | D78: Tauqeer Ahmed | E78: 4700H764078 | F78: 35201-5043196-1 | H78: 35697 | I78: 45348 | K78: =MAX(0, MIN(M78, J78) - MAX(L78, I78) + 1) -> 31 | L78: 45413 | M78: 45443 | N78: =ROUNDUP(K78/31*320,0) -> 320 | O78: 320 | P78: =N78*5 -> 1600 | Q78: =N78+P78 -> 1920
A79: FAA | B79: 4320 | C79: FS | D79: Tayyab Abbas | E79: 4700A685051 | F79: 17301-2752063-7 | H79: 36797 | I79: 44886 | K79: =MAX(0, MIN(M79, J79) - MAX(L79, I79) + 1) -> 31 | L79: 45413 | M79: 45443 | N79: =ROUNDUP(K79/31*320,0) -> 320 | O79: 320 | P79: =N79*5 -> 1600 | Q79: =N79+P79 -> 1920
A80: FAA | B80: 4320 | C80: FS | D80: Umaira Jabeen | E80: 3600J522091 | F80: 37104-5371430-8 | H80: 33769 | I80: 44816 | K80: =MAX(0, MIN(M80, J80) - MAX(L80, I80) + 1) -> 31 | L80: 45413 | M80: 45443 | N80: =ROUNDUP(K80/31*320,0) -> 320 | O80: 320 | P80: =N80*5 -> 1600 | Q80: =N80+P80 -> 1920
A81: FAA | B81: 4320 | C81: FS | D81: Umar Sheraz | E81: 3600C583492 | F81: 38403-8907880-9 | H81: 35973 | I81: 45414 | K81: =MAX(0, MIN(M81, J81) - MAX(L81, I81) + 1) -> 30 | L81: 45413 | M81: 45443 | N81: =ROUNDUP(K81/31*320,0) -> 310 | O81: 309.67742 | P81: =N81*5 -> 1550 | Q81: =N81+P81 -> 1860
A82: FAA | B82: 4320 | C82: FS | D82: Waleed Sadiq | E82: 4700C710870 | F82: 82101-6085499-3 | H82: 35818 | I82: 45089 | K82: =MAX(0, MIN(M82, J82) - MAX(L82, I82) + 1) -> 31 | L82: 45413 | M82: 45443 | N82: =ROUNDUP(K82/31*320,0) -> 320 | O82: 320 | P82: =N82*5 -> 1600 | Q82: =N82+P82 -> 1920
... A85: FAA | B85: 4320 | C85: FS | D85: Zoha Munir | E85: 0600G182381 | F85: 35202-9887337-8 | H85: 35743 | I85: 45222 | K85: =MAX(0, MIN(M85, J85) - MAX(L85, I85) + 1) -> 31 | L85: 45413 | M85: 45443 | N85: =ROUNDUP(K85/31*320,0) -> 320 | O85: 320 | P85: =N85*5 -> 1600 | Q85: =N85+P85 -> 1920
Q86: =SUM(Q2:Q85) -> 148260

Sheet Jun-24
A1: EMP_AREA_CODE | B1: EMP_REG_SERIAL_NO | C1: EMP_SUB_AREA_CODE | D1: Name | E1: EOBI_NO | F1: CNIC | G1: NIC | H1: DOB | I1: DOJ | J1: DOE | K1: NO_OF_DAYS_WORKED | L1: From_Date | M1: To_Date | N1: Employee Contribution | O1: Employer Contribution | P1: Total EOBI
A2: FAA | B2: 4320 | C2: FS | D2: Abdul Hameed | E2: 4700J763957 | F2: 17301-6508006-1 | H2: 36617 | I2: 45299 | K2: =MAX(0, MIN(M2, J2) - MAX(L2, I2) + 1) -> 30 | L2: 45444 | M2: 45473 | N2: =ROUNDUP(K2/30*320,0) -> 320 | O2: =N2*5 -> 1600 | P2: =N2+O2 -> 1920
A3: FAA | B3: 4320 | C3: FS | D3: Abdul Moiez Akhtar | E3: 4700I763958 | F3: 34201-8434498-9 | H3: 37149 | I3: 45397 | K3: =MAX(0, MIN(M3, J3) - MAX(L3, I3) + 1) -> 30 | L3: 45444 | M3: 45473 | N3: =ROUNDUP(K3/30*320,0) -> 320 | O3: =N3*5 -> 1600 | P3: =N3+O3 -> 1920
A4: FAA | B4: 4320 | C4: FS | D4: Abdullah Bin Rashid | E4: 4700A705194 | F4: 61101-3101618-7 | H4: 36358 | I4: 45027 | K4: =MAX(0, MIN(M4, J4) - MAX(L4, I4) + 1) -> 30 | L4: 45444 | M4: 45473 | N4: =ROUNDUP(K4/30*320,0) -> 320 | O4: =N4*5 -> 1600 | P4: =N4+O4 -> 1920
A5: FAA | B5: 4320 | C5: FS | D5: Abdullah Rasheed | E5: 4700G688671 | F5: 37401-7271621-7 | H5: 36860 | I5: 45124 | K5: =MAX(0, MIN(M5, J5) - MAX(L5, I5) + 1) -> 30 | L5: 45444 | M5: 45473 | N5: =ROUNDUP(K5/30*320,0) -> 320 | O5: =N5*5 -> 1600 | P5: =N5+O5 -> 1920
A6: FAA | B6: 4320 | C6: FS | D6: Abdullah Salam | E6: 4700G697010 | F6: 17301-7752570-9 | H6: 36690 | I6: 44938 | K6: =MAX(0, MIN(M6, J6) - MAX(L6, I6) + 1) -> 30 | L6: 45444 | M6: 45473 | N6: =ROUNDUP(K6/30*320,0) -> 320 | O6: =N6*5 -> 1600 | P6: =N6+O6 -> 1920
A7: FAA | B7: 4320 | C7: FS | D7: Adil Ali | E7: 4700H780618 | F7: 37405-7507683-3 | H7: 37978 | I7: 45453 | K7: 21 | L7: 45453 | M7: 45473 | N7: =ROUNDUP(K7/30*320,0) -> 224 | O7: =N7*5 -> 1120 | P7: =N7+O7 -> 1344
A8: FAA | B8: 4320 | C8: FS | D8: Ahmad Hassan | E8: 4600D315335 | F8: 37405-4246562-3 | H8: 35997 | I8: 45061 | K8: =MAX(0, MIN(M8, J8) - MAX(L8, I8) + 1) -> 30 | L8: 45444 | M8: 45473 | N8: =ROUNDUP(K8/30*320,0) -> 320 | O8: =N8*5 -> 1600 | P8: =N8+O8 -> 1920
A9: FAA | B9: 4320 | C9: FS | D9: Ahmed Hussain | E9: 4800F063920 | F9: 38102-5707136-9 | H9: 36353 | I9: 45278 | K9: =MAX(0, MIN(M9, J9) - MAX(L9, I9) + 1) -> 30 | L9: 45444 | M9: 45473 | N9: =ROUNDUP(K9/30*320,0) -> 320 | O9: =N9*5 -> 1600 | P9: =N9+O9 -> 1920
A10: FAA | B10: 4320 | C10: FS | D10: Aiman Daud | E10: 4700C764099 | F10: 37404-5596830-8 | H10: 35669 | I10: 45418 | K10: =MAX(0, MIN(M10, J10) - MAX(L10, I10) + 1) -> 30 | L10: 45444 | M10: 45473 | N10: =ROUNDUP(K10/30*320,0) -> 320 | O10: =N10*5 -> 1600 | P10: =N10+O10 -> 1920
A11: FAA | B11: 4320 | C11: FS | D11: Amish Tufail | E11: 4700H764094 | F11: 13302-2902324-3 | H11: 37274 | I11: 45362 | K11: =MAX(0, MIN(M11, J11) - MAX(L11, I11) + 1) -> 30 | L11: 45444 | M11: 45473 | N11: =ROUNDUP(K11/30*320,0) -> 320 | O11: =N11*5 -> 1600 | P11: =N11+O11 -> 1920
A12: FAA | B12: 4320 | C12: FS | D12: Anamil Mehtab | E12: 4700A710822 | F12: 37103-6819266-4 | H12: 37398 | I12: 45096 | K12: =MAX(0, MIN(M12, J12) - MAX(L12, I12) + 1) -> 30 | L12: 45444 | M12: 45473 | N12: =ROUNDUP(K12/30*320,0) -> 320 | O12: =N12*5 -> 1600 | P12: =N12+O12 -> 1920
A13: FAA | B13: 4320 | C13: FS | D13: Anas Hanif Attas | E13: 4700B665806 | F13: 38403-3251146-3 | H13: 36360 | I13: 45355 | K13: =MAX(0, MIN(M13, J13) - MAX(L13, I13) + 1) -> 30 | L13: 45444 | M13: 45473 | N13: =ROUNDUP(K13/30*320,0) -> 320 | O13: =N13*5 -> 1600 | P13: =N13+O13 -> 1920
A14: FAA | B14: 4320 | C14: FS | D14: Annum Inam | E14: 4700D780620 | F14: 61101-7960847-6 | H14: 33230 | I14: 45453 | K14: 21 | L14: 45453 | M14: 45473 | N14: =ROUNDUP(K14/30*320,0) -> 224 | O14: =N14*5 -> 1120 | P14: =N14+O14 -> 1344
A15: FAA | B15: 4320 | C15: FS | D15: Asad Ullah | E15: 4700C748792 | F15: 34401-8557347-3 | H15: 35047 | I15: 45257 | K15: =MAX(0, MIN(M15, J15) - MAX(L15, I15) + 1) -> 30 | L15: 45444 | M15: 45473 | N15: =ROUNDUP(K15/30*320,0) -> 320 | O15: =N15*5 -> 1600 | P15: =N15+O15 -> 1920
A16: FAA | B16: 4320 | C16: FS | D16: Asim Latif | E16: 4700A658224 | F16: 33302-5158556-5 | H16: 37370 | I16: 44739 | K16: =MAX(0, MIN(M16, J16) - MAX(L16, I16) + 1) -> 30 | L16: 45444 | M16: 45473 | N16: =ROUNDUP(K16/30*320,0) -> 320 | O16: =N16*5 -> 1600 | P16: =N16+O16 -> 1920
A17: FAA | B17: 4320 | C17: FS | D17: Atif Nawaz | E17: 4700E740695 | F17: 38404-7428636-7 | H17: 36399 | I17: 45229 | K17: =MAX(0, MIN(M17, J17) - MAX(L17, I17) + 1) -> 30 | L17: 45444 | M17: 45473 | N17: =ROUNDUP(K17/30*320,0) -> 320 | O17: =N17*5 -> 1600 | P17: =N17+O17 -> 1920
A18: FAA | B18: 4320 | C18: FS | D18: Aun Ishfaq | E18: 4700E764097 | F18: 90403-0143681-7 | H18: 36183 | I18: 45418 | K18: =MAX(0, MIN(M18, J18) - MAX(L18, I18) + 1) -> 30 | L18: 45444 | M18: 45473 | N18: =ROUNDUP(K18/30*320,0) -> 320 | O18: =N18*5 -> 1600 | P18: =N18+O18 -> 1920
A19: FAA | B19: 4320 | C19: FS | D19: Ayesha Nasir | E19: 4700G764100 | F19: 37405-8603058-0 | H19: 37144 | I19: 45418 | K19: =MAX(0, MIN(M19, J19) - MAX(L19, I19) + 1) -> 30 | L19: 45444 | M19: 45473 | N19: =ROUNDUP(K19/30*320,0) -> 320 | O19: =N19*5 -> 1600 | P19: =N19+O19 -> 1920
A20: FAA | B20: 4320 | C20: FS | D20: Ayesha Shakeel | E20: 4700H763959 | F20: 42301-1838144-6 | H20: 36962 | I20: 45376 | K20: =MAX(0, MIN(M20, J20) - MAX(L20, I20) + 1) -> 30 | L20: 45444 | M20: 45473 | N20: =ROUNDUP(K20/30*320,0) -> 320 | O20: =N20*5 -> 1600 | P20: =N20+O20 -> 1920
A21: FAA | B21: 4320 | C21: FS | D21: Ayesha Syed | E21: 4700E763960 | F21: 37405-5537896-0 | H21: 37377 | I21: 45334 | K21: =MAX(0, MIN(M21, J21) - MAX(L21, I21) + 1) -> 30 | L21: 45444 | M21: 45473 | N21: =ROUNDUP(K21/30*320,0) -> 320 | O21: =N21*5 -> 1600 | P21: =N21+O21 -> 1920
A22: FAA | B22: 4320 | C22: FS | D22: Ayesha Tahir | E22: 4700A748794 | F22: 13101-5843018-0 | H22: 37047 | I22: 45453 | K22: =MAX(0, MIN(M22, J22) - MAX(L22, I22) + 1) -> 21 | L22: 45444 | M22: 45473 | N22: =ROUNDUP(K22/30*320,0) -> 224 | O22: =N22*5 -> 1120 | P22: =N22+O22 -> 1344
A23: FAA | B23: 4320 | C23: FS | D23: Basit Afraz | E23: 4700C703310 | F23: 37405-8019865-5 | H23: 34601 | I23: 44986 | K23: =MAX(0, MIN(M23, J23) - MAX(L23, I23) + 1) -> 30 | L23: 45444 | M23: 45473 | N23: =ROUNDUP(K23/30*320,0) -> 320 | O23: =N23*5 -> 1600 | P23: =N23+O23 -> 1920
A24: FAA | B24: 4320 | C24: FS | D24: Faiza Khan | E24: 4700J710823 | F24: 61101-0776147-2 | H24: 37322 | I24: 45096 | K24: =MAX(0, MIN(M24, J24) - MAX(L24, I24) + 1) -> 30 | L24: 45444 | M24: 45473 | N24: =ROUNDUP(K24/30*320,0) -> 320 | O24: =N24*5 -> 1600 | P24: =N24+O24 -> 1920
A25: FAA | B25: 4320 | C25: FS | D25: Faizan Khan | E25: 4700C662124 | F25: 16204-0388636-3 | H25: 35704 | I25: 44760 | K25: =MAX(0, MIN(M25, J25) - MAX(L25, I25) + 1) -> 30 | L25: 45444 | M25: 45473 | N25: =ROUNDUP(K25/30*320,0) -> 320 | O25: =N25*5 -> 1600 | P25: =N25+O25 -> 1920
A26: FAA | B26: 4320 | C26: FS | D26: Farzam Habib Khan | E26: 4700B748793 | F26: 12101-9669033-4 | H26: 37219 | I26: 45257 | K26: =MAX(0, MIN(M26, J26) - MAX(L26, I26) + 1) -> 30 | L26: 45444 | M26: 45473 | N26: =ROUNDUP(K26/30*320,0) -> 320 | O26: =N26*5 -> 1600 | P26: =N26+O26 -> 1920
... A33: FAA | B33: 4320 | C33: FS | D33: Ibrahim Shah | E33: 4700G658260 | F33: 35201-2147689-9 | H33: 36891 | I33: 44739 | K33: =MAX(0, MIN(M33, J33) - MAX(L33, I33) + 1) -> 30 | L33: 45444 | M33: 45473 | N33: =ROUNDUP(K33/30*320,0) -> 320 | O33: =N33*5 -> 1600 | P33: =N33+O33 -> 1920
A34: FAA | B34: 4320 | C34: FS | D34: Immar Karim | E34: 4700E720920 | F34: 43203-1564655-3 | H34: 37516 | I34: 45159 | J34: 45450 | K34: =MAX(0, MIN(M34, J34) - MAX(L34, I34) + 1) -> 7 | L34: 45444 | M34: 45473 | N34: =ROUNDUP(K34/30*320,0) -> 75 | O34: =N34*5 -> 375 | P34: =N34+O34 -> 450
A35: FAA | B35: 4320 | C35: FS | D35: Khadija Umer | E35: 4700A710848 | F35: 31202-4982058-2 | H35: 36401 | I35: 45096 | K35: =MAX(0, MIN(M35, J35) - MAX(L35, I35) + 1) -> 30 | L35: 45444 | M35: 45473 | N35: =ROUNDUP(K35/30*320,0) -> 320 | O35: =N35*5 -> 1600 | P35: =N35+O35 -> 1920
A36: FAA | B36: 4320 | C36: FS | D36: Lamees Zafar | E36: 4700C763962 | F36: 36304-3814800-4 | H36: 37958 | I36: 45369 | K36: =MAX(0, MIN(M36, J36) - MAX(L36, I36) + 1) -> 30 | L36: 45444 | M36: 45473 | N36: =ROUNDUP(K36/30*320,0) -> 320 | O36: =N36*5 -> 1600 | P36: =N36+O36 -> 1920
A37: FAA | B37: 4320 | C37: FS | D37: Luqman Ahmed | E37: 4700D764098 | F37: 37102-2088988-7 | H37: 34922 | I37: 45418 | K37: =MAX(0, MIN(M37, J37) - MAX(L37, I37) + 1) -> 30 | L37: 45444 | M37: 45473 | N37: =ROUNDUP(K37/30*320,0) -> 320 | O37: =N37*5 -> 1600 | P37: =N37+O37 -> 1920
A38: FAA | B38: 4320 | C38: FS | D38: Misbah Aziz | F38: 36602-2764423-2 | H38: 36443 | I38: 45446 | K38: 28 | L38: 45446 | M38: 45473 | N38: =ROUNDUP(K38/30*320,0) -> 299 | O38: =N38*5 -> 1495 | P38: =N38+O38 -> 1794
A39: FAA | B39: 4320 | C39: FS | D39: Mohammad Ehtasham Balland | E39: 4700D711914 | F39: 36302-5494206-1 | H39: 33737 | I39: 45139 | K39: =MAX(0, MIN(M39, J39) - MAX(L39, I39) + 1) -> 30 | L39: 45444 | M39: 45473 | N39: =ROUNDUP(K39/30*320,0) -> 320 | O39: =N39*5 -> 1600 | P39: =N39+O39 -> 1920
A40: FAA | B40: 4320 | C40: FS | D40: Mohsin Ali Anjum | E40: 4700A763964 | F40: 37402-3744622-3 | H40: 35272 | I40: 45355 | K40: =MAX(0, MIN(M40, J40) - MAX(L40, I40) + 1) -> 30 | L40: 45444 | M40: 45473 | N40: =ROUNDUP(K40/30*320,0) -> 320 | O40: =N40*5 -> 1600 | P40: =N40+O40 -> 1920
A41: FAA | B41: 4320 | C41: FS | D41: Muawiz Umer | E41: 4700I763966 | F41: 31202-0967091-9 | H41: 37539 | I41: 45362 | K41: =MAX(0, MIN(M41, J41) - MAX(L41, I41) + 1) -> 30 | L41: 45444 | M41: 45473 | N41: =ROUNDUP(K41/30*320,0) -> 320 | O41: =N41*5 -> 1600 | P41: =N41+O41 -> 1920
A42: FAA | B42: 4320 | C42: FS | D42: Muhammad Abubakar | E42: 4700H723959 | F42: 35201-8046049-1 | H42: 37240 | I42: 45176 | K42: =MAX(0, MIN(M42, J42) - MAX(L42, I42) + 1) -> 30 | L42: 45444 | M42: 45473 | N42: =ROUNDUP(K42/30*320,0) -> 320 | O42: =N42*5 -> 1600 | P42: =N42+O42 -> 1920
A43: FAA | B43: 4320 | C43: FS | D43: Muhammad Adnan | E43: 4700A638371 | F43: 54401-7578020-9 | H43: 33240 | I43: 44287 | K43: =MAX(0, MIN(M43, J43) - MAX(L43, I43) + 1) -> 30 | L43: 45444 | M43: 45473 | N43: =ROUNDUP(K43/30*320,0) -> 320 | O43: =N43*5 -> 1600 | P43: =N43+O43 -> 1920
A44: FAA | B44: 4320 | C44: FS | D44: Muhammad Ali Kiyani | E44: 4700I483207 | F44: 61101-7478749-3 | H44: 35173 | I44: 45264 | K44: =MAX(0, MIN(M44, J44) - MAX(L44, I44) + 1) -> 30 | L44: 45444 | M44: 45473 | N44: =ROUNDUP(K44/30*320,0) -> 320 | O44: =N44*5 -> 1600 | P44: =N44+O44 -> 1920
A45: FAA | B45: 4320 | C45: FS | D45: Muhammad Anas Khan | E45: 4700J764084 | F45: 31202-1004575-1 | H45: 37964 | I45: 45355 | K45: =MAX(0, MIN(M45, J45) - MAX(L45, I45) + 1) -> 30 | L45: 45444 | M45: 45473 | N45: =ROUNDUP(K45/30*320,0) -> 320 | O45: =N45*5 -> 1600 | P45: =N45+O45 -> 1920
A46: FAA | B46: 4320 | C46: FS | D46: Muhammad Asadullah Shahid | E46: 4700G581544 | F46: 36603-1234883-1 | H46: 35943 | I46: 45215 | K46: =MAX(0, MIN(M46, J46) - MAX(L46, I46) + 1) -> 30 | L46: 45444 | M46: 45473 | N46: =ROUNDUP(K46/30*320,0) -> 320 | O46: =N46*5 -> 1600 | P46: =N46+O46 -> 1920
A47: FAA | B47: 4320 | C47: FS | D47: Muhammad Ayan Baig | E47: 4700E764102 | F47: 36302-5170382-5 | H47: 36557 | I47: 45432 | K47: =MAX(0, MIN(M47, J47) - MAX(L47, I47) + 1) -> 30 | L47: 45444 | M47: 45473 | N47: =ROUNDUP(K47/30*320,0) -> 320 | O47: =N47*5 -> 1600 | P47: =N47+O47 -> 1920
A48: FAA | B48: 4320 | C48: FS | D48: Muhammad Bilal Tanveer | E48: 4700D763961 | F48: 82203-3459651-7 | H48: 35551 | I48: 45383 | K48: =MAX(0, MIN(M48, J48) - MAX(L48, I48) + 1) -> 30 | L48: 45444 | M48: 45473 | N48: =ROUNDUP(K48/30*320,0) -> 320 | O48: =N48*5 -> 1600 | P48: =N48+O48 -> 1920
A49: FAA | B49: 4320 | C49: FS | D49: Muhammad Hassan Shakeel | E49: 4700H690431 | F49: 35402-2593513-5 | H49: 36794 | I49: 44915 | K49: =MAX(0, MIN(M49, J49) - MAX(L49, I49) + 1) -> 30 | L49: 45444 | M49: 45473 | N49: =ROUNDUP(K49/30*320,0) -> 320 | O49: =N49*5 -> 1600 | P49: =N49+O49 -> 1920
A50: FAA | B50: 4320 | C50: FS | D50: Muhammad Ibrahim | E50: 4700C720948 | F50: 31101-0776303-7 | H50: 37149 | I50: 45124 | J50: 45450 | K50: =MAX(0, MIN(M50, J50) - MAX(L50, I50) + 1) -> 7 | L50: 45444 | M50: 45473 | N50: =ROUNDUP(K50/30*320,0) -> 75 | O50: =N50*5 -> 375 | P50: =N50+O50 -> 450
A51: FAA | B51: 4320 | C51: FS | D51: Muhammad Osama Ehsaan | E51: 4700B764082 | F51: 31203-9951845-1 | H51: 36821 | I51: 45362 | K51: =MAX(0, MIN(M51, J51) - MAX(L51, I51) + 1) -> 30 | L51: 45444 | M51: 45473 | N51: =ROUNDUP(K51/30*320,0) -> 320 | O51: =N51*5 -> 1600 | P51: =N51+O51 -> 1920
A52: FAA | B52: 4320 | C52: FS | D52: Muhammad Shoaib | F52: 82401-2146189-7 | H52: 36346 | I52: 45453 | K52: 21 | L52: 45453 | M52: 45473 | N52: =ROUNDUP(K52/30*320,0) -> 224 | O52: =N52*5 -> 1120 | P52: =N52+O52 -> 1344
A53: FAA | B53: 4320 | C53: FS | D53: Muhammad Umair | F53: 37405-5832738-5 | H53: 37494 | I53: 45467 | K53: 7 | L53: 45467 | M53: 45473 | N53: =ROUNDUP(K53/30*320,0) -> 75 | O53: =N53*5 -> 375 | P53: =N53+O53 -> 450
A54: FAA | B54: 4320 | C54: FS | D54: Muhammad Umair Nasar | E54: 4700G764079 | F54: 35202-7433048-7 | H54: 36778 | I54: 45369 | K54: =MAX(0, MIN(M54, J54) - MAX(L54, I54) + 1) -> 30 | L54: 45444 | M54: 45473 | N54: =ROUNDUP(K54/30*320,0) -> 320 | O54: =N54*5 -> 1600 | P54: =N54+O54 -> 1920
A55: FAA | B55: 4320 | C55: FS | D55: Muhammad Uzaimah Mushtaq | E55: 4700J764076 | F55: 38201-8328241-1 | H55: 37085 | I55: 45400 | K55: =MAX(0, MIN(M55, J55) - MAX(L55, I55) + 1) -> 30 | L55: 45444 | M55: 45473 | N55: =ROUNDUP(K55/30*320,0) -> 320 | O55: =N55*5 -> 1600 | P55: =N55+O55 -> 1920
A56: FAA | B56: 4320 | C56: FS | D56: Muhammad Waleed Abdullah | E56: 4700I764077 | F56: 36601-1635702-5 | H56: 37647 | I56: 45355 | K56: =MAX(0, MIN(M56, J56) - MAX(L56, I56) + 1) -> 30 | L56: 45444 | M56: 45473 | N56: =ROUNDUP(K56/30*320,0) -> 320 | O56: =N56*5 -> 1600 | P56: =N56+O56 -> 1920
A57: FAA | B57: 4320 | C57: FS | D57: Muhammad Zahab Ahmed | E57: 3600G329844 | F57: 31102-2135283-9 | H57: 34300 | I57: 45183 | K57: =MAX(0, MIN(M57, J57) - MAX(L57, I57) + 1) -> 30 | L57: 45444 | M57: 45473 | N57: =ROUNDUP(K57/30*320,0) -> 320 | O57: =N57*5 -> 1600 | P57: =N57+O57 -> 1920
A58: FAA | B58: 4320 | C58: FS | D58: Muiz Hussain | E58: 4600F352555 | F58: 42301-8666708-3 | H58: 36412 | I58: 45355 | K58: =MAX(0, MIN(M58, J58) - MAX(L58, I58) + 1) -> 30 | L58: 45444 | M58: 45473 | N58: =ROUNDUP(K58/30*320,0) -> 320 | O58: =N58*5 -> 1600 | P58: =N58+O58 -> 1920
A59: FAA | B59: 4320 | C59: FS | D59: Musa Chughtai | F59: 37405-0493023-7 | H59: 36907 | I59: 45446 | K59: 28 | L59: 45446 | M59: 45473 | N59: =ROUNDUP(K59/30*320,0) -> 299 | O59: =N59*5 -> 1495 | P59: =N59+O59 -> 1794
A60: FAA | B60: 4320 | C60: FS | D60: Myda Abbas | E60: 4700F764101 | F60: 37405-3363346-0 | H60: 36655 | I60: 45418 | K60: =MAX(0, MIN(M60, J60) - MAX(L60, I60) + 1) -> 30 | L60: 45444 | M60: 45473 | N60: =ROUNDUP(K60/30*320,0) -> 320 | O60: =N60*5 -> 1600 | P60: =N60+O60 -> 1920
A61: FAA | B61: 4320 | C61: FS | D61: Naveed Ahmed | E61: 4700H679736 | F61: 42201-5462974-9 | H61: 31014 | I61: 44805 | K61: =MAX(0, MIN(M61, J61) - MAX(L61, I61) + 1) -> 30 | L61: 45444 | M61: 45473 | N61: =ROUNDUP(K61/30*320,0) -> 320 | O61: =N61*5 -> 1600 | P61: =N61+O61 -> 1920
A62: FAA | B62: 4320 | C62: FS | D62: Nimra Zahid | E62: 4700G537391 | F62: 42201-1439506-4 | H62: 34522 | I62: 45292 | K62: =MAX(0, MIN(M62, J62) - MAX(L62, I62) + 1) -> 30 | L62: 45444 | M62: 45473 | N62: =ROUNDUP(K62/30*320,0) -> 320 | O62: =N62*5 -> 1600 | P62: =N62+O62 -> 1920
A63: FAA | B63: 4320 | C63: FS | D63: Qazi Maaz Sajjad | F63: 35102-2075551-3 | H63: 37415 | I63: 45441 | K63: 30 | L63: 45444 | M63: 45473 | N63: =ROUNDUP(K63/30*320,0) -> 320 | O63: =N63*5 -> 1600 | P63: =N63+O63 -> 1920
A64: FAA | B64: 4320 | C64: FS | D64: Rashid Iqbal | E64: 4700I703314 | F64: 37405-6880780-7 | H64: 34732 | I64: 44986 | K64: =MAX(0, MIN(M64, J64) - MAX(L64, I64) + 1) -> 30 | L64: 45444 | M64: 45473 | N64: =ROUNDUP(K64/30*320,0) -> 320 | O64: =N64*5 -> 1600 | P64: =N64+O64 -> 1920
A65: FAA | B65: 4320 | C65: FS | D65: Sabdezar Irfan | E65: 3600G465789 | F65: 35201-1547140-8 | H65: 35395 | I65: 45376 | K65: =MAX(0, MIN(M65, J65) - MAX(L65, I65) + 1) -> 30 | L65: 45444 | M65: 45473 | N65: =ROUNDUP(K65/30*320,0) -> 320 | O65: =N65*5 -> 1600 | P65: =N65+O65 -> 1920
A66: FAA | B66: 4320 | C66: FS | D66: Saboor Ahmad | E66: 4700D763937 | F66: 61101-8448365-1 | H66: 37397 | I66: 45377 | J66: 45454 | K66: =MAX(0, MIN(M66, J66) - MAX(L66, I66) + 1) -> 11 | L66: 45444 | M66: 45473 | N66: =ROUNDUP(K66/30*320,0) -> 118 | O66: =N66*5 -> 590 | P66: =N66+O66 -> 708
A67: FAA | B67: 4320 | C67: FS | D67: Saif Ullah | E67: 4700A764083 | F67: 61101-5764361-9 | H67: 37479 | I67: 45320 | J67: 45457 | K67: =MAX(0, MIN(M67, J67) - MAX(L67, I67) + 1) -> 14 | L67: 45444 | M67: 45473 | N67: =ROUNDUP(K67/30*320,0) -> 150 | O67: =N67*5 -> 750 | P67: =N67+O67 -> 900
A68: FAA | B68: 4320 | C68: FS | D68: Sana Tahir | E68: 4700D706561 | F68: 37103-2235902-2 | H68: 35976 | I68: 45042 | J68: 45464 | K68: =MAX(0, MIN(M68, J68) - MAX(L68, I68) + 1) -> 21 | L68: 45444 | M68: 45473 | N68: =ROUNDUP(K68/30*320,0) -> 224 | O68: =N68*5 -> 1120 | P68: =N68+O68 -> 1344
A69: FAA | B69: 4320 | C69: FS | D69: Shahzad Farooq | E69: 4700G690432 | F69: 42501-8133748-7 | H69: 36979 | I69: 44907 | K69: =MAX(0, MIN(M69, J69) - MAX(L69, I69) + 1) -> 30 | L69: 45444 | M69: 45473 | N69: =ROUNDUP(K69/30*320,0) -> 320 | O69: =N69*5 -> 1600 | P69: =N69+O69 -> 1920
A70: FAA | B70: 4320 | C70: FS | D70: Shaiq Habib | E70: 0400C579124 | F70: 61101-1388832-7 | H70: 36421 | I70: 45208 | K70: =MAX(0, MIN(M70, J70) - MAX(L70, I70) + 1) -> 30 | L70: 45444 | M70: 45473 | N70: =ROUNDUP(K70/30*320,0) -> 320 | O70: =N70*5 -> 1600 | P70: =N70+O70 -> 1920
A71: FAA | B71: 4320 | C71: FS | D71: Shan Ahmad | E71: 4700C748360 | F71: 35202-9717455-5 | H71: 35447 | I71: 45273 | K71: =MAX(0, MIN(M71, J71) - MAX(L71, I71) + 1) -> 30 | L71: 45444 | M71: 45473 | N71: =ROUNDUP(K71/30*320,0) -> 320 | O71: =N71*5 -> 1600 | P71: =N71+O71 -> 1920
A72: FAA | B72: 4320 | C72: FS | D72: Subhana Yasin | E72: 4700E723960 | F72: 36502-1828819-0 | H72: 36574 | I72: 45187 | K72: =MAX(0, MIN(M72, J72) - MAX(L72, I72) + 1) -> 30 | L72: 45444 | M72: 45473 | N72: =ROUNDUP(K72/30*320,0) -> 320 | O72: =N72*5 -> 1600 | P72: =N72+O72 -> 1920
A73: FAA | B73: 4320 | C73: FS | D73: Sukaina Ali | E73: 4700C688544 | F73: 37405-6240250-8 | H73: 36991 | I73: 45205 | K73: =MAX(0, MIN(M73, J73) - MAX(L73, I73) + 1) -> 30 | L73: 45444 | M73: 45473 | N73: =ROUNDUP(K73/30*320,0) -> 320 | O73: =N73*5 -> 1600 | P73: =N73+O73 -> 1920
A74: FAA | B74: 4320 | C74: FS | D74: Syed Maaz Ahmed | E74: 0500A167653 | F74: 42101-8025278-5 | H74: 36433 | I74: 45432 | K74: =MAX(0, MIN(M74, J74) - MAX(L74, I74) + 1) -> 30 | L74: 45444 | M74: 45473 | N74: =ROUNDUP(K74/30*320,0) -> 320 | O74: =N74*5 -> 1600 | P74: =N74+O74 -> 1920
A75: FAA | B75: 4320 | C75: FS | D75: Syeda Fatima Shahid | F75: 61101-4873618-6 | H75: 37818 | I75: 45467 | K75: 7 | L75: 45467 | M75: 45473 | N75: =ROUNDUP(K75/30*320,0) -> 75 | O75: =N75*5 -> 375 | P75: =N75+O75 -> 450
A76: FAA | B76: 4320 | C76: FS | D76: Talha Arshad Malik | E76: 3600F372686 | F76: 37405-6378563-1 | H76: 33156 | I76: 44285 | K76: =MAX(0, MIN(M76, J76) - MAX(L76, I76) + 1) -> 30 | L76: 45444 | M76: 45473 | N76: =ROUNDUP(K76/30*320,0) -> 320 | O76: =N76*5 -> 1600 | P76: =N76+O76 -> 1920
A77: FAA | B77: 4320 | C77: FS | D77: Tauqeer Ahmed | E77: 4700H764078 | F77: 35201-5043196-1 | H77: 35697 | I77: 45348 | K77: =MAX(0, MIN(M77, J77) - MAX(L77, I77) + 1) -> 30 | L77: 45444 | M77: 45473 | N77: =ROUNDUP(K77/30*320,0) -> 320 | O77: =N77*5 -> 1600 | P77: =N77+O77 -> 1920
A78: FAA | B78: 4320 | C78: FS | D78: Tayyab Abbas | E78: 4700A685051 | F78: 17301-2752063-7 | H78: 36797 | I78: 44886 | K78: =MAX(0, MIN(M78, J78) - MAX(L78, I78) + 1) -> 30 | L78: 45444 | M78: 45473 | N78: =ROUNDUP(K78/30*320,0) -> 320 | O78: =N78*5 -> 1600 | P78: =N78+O78 -> 1920
A79: FAA | B79: 4320 | C79: FS | D79: Ubaid Ullah | F79: 36103-3565578-3 | H79: 36530 | I79: 45446 | K79: 28 | L79: 45446 | M79: 45473 | N79: =ROUNDUP(K79/30*320,0) -> 299 | O79: =N79*5 -> 1495 | P79: =N79+O79 -> 1794
A80: FAA | B80: 4320 | C80: FS | D80: Umaira Jabeen | E80: 3600J522091 | F80: 37104-5371430-8 | H80: 33769 | I80: 44816 | K80: =MAX(0, MIN(M80, J80) - MAX(L80, I80) + 1) -> 30 | L80: 45444 | M80: 45473 | N80: =ROUNDUP(K80/30*320,0) -> 320 | O80: =N80*5 -> 1600 | P80: =N80+O80 -> 1920
A81: FAA | B81: 4320 | C81: FS | D81: Umar Sheraz | E81: 3600C583492 | F81: 38403-8907880-9 | H81: 35973 | I81: 45414 | K81: =MAX(0, MIN(M81, J81) - MAX(L81, I81) + 1) -> 30 | L81: 45444 | M81: 45473 | N81: =ROUNDUP(K81/30*320,0) -> 320 | O81: =N81*5 -> 1600 | P81: =N81+O81 -> 1920
A82: FAA | B82: 4320 | C82: FS | D82: Uzma Shaheen | F82: 37104-4296305-6 | H82: 36451 | I82: 45453 | K82: 21 | L82: 45453 | M82: 45473 | N82: =ROUNDUP(K82/30*320,0) -> 224 | O82: =N82*5 -> 1120 | P82: =N82+O82 -> 1344
A83: FAA | B83: 4320 | C83: FS | D83: Waleed Sadiq | E83: 4700C710870 | F83: 82101-6085499-3 | H83: 35818 | I83: 45089 | K83: =MAX(0, MIN(M83, J83) - MAX(L83, I83) + 1) -> 30 | L83: 45444 | M83: 45473 | N83: =ROUNDUP(K83/30*320,0) -> 320 | O83: =N83*5 -> 1600 | P83: =N83+O83 -> 1920
A84: FAA | B84: 4320 | C84: FS | D84: Zain Shahid | E84: 4700H700799 | F84: 36401-6591078-1 | H84: 36177 | I84: 45320 | K84: =MAX(0, MIN(M84, J84) - MAX(L84, I84) + 1) -> 30 | L84: 45444 | M84: 45473 | N84: =ROUNDUP(K84/30*320,0) -> 320 | O84: =N84*5 -> 1600 | P84: =N84+O84 -> 1920
A85: FAA | B85: 4320 | C85: FS | D85: Zeeshan Nasir | E85: 4700J764092 | F85: 37405-3360545-9 | H85: 36522 | I85: 45328 | K85: =MAX(0, MIN(M85, J85) - MAX(L85, I85) + 1) -> 30 | L85: 45444 | M85: 45473 | N85: =ROUNDUP(K85/30*320,0) -> 320 | O85: =N85*5 -> 1600 | P85: =N85+O85 -> 1920
A86: FAA | B86: 4320 | C86: FS | D86: Zoha Munir | E86: 0600G182381 | F86: 35202-9887337-8 | H86: 35743 | I86: 45222 | K86: =MAX(0, MIN(M86, J86) - MAX(L86, I86) + 1) -> 30 | L86: 45444 | M86: 45473 | N86: =ROUNDUP(K86/30*320,0) -> 320 | O86: =N86*5 -> 1600 | P86: =N86+O86 -> 1920
P87: =SUM(P2:P86) -> 151254

Sheet Jul-24
A1: EMP_AREA_CODE | B1: EMP_REG_SERIAL_NO | C1: EMP_SUB_AREA_CODE | D1: Name | E1: EOBI_NO | F1: CNIC | G1: NIC | H1: DOB | I1: DOJ | J1: DOE | K1: NO_OF_DAYS_WORKED | L1: From_Date | M1: To_Date | N1: Employee Contribution | O1: Employer Contribution | P1: Total EOBI
A2: FAA | B2: 4320 | C2: FS | D2: Abdul Hameed | E2: 4700J763957 | F2: 17301-6508006-1 | H2: 36617 | I2: 45299 | K2: =MAX(0, MIN(M2, J2) - MAX(L2, I2) + 1) -> 31 | L2: 45474 | M2: 45504 | N2: =ROUNDUP(K2/31*370,0) -> 370 | O2: =N2*5 -> 1850 | P2: =N2+O2 -> 2220
A3: FAA | B3: 4320 | C3: FS | D3: Abdul Moiez Akhtar | E3: 4700I763958 | F3: 34201-8434498-9 | H3: 37149 | I3: 45397 | K3: =MAX(0, MIN(M3, J3) - MAX(L3, I3) + 1) -> 31 | L3: 45474 | M3: 45504 | N3: =ROUNDUP(K3/31*370,0) -> 370 | O3: =N3*5 -> 1850 | P3: =N3+O3 -> 2220
A4: FAA | B4: 4320 | C4: FS | D4: Abdullah Bin Rashid | E4: 4700A705194 | F4: 61101-3101618-7 | H4: 36358 | I4: 45027 | K4: =MAX(0, MIN(M4, J4) - MAX(L4, I4) + 1) -> 31 | L4: 45474 | M4: 45504 | N4: =ROUNDUP(K4/31*370,0) -> 370 | O4: =N4*5 -> 1850 | P4: =N4+O4 -> 2220
A5: FAA | B5: 4320 | C5: FS | D5: Abdullah Rasheed | E5: 4700G688671 | F5: 37401-7271621-7 | H5: 36860 | I5: 45124 | K5: =MAX(0, MIN(M5, J5) - MAX(L5, I5) + 1) -> 31 | L5: 45474 | M5: 45504 | N5: =ROUNDUP(K5/31*370,0) -> 370 | O5: =N5*5 -> 1850 | P5: =N5+O5 -> 2220
A6: FAA | B6: 4320 | C6: FS | D6: Adil Ali | E6: 4700H780618 | F6: 37405-7507683-3 | H6: 37978 | I6: 45453 | K6: 31 | L6: 45474 | M6: 45504 | N6: =ROUNDUP(K6/31*370,0) -> 370 | O6: =N6*5 -> 1850 | P6: =N6+O6 -> 2220
A7: FAA | B7: 4320 | C7: FS | D7: Ahmad Hassan | E7: 4600D315335 | F7: 37405-4246562-3 | H7: 35997 | I7: 45061 | K7: =MAX(0, MIN(M7, J7) - MAX(L7, I7) + 1) -> 31 | L7: 45474 | M7: 45504 | N7: =ROUNDUP(K7/31*370,0) -> 370 | O7: =N7*5 -> 1850 | P7: =N7+O7 -> 2220
A8: FAA | B8: 4320 | C8: FS | D8: Ahmed Hussain | E8: 4800F063920 | F8: 38102-5707136-9 | H8: 36353 | I8: 45278 | K8: =MAX(0, MIN(M8, J8) - MAX(L8, I8) + 1) -> 31 | L8: 45474 | M8: 45504 | N8: =ROUNDUP(K8/31*370,0) -> 370 | O8: =N8*5 -> 1850 | P8: =N8+O8 -> 2220
A9: FAA | B9: 4320 | C9: FS | D9: Aiman Daud | E9: 4700C764099 | F9: 37404-5596830-8 | H9: 35669 | I9: 45418 | J9: 45481 | K9: =MAX(0, MIN(M9, J9) - MAX(L9, I9) + 1) -> 8 | L9: 45474 | M9: 45504 | N9: =ROUNDUP(K9/31*370,0) -> 96 | O9: =N9*5 -> 480 | P9: =N9+O9 -> 576
A10: FAA | B10: 4320 | C10: FS | D10: Amish Tufail | E10: 4700H764094 | F10: 13302-2902324-3 | H10: 37274 | I10: 45362 | K10: =MAX(0, MIN(M10, J10) - MAX(L10, I10) + 1) -> 31 | L10: 45474 | M10: 45504 | N10: =ROUNDUP(K10/31*370,0) -> 370 | O10: =N10*5 -> 1850 | P10: =N10+O10 -> 2220
A11: FAA | B11: 4320 | C11: FS | D11: Anamil Mehtab | E11: 4700A710822 | F11: 37103-6819266-4 | H11: 37398 | I11: 45096 | K11: =MAX(0, MIN(M11, J11) - MAX(L11, I11) + 1) -> 31 | L11: 45474 | M11: 45504 | N11: =ROUNDUP(K11/31*370,0) -> 370 | O11: =N11*5 -> 1850 | P11: =N11+O11 -> 2220
A12: FAA | B12: 4320 | C12: FS | D12: Anas Hanif Attas | E12: 4700B665806 | F12: 38403-3251146-3 | H12: 36360 | I12: 45355 | K12: =MAX(0, MIN(M12, J12) - MAX(L12, I12) + 1) -> 31 | L12: 45474 | M12: 45504 | N12: =ROUNDUP(K12/31*370,0) -> 370 | O12: =N12*5 -> 1850 | P12: =N12+O12 -> 2220
A13: FAA | B13: 4320 | C13: FS | D13: Annum Inam | E13: 4700D780620 | F13: 61101-7960847-6 | H13: 33230 | I13: 45453 | K13: 31 | L13: 45474 | M13: 45504 | N13: =ROUNDUP(K13/31*370,0) -> 370 | O13: =N13*5 -> 1850 | P13: =N13+O13 -> 2220
A14: FAA | B14: 4320 | C14: FS | D14: Asad Ullah | E14: 4700C748792 | F14: 34401-8557347-3 | H14: 35047 | I14: 45257 | K14: =MAX(0, MIN(M14, J14) - MAX(L14, I14) + 1) -> 31 | L14: 45474 | M14: 45504 | N14: =ROUNDUP(K14/31*370,0) -> 370 | O14: =N14*5 -> 1850 | P14: =N14+O14 -> 2220
A15: FAA | B15: 4320 | C15: FS | D15: Asim Latif | E15: 4700A658224 | F15: 33302-5158556-5 | H15: 37370 | I15: 44739 | K15: =MAX(0, MIN(M15, J15) - MAX(L15, I15) + 1) -> 31 | L15: 45474 | M15: 45504 | N15: =ROUNDUP(K15/31*370,0) -> 370 | O15: =N15*5 -> 1850 | P15: =N15+O15 -> 2220
A16: FAA | B16: 4320 | C16: FS | D16: Atif Nawaz | E16: 4700E740695 | F16: 38404-7428636-7 | H16: 36399 | I16: 45229 | K16: =MAX(0, MIN(M16, J16) - MAX(L16, I16) + 1) -> 31 | L16: 45474 | M16: 45504 | N16: =ROUNDUP(K16/31*370,0) -> 370 | O16: =N16*5 -> 1850 | P16: =N16+O16 -> 2220
A17: FAA | B17: 4320 | C17: FS | D17: Aun Ishfaq | E17: 4700E764097 | F17: 90403-0143681-7 | H17: 36183 | I17: 45418 | K17: =MAX(0, MIN(M17, J17) - MAX(L17, I17) + 1) -> 31 | L17: 45474 | M17: 45504 | N17: =ROUNDUP(K17/31*370,0) -> 370 | O17: =N17*5 -> 1850 | P17: =N17+O17 -> 2220
A18: FAA | B18: 4320 | C18: FS | D18: Ayesha Nasir | E18: 4700G764100 | F18: 37405-8603058-0 | H18: 37144 | I18: 45418 | J18: 45483 | K18: =MAX(0, MIN(M18, J18) - MAX(L18, I18) + 1) -> 10 | L18: 45474 | M18: 45504 | N18: =ROUNDUP(K18/31*370,0) -> 120 | O18: =N18*5 -> 600 | P18: =N18+O18 -> 720
A19: FAA | B19: 4320 | C19: FS | D19: Ayesha Shakeel | E19: 4700H763959 | F19: 42301-1838144-6 | H19: 36962 | I19: 45376 | K19: =MAX(0, MIN(M19, J19) - MAX(L19, I19) + 1) -> 31 | L19: 45474 | M19: 45504 | N19: =ROUNDUP(K19/31*370,0) -> 370 | O19: =N19*5 -> 1850 | P19: =N19+O19 -> 2220
A20: FAA | B20: 4320 | C20: FS | D20: Ayesha Syed | E20: 4700E763960 | F20: 37405-5537896-0 | H20: 37377 | I20: 45334 | K20: =MAX(0, MIN(M20, J20) - MAX(L20, I20) + 1) -> 31 | L20: 45474 | M20: 45504 | N20: =ROUNDUP(K20/31*370,0) -> 370 | O20: =N20*5 -> 1850 | P20: =N20+O20 -> 2220
A21: FAA | B21: 4320 | C21: FS | D21: Ayesha Tahir | E21: 4700A748794 | F21: 13101-5843018-0 | H21: 37047 | I21: 45257 | K21: =MAX(0, MIN(M21, J21) - MAX(L21, I21) + 1) -> 31 | L21: 45474 | M21: 45504 | N21: =ROUNDUP(K21/31*370,0) -> 370 | O21: =N21*5 -> 1850 | P21: =N21+O21 -> 2220
A22: FAA | B22: 4320 | C22: FS | D22: Basit Afraz | E22: 4700C703310 | F22: 37405-8019865-5 | H22: 34601 | I22: 44986 | K22: =MAX(0, MIN(M22, J22) - MAX(L22, I22) + 1) -> 31 | L22: 45474 | M22: 45504 | N22: =ROUNDUP(K22/31*370,0) -> 370 | O22: =N22*5 -> 1850 | P22: =N22+O22 -> 2220
A23: FAA | B23: 4320 | C23: FS | D23: Faiza Khan | E23: 4700J710823 | F23: 61101-0776147-2 | H23: 37322 | I23: 45096 | K23: =MAX(0, MIN(M23, J23) - MAX(L23, I23) + 1) -> 31 | L23: 45474 | M23: 45504 | N23: =ROUNDUP(K23/31*370,0) -> 370 | O23: =N23*5 -> 1850 | P23: =N23+O23 -> 2220
A24: FAA | B24: 4320 | C24: FS | D24: Faizan Khan | E24: 4700C662124 | F24: 16204-0388636-3 | H24: 35704 | I24: 44760 | K24: =MAX(0, MIN(M24, J24) - MAX(L24, I24) + 1) -> 31 | L24: 45474 | M24: 45504 | N24: =ROUNDUP(K24/31*370,0) -> 370 | O24: =N24*5 -> 1850 | P24: =N24+O24 -> 2220
A25: FAA | B25: 4320 | C25: FS | D25: Farzam Habib Khan | E25: 4700B748793 | F25: 12101-9669033-4 | H25: 37219 | I25: 45257 | K25: =MAX(0, MIN(M25, J25) - MAX(L25, I25) + 1) -> 31 | L25: 45474 | M25: 45504 | N25: =ROUNDUP(K25/31*370,0) -> 370 | O25: =N25*5 -> 1850 | P25: =N25+O25 -> 2220
A26: FAA | B26: 4320 | C26: FS | D26: Hafsa Hassan | E26: 4700B764090 | F26: 37406-2194723-0 | H26: 36718 | I26: 45397 | J26: 45485 | K26: =MAX(0, MIN(M26, J26) - MAX(L26, I26) + 1) -> 12 | L26: 45474 | M26: 45504 | N26: =ROUNDUP(K26/31*370,0) -> 144 | O26: =N26*5 -> 720 | P26: =N26+O26 -> 864
A27: FAA | B27: 4320 | C27: FS | D27: Hamza Ahmad | E27: 4700I678608 | F27: 37405-6689341-9 | H27: 36246 | I27: 44851 | K27: =MAX(0, MIN(M27, J27) - MAX(L27, I27) + 1) -> 31 | L27: 45474 | M27: 45504 | N27: =ROUNDUP(K27/31*370,0) -> 370 | O27: =N27*5 -> 1850 | P27: =N27+O27 -> 2220
A28: FAA | B28: 4320 | C28: FS | D28: Hamza Ali Khan | E28: 4700B690429 | F28: 37405-5700118-7 | H28: 35606 | I28: 44896 | K28: =MAX(0, MIN(M28, J28) - MAX(L28, I28) + 1) -> 31 | L28: 45474 | M28: 45504 | N28: =ROUNDUP(K28/31*370,0) -> 370 | O28: =N28*5 -> 1850 | P28: =N28+O28 -> 2220
A29: FAA | B29: 4320 | C29: FS | D29: Hamza Mughal | E29: 4700F739740 | F29: 13501-9345271-1 | H29: 36111 | I29: 45418 | K29: =MAX(0, MIN(M29, J29) - MAX(L29, I29) + 1) -> 31 | L29: 45474 | M29: 45504 | N29: =ROUNDUP(K29/31*370,0) -> 370 | O29: =N29*5 -> 1850 | P29: =N29+O29 -> 2220
A30: FAA | B30: 4320 | C30: FS | D30: Hira Farooq | E30: 4700B703311 | F30: 61101-2625195-8 | H30: 34973 | I30: 44986 | K30: =MAX(0, MIN(M30, J30) - MAX(L30, I30) + 1) -> 31 | L30: 45474 | M30: 45504 | N30: =ROUNDUP(K30/31*370,0) -> 370 | O30: =N30*5 -> 1850 | P30: =N30+O30 -> 2220
A31: FAA | B31: 4320 | C31: FS | D31: Humaira Amjad | E31: 4700A764091 | F31: 36302-7205229-8 | H31: 34590 | I31: 45313 | K31: =MAX(0, MIN(M31, J31) - MAX(L31, I31) + 1) -> 31 | L31: 45474 | M31: 45504 | N31: =ROUNDUP(K31/31*370,0) -> 370 | O31: =N31*5 -> 1850 | P31: =N31+O31 -> 2220
A32: FAA | B32: 4320 | C32: FS | D32: Ibrahim Shah | E32: 4700G658260 | F32: 35201-2147689-9 | H32: 36891 | I32: 44739 | K32: =MAX(0, MIN(M32, J32) - MAX(L32, I32) + 1) -> 31 | L32: 45474 | M32: 45504 | N32: =ROUNDUP(K32/31*370,0) -> 370 | O32: =N32*5 -> 1850 | P32: =N32+O32 -> 2220
A33: FAA | B33: 4320 | C33: FS | D33: Khadija Umer | E33: 4700A710848 | F33: 31202-4982058-2 | H33: 36401 | I33: 45096 | K33: =MAX(0, MIN(M33, J33) - MAX(L33, I33) + 1) -> 31 | L33: 45474 | M33: 45504 | N33: =ROUNDUP(K33/31*370,0) -> 370 | O33: =N33*5 -> 1850 | P33: =N33+O33 -> 2220
A34: FAA | B34: 4320 | C34: FS | D34: Lamees Zafar | E34: 4700C763962 | F34: 36304-3814800-4 | H34: 37958 | I34: 45369 | K34: =MAX(0, MIN(M34, J34) - MAX(L34, I34) + 1) -> 31 | L34: 45474 | M34: 45504 | N34: =ROUNDUP(K34/31*370,0) -> 370 | O34: =N34*5 -> 1850 | P34: =N34+O34 -> 2220
A35: FAA | B35: 4320 | C35: FS | D35: Luqman Ahmed | E35: 4700D764098 | F35: 37102-2088988-7 | H35: 34922 | I35: 45418 | K35: =MAX(0, MIN(M35, J35) - MAX(L35, I35) + 1) -> 31 | L35: 45474 | M35: 45504 | N35: =ROUNDUP(K35/31*370,0) -> 370 | O35: =N35*5 -> 1850 | P35: =N35+O35 -> 2220
A36: FAA | B36: 4320 | C36: FS | D36: Misbah Aziz | F36: 36602-2764423-2 | H36: 36443 | I36: 45446 | K36: 31 | L36: 45474 | M36: 45504 | N36: =ROUNDUP(K36/31*370,0) -> 370 | O36: =N36*5 -> 1850 | P36: =N36+O36 -> 2220
A37: FAA | B37: 4320 | C37: FS | D37: Mohammad Ehtasham Balland | E37: 4700D711914 | F37: 36302-5494206-1 | H37: 33737 | I37: 45139 | K37: =MAX(0, MIN(M37, J37) - MAX(L37, I37) + 1) -> 31 | L37: 45474 | M37: 45504 | N37: =ROUNDUP(K37/31*370,0) -> 370 | O37: =N37*5 -> 1850 | P37: =N37+O37 -> 2220
A38: FAA | B38: 4320 | C38: FS | D38: Mohsin Ali Anjum | E38: 4700A763964 | F38: 37402-3744622-3 | H38: 35272 | I38: 45355 | K38: =MAX(0, MIN(M38, J38) - MAX(L38, I38) + 1) -> 31 | L38: 45474 | M38: 45504 | N38: =ROUNDUP(K38/31*370,0) -> 370 | O38: =N38*5 -> 1850 | P38: =N38+O38 -> 2220
A39: FAA | B39: 4320 | C39: FS | D39: Muawiz Umer | E39: 4700I763966 | F39: 31202-0967091-9 | H39: 37539 | I39: 45362 | K39: =MAX(0, MIN(M39, J39) - MAX(L39, I39) + 1) -> 31 | L39: 45474 | M39: 45504 | N39: =ROUNDUP(K39/31*370,0) -> 370 | O39: =N39*5 -> 1850 | P39: =N39+O39 -> 2220
A40: FAA | B40: 4320 | C40: FS | D40: Muhammad Abdullah Salam | E40: 4700G697010 | F40: 17301-7752570-9 | H40: 36690 | I40: 44938 | K40: =MAX(0, MIN(M40, J40) - MAX(L40, I40) + 1) -> 31 | L40: 45474 | M40: 45504 | N40: =ROUNDUP(K40/31*370,0) -> 370 | O40: =N40*5 -> 1850 | P40: =N40+O40 -> 2220
A41: FAA | B41: 4320 | C41: FS | D41: Muhammad Abubakar | E41: 4700H723959 | F41: 35201-8046049-1 | H41: 37240 | I41: 45176 | K41: =MAX(0, MIN(M41, J41) - MAX(L41, I41) + 1) -> 31 | L41: 45474 | M41: 45504 | N41: =ROUNDUP(K41/31*370,0) -> 370 | O41: =N41*5 -> 1850 | P41: =N41+O41 -> 2220
A42: FAA | B42: 4320 | C42: FS | D42: Muhammad Adnan | E42: 4700A638371 | F42: 54401-7578020-9 | H42: 33240 | I42: 44287 | K42: =MAX(0, MIN(M42, J42) - MAX(L42, I42) + 1) -> 31 | L42: 45474 | M42: 45504 | N42: =ROUNDUP(K42/31*370,0) -> 370 | O42: =N42*5 -> 1850 | P42: =N42+O42 -> 2220
A43: FAA | B43: 4320 | C43: FS | D43: Muhammad Ali Kiyani | E43: 4700I483207 | F43: 61101-7478749-3 | H43: 35173 | I43: 45264 | K43: =MAX(0, MIN(M43, J43) - MAX(L43, I43) + 1) -> 31 | L43: 45474 | M43: 45504 | N43: =ROUNDUP(K43/31*370,0) -> 370 | O43: =N43*5 -> 1850 | P43: =N43+O43 -> 2220
A44: FAA | B44: 4320 | C44: FS | D44: Muhammad Anas Khan | E44: 4700J764084 | F44: 31202-1004575-1 | H44: 37964 | I44: 45355 | K44: =MAX(0, MIN(M44, J44) - MAX(L44, I44) + 1) -> 31 | L44: 45474 | M44: 45504 | N44: =ROUNDUP(K44/31*370,0) -> 370 | O44: =N44*5 -> 1850 | P44: =N44+O44 -> 2220
A45: FAA | B45: 4320 | C45: FS | D45: Muhammad Asadullah Shahid | E45: 4700G581544 | F45: 36603-1234883-1 | H45: 35943 | I45: 45215 | K45: =MAX(0, MIN(M45, J45) - MAX(L45, I45) + 1) -> 31 | L45: 45474 | M45: 45504 | N45: =ROUNDUP(K45/31*370,0) -> 370 | O45: =N45*5 -> 1850 | P45: =N45+O45 -> 2220
A46: FAA | B46: 4320 | C46: FS | D46: Muhammad Ayan Baig | E46: 4700E764102 | F46: 36302-5170382-5 | H46: 36557 | I46: 45432 | K46: =MAX(0, MIN(M46, J46) - MAX(L46, I46) + 1) -> 31 | L46: 45474 | M46: 45504 | N46: =ROUNDUP(K46/31*370,0) -> 370 | O46: =N46*5 -> 1850 | P46: =N46+O46 -> 2220
A47: FAA | B47: 4320 | C47: FS | D47: Muhammad Bilal Tanveer | E47: 4700D763961 | F47: 82203-3459651-7 | H47: 35551 | I47: 45383 | K47: =MAX(0, MIN(M47, J47) - MAX(L47, I47) + 1) -> 31 | L47: 45474 | M47: 45504 | N47: =ROUNDUP(K47/31*370,0) -> 370 | O47: =N47*5 -> 1850 | P47: =N47+O47 -> 2220
A48: FAA | B48: 4320 | C48: FS | D48: Muhammad Hassan Shakeel | E48: 4700H690431 | F48: 35402-2593513-5 | H48: 36794 | I48: 44915 | K48: =MAX(0, MIN(M48, J48) - MAX(L48, I48) + 1) -> 31 | L48: 45474 | M48: 45504 | N48: =ROUNDUP(K48/31*370,0) -> 370 | O48: =N48*5 -> 1850 | P48: =N48+O48 -> 2220
A49: FAA | B49: 4320 | C49: FS | D49: Muhammad Osama Ehsaan | E49: 4700B764082 | F49: 31203-9951845-1 | H49: 36821 | I49: 45362 | K49: =MAX(0, MIN(M49, J49) - MAX(L49, I49) + 1) -> 31 | L49: 45474 | M49: 45504 | N49: =ROUNDUP(K49/31*370,0) -> 370 | O49: =N49*5 -> 1850 | P49: =N49+O49 -> 2220
A50: FAA | B50: 4320 | C50: FS | D50: Muhammad Saqib Rasheed | F50: 33201-7216483-1 | H50: 37257 | I50: 45481 | K50: 24 | L50: 45481 | M50: 45504 | N50: =ROUNDUP(K50/31*370,0) -> 287 | O50: =N50*5 -> 1435 | P50: =N50+O50 -> 1722
A51: FAA | B51: 4320 | C51: FS | D51: Muhammad Shoaib | F51: 82401-2146189-7 | H51: 36346 | I51: 45453 | K51: 31 | L51: 45474 | M51: 45504 | N51: =ROUNDUP(K51/31*370,0) -> 370 | O51: =N51*5 -> 1850 | P51: =N51+O51 -> 2220
A52: FAA | B52: 4320 | C52: FS | D52: Muhammad Umair | F52: 37405-5832738-5 | H52: 37494 | I52: 45467 | K52: 31 | L52: 45474 | M52: 45504 | N52: =ROUNDUP(K52/31*370,0) -> 370 | O52: =N52*5 -> 1850 | P52: =N52+O52 -> 2220
A53: FAA | B53: 4320 | C53: FS | D53: Muhammad Umair Nasar | E53: 4700G764079 | F53: 35202-7433048-7 | H53: 36778 | I53: 45369 | K53: =MAX(0, MIN(M53, J53) - MAX(L53, I53) + 1) -> 31 | L53: 45474 | M53: 45504 | N53: =ROUNDUP(K53/31*370,0) -> 370 | O53: =N53*5 -> 1850 | P53: =N53+O53 -> 2220
A54: FAA | B54: 4320 | C54: FS | D54: Muhammad Uzaimah Mushtaq | E54: 4700J764076 | F54: 38201-8328241-1 | H54: 37085 | I54: 45400 | K54: =MAX(0, MIN(M54, J54) - MAX(L54, I54) + 1) -> 31 | L54: 45474 | M54: 45504 | N54: =ROUNDUP(K54/31*370,0) -> 370 | O54: =N54*5 -> 1850 | P54: =N54+O54 -> 2220
A55: FAA | B55: 4320 | C55: FS | D55: Muhammad Waleed Abdullah | E55: 4700I764077 | F55: 36601-1635702-5 | H55: 37647 | I55: 45355 | K55: =MAX(0, MIN(M55, J55) - MAX(L55, I55) + 1) -> 31 | L55: 45474 | M55: 45504 | N55: =ROUNDUP(K55/31*370,0) -> 370 | O55: =N55*5 -> 1850 | P55: =N55+O55 -> 2220
A56: FAA | B56: 4320 | C56: FS | D56: Muhammad Zahab Ahmed | E56: 3600G329844 | F56: 31102-2135283-9 | H56: 34300 | I56: 45183 | K56: =MAX(0, MIN(M56, J56) - MAX(L56, I56) + 1) -> 31 | L56: 45474 | M56: 45504 | N56: =ROUNDUP(K56/31*370,0) -> 370 | O56: =N56*5 -> 1850 | P56: =N56+O56 -> 2220
A57: FAA | B57: 4320 | C57: FS | D57: Muiz Hussain | E57: 4600F352555 | F57: 42301-8666708-3 | H57: 36412 | I57: 45355 | K57: =MAX(0, MIN(M57, J57) - MAX(L57, I57) + 1) -> 31 | L57: 45474 | M57: 45504 | N57: =ROUNDUP(K57/31*370,0) -> 370 | O57: =N57*5 -> 1850 | P57: =N57+O57 -> 2220
A58: FAA | B58: 4320 | C58: FS | D58: Musa Chughtai | F58: 37405-0493023-7 | H58: 36907 | I58: 45446 | K58: 31 | L58: 45474 | M58: 45504 | N58: =ROUNDUP(K58/31*370,0) -> 370 | O58: =N58*5 -> 1850 | P58: =N58+O58 -> 2220
A59: FAA | B59: 4320 | C59: FS | D59: Myda Abbas | E59: 4700F764101 | F59: 37405-3363346-0 | H59: 36655 | I59: 45418 | K59: =MAX(0, MIN(M59, J59) - MAX(L59, I59) + 1) -> 31 | L59: 45474 | M59: 45504 | N59: =ROUNDUP(K59/31*370,0) -> 370 | O59: =N59*5 -> 1850 | P59: =N59+O59 -> 2220
A60: FAA | B60: 4320 | C60: FS | D60: Naveed Ahmed | E60: 4700H679736 | F60: 42201-5462974-9 | H60: 31014 | I60: 44805 | K60: =MAX(0, MIN(M60, J60) - MAX(L60, I60) + 1) -> 31 | L60: 45474 | M60: 45504 | N60: =ROUNDUP(K60/31*370,0) -> 370 | O60: =N60*5 -> 1850 | P60: =N60+O60 -> 2220
A61: FAA | B61: 4320 | C61: FS | D61: Nimra Zahid | E61: 4700G537391 | F61: 42201-1439506-4 | H61: 34522 | I61: 45292 | K61: =MAX(0, MIN(M61, J61) - MAX(L61, I61) + 1) -> 31 | L61: 45474 | M61: 45504 | N61: =ROUNDUP(K61/31*370,0) -> 370 | O61: =N61*5 -> 1850 | P61: =N61+O61 -> 2220
A62: FAA | B62: 4320 | C62: FS | D62: Qazi Maaz Sajjad | F62: 35102-2075551-3 | H62: 37415 | I62: 45441 | K62: 31 | L62: 45474 | M62: 45504 | N62: =ROUNDUP(K62/31*370,0) -> 370 | O62: =N62*5 -> 1850 | P62: =N62+O62 -> 2220
A63: FAA | B63: 4320 | C63: FS | D63: Rashid Iqbal | E63: 4700I703314 | F63: 37405-6880780-7 | H63: 34732 | I63: 44986 | K63: =MAX(0, MIN(M63, J63) - MAX(L63, I63) + 1) -> 31 | L63: 45474 | M63: 45504 | N63: =ROUNDUP(K63/31*370,0) -> 370 | O63: =N63*5 -> 1850 | P63: =N63+O63 -> 2220
A64: FAA | B64: 4320 | C64: FS | D64: Sabdezar Irfan | E64: 3600G465789 | F64: 35201-1547140-8 | H64: 35395 | I64: 45376 | K64: =MAX(0, MIN(M64, J64) - MAX(L64, I64) + 1) -> 31 | L64: 45474 | M64: 45504 | N64: =ROUNDUP(K64/31*370,0) -> 370 | O64: =N64*5 -> 1850 | P64: =N64+O64 -> 2220
A65: FAA | B65: 4320 | C65: FS | D65: Shaharyar Haque | F65: 37405-6028477-3 | H65: 36289 | I65: 45476 | K65: 29 | L65: 45476 | M65: 45504 | N65: =ROUNDUP(K65/31*370,0) -> 347 | O65: =N65*5 -> 1735 | P65: =N65+O65 -> 2082
A66: FAA | B66: 4320 | C66: FS | D66: Shahzad Farooq | E66: 4700G690432 | F66: 42501-8133748-7 | H66: 36979 | I66: 44907 | K66: =MAX(0, MIN(M66, J66) - MAX(L66, I66) + 1) -> 31 | L66: 45474 | M66: 45504 | N66: =ROUNDUP(K66/31*370,0) -> 370 | O66: =N66*5 -> 1850 | P66: =N66+O66 -> 2220
A67: FAA | B67: 4320 | C67: FS | D67: Shaiq Habib | E67: 0400C579124 | F67: 61101-1388832-7 | H67: 36421 | I67: 45208 | K67: =MAX(0, MIN(M67, J67) - MAX(L67, I67) + 1) -> 31 | L67: 45474 | M67: 45504 | N67: =ROUNDUP(K67/31*370,0) -> 370 | O67: =N67*5 -> 1850 | P67: =N67+O67 -> 2220
A68: FAA | B68: 4320 | C68: FS | D68: Shan Ahmad | E68: 4700C748360 | F68: 35202-9717455-5 | H68: 35447 | I68: 45273 | K68: =MAX(0, MIN(M68, J68) - MAX(L68, I68) + 1) -> 31 | L68: 45474 | M68: 45504 | N68: =ROUNDUP(K68/31*370,0) -> 370 | O68: =N68*5 -> 1850 | P68: =N68+O68 -> 2220
A69: FAA | B69: 4320 | C69: FS | D69: Subhana Yasin | E69: 4700E723960 | F69: 36502-1828819-0 | H69: 36574 | I69: 45187 | K69: =MAX(0, MIN(M69, J69) - MAX(L69, I69) + 1) -> 31 | L69: 45474 | M69: 45504 | N69: =ROUNDUP(K69/31*370,0) -> 370 | O69: =N69*5 -> 1850 | P69: =N69+O69 -> 2220
A70: FAA | B70: 4320 | C70: FS | D70: Sukaina Ali | E70: 4700C688544 | F70: 37405-6240250-8 | H70: 36991 | I70: 45205 | K70: =MAX(0, MIN(M70, J70) - MAX(L70, I70) + 1) -> 31 | L70: 45474 | M70: 45504 | N70: =ROUNDUP(K70/31*370,0) -> 370 | O70: =N70*5 -> 1850 | P70: =N70+O70 -> 2220
A71: FAA | B71: 4320 | C71: FS | D71: Suleman Aamir | F71: 37405-8086527-1 | H71: 34504 | I71: 45481 | K71: 24 | L71: 45481 | M71: 45504 | N71: =ROUNDUP(K71/31*370,0) -> 287 | O71: =N71*5 -> 1435 | P71: =N71+O71 -> 1722
A72: FAA | B72: 4320 | C72: FS | D72: Syed Hamza Ali Shah | F72: 37406-0599193-7 | H72: 37446 | I72: 45495 | K72: 10 | L72: 45495 | M72: 45504 | N72: =ROUNDUP(K72/31*370,0) -> 120 | O72: =N72*5 -> 600 | P72: =N72+O72 -> 720
A73: FAA | B73: 4320 | C73: FS | D73: Syed Maaz Ahmed | E73: 0500A167653 | F73: 42101-8025278-5 | H73: 36433 | I73: 45432 | K73: =MAX(0, MIN(M73, J73) - MAX(L73, I73) + 1) -> 31 | L73: 45474 | M73: 45504 | N73: =ROUNDUP(K73/31*370,0) -> 370 | O73: =N73*5 -> 1850 | P73: =N73+O73 -> 2220
A74: FAA | B74: 4320 | C74: FS | D74: Syeda Fatima Shahid | F74: 61101-4873618-6 | H74: 37818 | I74: 45467 | K74: 31 | L74: 45474 | M74: 45504 | N74: =ROUNDUP(K74/31*370,0) -> 370 | O74: =N74*5 -> 1850 | P74: =N74+O74 -> 2220
A75: FAA | B75: 4320 | C75: FS | D75: Tauqeer Ahmed | E75: 4700H764078 | F75: 35201-5043196-1 | H75: 35697 | I75: 45348 | K75: =MAX(0, MIN(M75, J75) - MAX(L75, I75) + 1) -> 31 | L75: 45474 | M75: 45504 | N75: =ROUNDUP(K75/31*370,0) -> 370 | O75: =N75*5 -> 1850 | P75: =N75+O75 -> 2220
A76: FAA | B76: 4320 | C76: FS | D76: Tayyab Abbas | E76: 4700A685051 | F76: 17301-2752063-7 | H76: 36797 | I76: 44886 | K76: =MAX(0, MIN(M76, J76) - MAX(L76, I76) + 1) -> 31 | L76: 45474 | M76: 45504 | N76: =ROUNDUP(K76/31*370,0) -> 370 | O76: =N76*5 -> 1850 | P76: =N76+O76 -> 2220
A77: FAA | B77: 4320 | C77: FS | D77: Ubaid Ullah | F77: 36103-3565578-3 | H77: 36530 | I77: 45446 | K77: 31 | L77: 45474 | M77: 45504 | N77: =ROUNDUP(K77/31*370,0) -> 370 | O77: =N77*5 -> 1850 | P77: =N77+O77 -> 2220
A78: FAA | B78: 4320 | C78: FS | D78: Umaira Jabeen | E78: 3600J522091 | F78: 37104-5371430-8 | H78: 33769 | I78: 44816 | K78: =MAX(0, MIN(M78, J78) - MAX(L78, I78) + 1) -> 31 | L78: 45474 | M78: 45504 | N78: =ROUNDUP(K78/31*370,0) -> 370 | O78: =N78*5 -> 1850 | P78: =N78+O78 -> 2220
A79: FAA | B79: 4320 | C79: FS | D79: Umar Sheraz | E79: 3600C583492 | F79: 38403-8907880-9 | H79: 35973 | I79: 45414 | K79: =MAX(0, MIN(M79, J79) - MAX(L79, I79) + 1) -> 31 | L79: 45474 | M79: 45504 | N79: =ROUNDUP(K79/31*370,0) -> 370 | O79: =N79*5 -> 1850 | P79: =N79+O79 -> 2220
A80: FAA | B80: 4320 | C80: FS | D80: Uzma Shaheen | F80: 37104-4296305-6 | H80: 36451 | I80: 45453 | K80: 31 | L80: 45474 | M80: 45504 | N80: =ROUNDUP(K80/31*370,0) -> 370 | O80: =N80*5 -> 1850 | P80: =N80+O80 -> 2220
A81: FAA | B81: 4320 | C81: FS | D81: Waleed Sadiq | E81: 4700C710870 | F81: 82101-6085499-3 | H81: 35818 | I81: 45089 | K81: =MAX(0, MIN(M81, J81) - MAX(L81, I81) + 1) -> 31 | L81: 45474 | M81: 45504 | N81: =ROUNDUP(K81/31*370,0) -> 370 | O81: =N81*5 -> 1850 | P81: =N81+O81 -> 2220
A82: FAA | B82: 4320 | C82: FS | D82: Zain Shahid | E82: 4700H700799 | F82: 36401-6591078-1 | H82: 36177 | I82: 45320 | K82: =MAX(0, MIN(M82, J82) - MAX(L82, I82) + 1) -> 31 | L82: 45474 | M82: 45504 | N82: =ROUNDUP(K82/31*370,0) -> 370 | O82: =N82*5 -> 1850 | P82: =N82+O82 -> 2220
A83: FAA | B83: 4320 | C83: FS | D83: Zeeshan Nasir | E83: 4700J764092 | F83: 37405-3360545-9 | H83: 36522 | I83: 45328 | K83: =MAX(0, MIN(M83, J83) - MAX(L83, I83) + 1) -> 31 | L83: 45474 | M83: 45504 | N83: =ROUNDUP(K83/31*370,0) -> 370 | O83: =N83*5 -> 1850 | P83: =N83+O83 -> 2220
A84: FAA | B84: 4320 | C84: FS | D84: Zoha Munir | E84: 0600G182381 | F84: 35202-9887337-8 | H84: 35743 | I84: 45222 | K84: =MAX(0, MIN(M84, J84) - MAX(L84, I84) + 1) -> 31 | L84: 45474 | M84: 45504 | N84: =ROUNDUP(K84/31*370,0) -> 370 | O84: =N84*5 -> 1850 | P84: =N84+O84 -> 2220
P85: =SUM(P2:P84) -> 177126
D93: Abdul Hameed | E93: 320 | F93: =E93/10.322 -> 31.001744
D94: Abdul Moiez | E94: 320 | F94: =E94/10.322 -> 31.001744
D95: Abdullah Bin Rashid | E95: 320 | F95: =E95/10.322 -> 31.001744
D96: Abdullah Rasheed | E96: 320 | F96: =E96/10.322 -> 31.001744
D97: Adil Ali | E97: 320 | F97: =E97/10.322 -> 31.001744
D98: Ahmad Hassan | E98: 320 | F98: =E98/10.322 -> 31.001744
D99: Ahmed Hussain | E99: 320 | F99: =E99/10.322 -> 31.001744
D100: Aiman Daud | E100: 82.580645 | F100: =E100/10.322 -> 8.00045
D101: Amish Tufail | E101: 320 | F101: =E101/10.322 -> 31.001744
D102: Anamil Mehtab | E102: 320 | F102: =E102/10.322 -> 31.001744
D103: Anas Hanif Attas | E103: 320 | F103: =E103/10.322 -> 31.001744
D104: Annum Inam | E104: 320 | F104: =E104/10.322 -> 31.001744
... D175: Zoha Munir | E175: 320 | F175: =E175/10.322 -> 31.001744

Sheet Aug-24
A1: EMP_AREA_CODE | B1: EMP_REG_SERIAL_NO | C1: EMP_SUB_AREA_CODE | D1: Name | E1: payroll | F1: EOBI_NO | G1: CNIC | H1: NIC | I1: DOB | J1: DOJ | K1: DOE | L1: NO_OF_DAYS_WORKED | M1: From_Date | N1: To_Date | O1: Employee Contribution | P1: Employer Contribution | Q1: Total EOBI
A2: FAA | B2: 4320 | C2: FS | D2: Abdul Hameed | E2: Abdul Hameed | F2: 4700J763957 | G2: 17301-6508006-1 | I2: 36617 | J2: 45299 | L2: 31 | M2: 45505 | N2: 45535 | O2: =ROUNDUP(L2/31*370,0) -> 370 | P2: =O2*5 -> 1850 | Q2: =O2+P2 -> 2220
A3: FAA | B3: 4320 | C3: FS | D3: Abdul Moiez Akhtar | E3: Abdul Moiez | F3: 4700I763958 | G3: 34201-8434498-9 | I3: 37149 | J3: 45397 | L3: 31 | M3: 45505 | N3: 45535 | O3: =ROUNDUP(L3/31*370,0) -> 370 | P3: =O3*5 -> 1850 | Q3: =O3+P3 -> 2220
A4: FAA | B4: 4320 | C4: FS | D4: Abdullah Bin Rashid | E4: Abdullah Bin Rashid | F4: 4700A705194 | G4: 61101-3101618-7 | I4: 36358 | J4: 45027 | L4: 31 | M4: 45505 | N4: 45535 | O4: =ROUNDUP(L4/31*370,0) -> 370 | P4: =O4*5 -> 1850 | Q4: =O4+P4 -> 2220
A5: FAA | B5: 4320 | C5: FS | D5: Abdullah Rasheed | E5: Abdullah Rasheed | F5: 4700G688671 | G5: 37401-7271621-7 | I5: 36860 | J5: 45124 | K5: 45527 | L5: 23 | M5: 45505 | N5: 45535 | O5: =ROUNDUP(L5/31*370,0) -> 275 | P5: =O5*5 -> 1375 | Q5: =O5+P5 -> 1650
A6: FAA | B6: 4320 | C6: FS | D6: Adil Ali | E6: Adil Ali | F6: 4700H780618 | G6: 37405-7507683-3 | I6: 37978 | J6: 45453 | L6: 31 | M6: 45505 | N6: 45535 | O6: =ROUNDUP(L6/31*370,0) -> 370 | P6: =O6*5 -> 1850 | Q6: =O6+P6 -> 2220
A7: FAA | B7: 4320 | C7: FS | D7: Ahmad Hassan | E7: Ahmad Hassan | F7: 4600D315335 | G7: 37405-4246562-3 | I7: 35997 | J7: 45061 | L7: 31 | M7: 45505 | N7: 45535 | O7: =ROUNDUP(L7/31*370,0) -> 370 | P7: =O7*5 -> 1850 | Q7: =O7+P7 -> 2220
A8: FAA | B8: 4320 | C8: FS | D8: Ahmed Hussain | E8: Ahmed Hussain | F8: 4800F063920 | G8: 38102-5707136-9 | I8: 36353 | J8: 45278 | L8: 31 | M8: 45505 | N8: 45535 | O8: =ROUNDUP(L8/31*370,0) -> 370 | P8: =O8*5 -> 1850 | Q8: =O8+P8 -> 2220
A9: FAA | B9: 4320 | C9: FS | D9: Amish Tufail | E9: Amish Tufail | F9: 4700H764094 | G9: 13302-2902324-3 | I9: 37274 | J9: 45362 | L9: 31 | M9: 45505 | N9: 45535 | O9: =ROUNDUP(L9/31*370,0) -> 370 | P9: =O9*5 -> 1850 | Q9: =O9+P9 -> 2220
A10: FAA | B10: 4320 | C10: FS | D10: Anamil Mehtab | E10: Anamil Mehtab | F10: 4700A710822 | G10: 37103-6819266-4 | I10: 37398 | J10: 45096 | L10: 31 | M10: 45505 | N10: 45535 | O10: =ROUNDUP(L10/31*370,0) -> 370 | P10: =O10*5 -> 1850 | Q10: =O10+P10 -> 2220
A11: FAA | B11: 4320 | C11: FS | D11: Anas Hanif Attas | E11: Attas Anas | F11: 4700B665806 | G11: 38403-3251146-3 | I11: 36360 | J11: 45355 | L11: 31 | M11: 45505 | N11: 45535 | O11: =ROUNDUP(L11/31*370,0) -> 370 | P11: =O11*5 -> 1850 | Q11: =O11+P11 -> 2220
A12: FAA | B12: 4320 | C12: FS | D12: Annum Inam | E12: Annum Inam | F12: 4700D780620 | G12: 61101-7960847-6 | I12: 33230 | J12: 45453 | L12: 31 | M12: 45505 | N12: 45535 | O12: =ROUNDUP(L12/31*370,0) -> 370 | P12: =O12*5 -> 1850 | Q12: =O12+P12 -> 2220
A13: FAA | B13: 4320 | C13: FS | D13: Asad Ullah | E13: Asad Ullah | F13: 4700C748792 | G13: 34401-8557347-3 | I13: 35047 | J13: 45257 | L13: 31 | M13: 45505 | N13: 45535 | O13: =ROUNDUP(L13/31*370,0) -> 370 | P13: =O13*5 -> 1850 | Q13: =O13+P13 -> 2220
A14: FAA | B14: 4320 | C14: FS | D14: Asim Latif | E14: Asim Latif | F14: 4700A658224 | G14: 33302-5158556-5 | I14: 37370 | J14: 44739 | L14: 31 | M14: 45505 | N14: 45535 | O14: =ROUNDUP(L14/31*370,0) -> 370 | P14: =O14*5 -> 1850 | Q14: =O14+P14 -> 2220
A15: FAA | B15: 4320 | C15: FS | D15: Atif Nawaz | E15: Atif Nawaz | F15: 4700E740695 | G15: 38404-7428636-7 | I15: 36399 | J15: 45229 | L15: 31 | M15: 45505 | N15: 45535 | O15: =ROUNDUP(L15/31*370,0) -> 370 | P15: =O15*5 -> 1850 | Q15: =O15+P15 -> 2220
A16: FAA | B16: 4320 | C16: FS | D16: Aun Ishfaq | E16: Aun Ishfaq | F16: 4700E764097 | G16: 90403-0143681-7 | I16: 36183 | J16: 45418 | L16: 31 | M16: 45505 | N16: 45535 | O16: =ROUNDUP(L16/31*370,0) -> 370 | P16: =O16*5 -> 1850 | Q16: =O16+P16 -> 2220
A17: FAA | B17: 4320 | C17: FS | D17: Ayesha Shakeel | E17: Ayesha Shakeel | F17: 4700H763959 | G17: 42301-1838144-6 | I17: 36962 | J17: 45376 | L17: 31 | M17: 45505 | N17: 45535 | O17: =ROUNDUP(L17/31*370,0) -> 370 | P17: =O17*5 -> 1850 | Q17: =O17+P17 -> 2220
... A20: FAA | B20: 4320 | C20: FS | D20: Basit Afraz | E20: Basit Afraz | F20: 4700C703310 | G20: 37405-8019865-5 | I20: 34601 | J20: 44986 | L20: 31 | M20: 45505 | N20: 45535 | O20: =ROUNDUP(L20/31*370,0) -> 370 | P20: =O20*5 -> 1850 | Q20: =O20+P20 -> 2220
A21: FAA | B21: 4320 | C21: FS | D21: Dur e kashaf | E21: Dur e kashaf (joiner data) | G21: 61101-9306108-2 | I21: 37047 | J21: 45505 | L21: 31 | M21: 45505 | N21: 45535 | O21: =ROUNDUP(L21/31*370,0) -> 370 | P21: =O21*5 -> 1850 | Q21: =O21+P21 -> 2220
A22: FAA | B22: 4320 | C22: FS | D22: Effa Ahmed | E22: Effa Ahmad (joiner data) | G22: 61101-3525818-2 | I22: 36682 | J22: 45505 | L22: 31 | M22: 45505 | N22: 45535 | O22: =ROUNDUP(L22/31*370,0) -> 370 | P22: =O22*5 -> 1850 | Q22: =O22+P22 -> 2220
A23: FAA | B23: 4320 | C23: FS | D23: Faiza Khan | E23: Faiza Khan | F23: 4700J710823 | G23: 61101-0776147-2 | I23: 37322 | J23: 45096 | K23: 45523 | L23: 19 | M23: 45505 | N23: 45535 | O23: =ROUNDUP(L23/31*370,0) -> 227 | P23: =O23*5 -> 1135 | Q23: =O23+P23 -> 1362
A24: FAA | B24: 4320 | C24: FS | D24: Faizan Khan | E24: Faizan Khan | F24: 4700C662124 | G24: 16204-0388636-3 | I24: 35704 | J24: 44760 | L24: 31 | M24: 45505 | N24: 45535 | O24: =ROUNDUP(L24/31*370,0) -> 370 | P24: =O24*5 -> 1850 | Q24: =O24+P24 -> 2220
A25: FAA | B25: 4320 | C25: FS | D25: Farzam Habib Khan | E25: Farzam Habib Khan | F25: 4700B748793 | G25: 12101-9669033-4 | I25: 37219 | J25: 45257 | L25: 31 | M25: 45505 | N25: 45535 | O25: =ROUNDUP(L25/31*370,0) -> 370 | P25: =O25*5 -> 1850 | Q25: =O25+P25 -> 2220
A26: FAA | B26: 4320 | C26: FS | D26: Hamza Ahmad | E26: Hamza Ahmad | F26: 4700I678608 | G26: 37405-6689341-9 | I26: 36246 | J26: 44851 | L26: 31 | M26: 45505 | N26: 45535 | O26: =ROUNDUP(L26/31*370,0) -> 370 | P26: =O26*5 -> 1850 | Q26: =O26+P26 -> 2220
A27: FAA | B27: 4320 | C27: FS | D27: Hamza Ali Khan | E27: Hamza Ali Khan | F27: 4700B690429 | G27: 37405-5700118-7 | I27: 35606 | J27: 44896 | L27: 31 | M27: 45505 | N27: 45535 | O27: =ROUNDUP(L27/31*370,0) -> 370 | P27: =O27*5 -> 1850 | Q27: =O27+P27 -> 2220
A28: FAA | B28: 4320 | C28: FS | D28: Hamza Mughal | E28: Hamza Mughal | F28: 4700F739740 | G28: 13501-9345271-1 | I28: 36111 | J28: 45418 | L28: 31 | M28: 45505 | N28: 45535 | O28: =ROUNDUP(L28/31*370,0) -> 370 | P28: =O28*5 -> 1850 | Q28: =O28+P28 -> 2220
A29: FAA | B29: 4320 | C29: FS | D29: Hira Farooq | E29: Hira Farooq | F29: 4700B703311 | G29: 61101-2625195-8 | I29: 34973 | J29: 44986 | L29: 31 | M29: 45505 | N29: 45535 | O29: =ROUNDUP(L29/31*370,0) -> 370 | P29: =O29*5 -> 1850 | Q29: =O29+P29 -> 2220
A30: FAA | B30: 4320 | C30: FS | D30: Humaira Amjad | E30: Humaira Amjad | F30: 4700A764091 | G30: 36302-7205229-8 | I30: 34590 | J30: 45313 | L30: 31 | M30: 45505 | N30: 45535 | O30: =ROUNDUP(L30/31*370,0) -> 370 | P30: =O30*5 -> 1850 | Q30: =O30+P30 -> 2220
A31: FAA | B31: 4320 | C31: FS | D31: Ibrahim Shah | E31: Ibrahim Shah | F31: 4700G658260 | G31: 35201-2147689-9 | I31: 36891 | J31: 44739 | L31: 31 | M31: 45505 | N31: 45535 | O31: =ROUNDUP(L31/31*370,0) -> 370 | P31: =O31*5 -> 1850 | Q31: =O31+P31 -> 2220
A32: FAA | B32: 4320 | C32: FS | D32: Khadija Umer | E32: Khadija Umer | F32: 4700A710848 | G32: 31202-4982058-2 | I32: 36401 | J32: 45096 | L32: 31 | M32: 45505 | N32: 45535 | O32: =ROUNDUP(L32/31*370,0) -> 370 | P32: =O32*5 -> 1850 | Q32: =O32+P32 -> 2220
A33: FAA | B33: 4320 | C33: FS | D33: Lamees Zafar | E33: Lamees Zafar | F33: 4700C763962 | G33: 36304-3814800-4 | I33: 37958 | J33: 45369 | L33: 31 | M33: 45505 | N33: 45535 | O33: =ROUNDUP(L33/31*370,0) -> 370 | P33: =O33*5 -> 1850 | Q33: =O33+P33 -> 2220
A34: FAA | B34: 4320 | C34: FS | D34: Luqman Ahmed | E34: Luqman Ahmed | F34: 4700D764098 | G34: 37102-2088988-7 | I34: 34922 | J34: 45418 | L34: 31 | M34: 45505 | N34: 45535 | O34: =ROUNDUP(L34/31*370,0) -> 370 | P34: =O34*5 -> 1850 | Q34: =O34+P34 -> 2220
A35: FAA | B35: 4320 | C35: FS | D35: Misbah Aziz | E35: Misbah Aziz | G35: 36602-2764423-2 | I35: 36443 | J35: 45446 | L35: 31 | M35: 45505 | N35: 45535 | O35: =ROUNDUP(L35/31*370,0) -> 370 | P35: =O35*5 -> 1850 | Q35: =O35+P35 -> 2220
A36: FAA | B36: 4320 | C36: FS | D36: Mohammad Ehtasham Balland | E36: Mohammad Ehtasham Balland | F36: 4700D711914 | G36: 36302-5494206-1 | I36: 33737 | J36: 45139 | L36: 31 | M36: 45505 | N36: 45535 | O36: =ROUNDUP(L36/31*370,0) -> 370 | P36: =O36*5 -> 1850 | Q36: =O36+P36 -> 2220
A37: FAA | B37: 4320 | C37: FS | D37: Mohsin Ali Anjum | E37: Mohsin Ali Anjum | F37: 4700A763964 | G37: 37402-3744622-3 | I37: 35272 | J37: 45355 | L37: 31 | M37: 45505 | N37: 45535 | O37: =ROUNDUP(L37/31*370,0) -> 370 | P37: =O37*5 -> 1850 | Q37: =O37+P37 -> 2220
A38: FAA | B38: 4320 | C38: FS | D38: Muawiz Umer | E38: Muawiz Umer | F38: 4700I763966 | G38: 31202-0967091-9 | I38: 37539 | J38: 45362 | L38: 31 | M38: 45505 | N38: 45535 | O38: =ROUNDUP(L38/31*370,0) -> 370 | P38: =O38*5 -> 1850 | Q38: =O38+P38 -> 2220
A39: FAA | B39: 4320 | C39: FS | D39: Muhammad Abdullah Salam | E39: Abdullah Salam | F39: 4700G697010 | G39: 17301-7752570-9 | I39: 36690 | J39: 44938 | L39: 31 | M39: 45505 | N39: 45535 | O39: =ROUNDUP(L39/31*370,0) -> 370 | P39: =O39*5 -> 1850 | Q39: =O39+P39 -> 2220
A40: FAA | B40: 4320 | C40: FS | D40: Muhammad Abeel Khan | E40: Muhammad Abeel Khan ( new joiner) | G40: 36302-2475816-5 | I40: 37834 | J40: 45505 | L40: 31 | M40: 45505 | N40: 45535 | O40: =ROUNDUP(L40/31*370,0) -> 370 | P40: =O40*5 -> 1850 | Q40: =O40+P40 -> 2220
A41: FAA | B41: 4320 | C41: FS | D41: Muhammad Abubakar | E41: Muhammad Abubakar | F41: 4700H723959 | G41: 35201-8046049-1 | I41: 37240 | J41: 45176 | K41: 45535 | L41: 31 | M41: 45505 | N41: 45535 | O41: =ROUNDUP(L41/31*370,0) -> 370 | P41: =O41*5 -> 1850 | Q41: =O41+P41 -> 2220
A42: FAA | B42: 4320 | C42: FS | D42: Muhammad Adnan | E42: Muhammad Adnan | F42: 4700A638371 | G42: 54401-7578020-9 | I42: 33240 | J42: 44287 | L42: 31 | M42: 45505 | N42: 45535 | O42: =ROUNDUP(L42/31*370,0) -> 370 | P42: =O42*5 -> 1850 | Q42: =O42+P42 -> 2220
A43: FAA | B43: 4320 | C43: FS | D43: Muhammad Ali Kiyani | E43: Muhammad Ali Kiyani | F43: 4700I483207 | G43: 61101-7478749-3 | I43: 35173 | J43: 45264 | L43: 31 | M43: 45505 | N43: 45535 | O43: =ROUNDUP(L43/31*370,0) -> 370 | P43: =O43*5 -> 1850 | Q43: =O43+P43 -> 2220
A44: FAA | B44: 4320 | C44: FS | D44: Muhammad Anas Khan | E44: Muhammad Anas | F44: 4700J764084 | G44: 31202-1004575-1 | I44: 37964 | J44: 45355 | L44: 31 | M44: 45505 | N44: 45535 | O44: =ROUNDUP(L44/31*370,0) -> 370 | P44: =O44*5 -> 1850 | Q44: =O44+P44 -> 2220
A45: FAA | B45: 4320 | C45: FS | D45: Muhammad Asadullah Shahid | E45: Muhammad Asadullah Shahid | F45: 4700G581544 | G45: 36603-1234883-1 | I45: 35943 | J45: 45215 | L45: 31 | M45: 45505 | N45: 45535 | O45: =ROUNDUP(L45/31*370,0) -> 370 | P45: =O45*5 -> 1850 | Q45: =O45+P45 -> 2220
A46: FAA | B46: 4320 | C46: FS | D46: Muhammad Ayan Baig | E46: Muhammad Ayan Baig | F46: 4700E764102 | G46: 36302-5170382-5 | I46: 36557 | J46: 45432 | L46: 31 | M46: 45505 | N46: 45535 | O46: =ROUNDUP(L46/31*370,0) -> 370 | P46: =O46*5 -> 1850 | Q46: =O46+P46 -> 2220
A47: FAA | B47: 4320 | C47: FS | D47: Muhammad Bilal Tanveer | E47: Muhammad Bilal Tanveer | F47: 4700D763961 | G47: 82203-3459651-7 | I47: 35551 | J47: 45383 | L47: 31 | M47: 45505 | N47: 45535 | O47: =ROUNDUP(L47/31*370,0) -> 370 | P47: =O47*5 -> 1850 | Q47: =O47+P47 -> 2220
A48: FAA | B48: 4320 | C48: FS | D48: Muhammad Hamza | E48: Muhammad Hamza (new joiner) | G48: 37402-5036823-1 | I48: 35872 | J48: 45523 | L48: 13 | M48: 45505 | N48: 45535 | O48: =ROUNDUP(L48/31*370,0) -> 156 | P48: =O48*5 -> 780 | Q48: =O48+P48 -> 936
A49: FAA | B49: 4320 | C49: FS | D49: Muhammad Hassam Khan | E49: Muhammad Hassam Khan | G49: 16202-1272274-1 | I49: 37061 | J49: 45505 | L49: 31 | M49: 45505 | N49: 45535 | O49: =ROUNDUP(L49/31*370,0) -> 370 | P49: =O49*5 -> 1850 | Q49: =O49+P49 -> 2220
A50: FAA | B50: 4320 | C50: FS | D50: Muhammad Hassan Shakeel | E50: Muhammad Hassan | F50: 4700H690431 | G50: 35402-2593513-5 | I50: 36794 | J50: 44915 | L50: 31 | M50: 45505 | N50: 45535 | O50: =ROUNDUP(L50/31*370,0) -> 370 | P50: =O50*5 -> 1850 | Q50: =O50+P50 -> 2220
A51: FAA | B51: 4320 | C51: FS | D51: Muhammad Osama Ehsaan | E51: Muhammad Osama Ehsaan | F51: 4700B764082 | G51: 31203-9951845-1 | I51: 36821 | J51: 45362 | L51: 31 | M51: 45505 | N51: 45535 | O51: =ROUNDUP(L51/31*370,0) -> 370 | P51: =O51*5 -> 1850 | Q51: =O51+P51 -> 2220
A52: FAA | B52: 4320 | C52: FS | D52: Muhammad Saqib Rasheed | E52: Muhammad Saqib Rasheed | G52: 33201-7216483-1 | I52: 37257 | J52: 45481 | L52: 31 | M52: 45505 | N52: 45535 | O52: =ROUNDUP(L52/31*370,0) -> 370 | P52: =O52*5 -> 1850 | Q52: =O52+P52 -> 2220
A53: FAA | B53: 4320 | C53: FS | D53: Muhammad Shoaib | E53: Muhammad Shoaib | G53: 82401-2146189-7 | I53: 36346 | J53: 45453 | L53: 31 | M53: 45505 | N53: 45535 | O53: =ROUNDUP(L53/31*370,0) -> 370 | P53: =O53*5 -> 1850 | Q53: =O53+P53 -> 2220
A54: FAA | B54: 4320 | C54: FS | D54: Muhammad Umair | E54: Muhammad Umair | G54: 37405-5832738-5 | I54: 37494 | J54: 45467 | L54: 31 | M54: 45505 | N54: 45535 | O54: =ROUNDUP(L54/31*370,0) -> 370 | P54: =O54*5 -> 1850 | Q54: =O54+P54 -> 2220
A55: FAA | B55: 4320 | C55: FS | D55: Muhammad Umair Nasar | E55: Muhammad Umair Nasar | F55: 4700G764079 | G55: 35202-7433048-7 | I55: 36778 | J55: 45369 | L55: 31 | M55: 45505 | N55: 45535 | O55: =ROUNDUP(L55/31*370,0) -> 370 | P55: =O55*5 -> 1850 | Q55: =O55+P55 -> 2220
A56: FAA | B56: 4320 | C56: FS | D56: Muhammad Uzaimah Mushtaq | E56: Muhammad Uzaimah | F56: 4700J764076 | G56: 38201-8328241-1 | I56: 37085 | J56: 45400 | L56: 31 | M56: 45505 | N56: 45535 | O56: =ROUNDUP(L56/31*370,0) -> 370 | P56: =O56*5 -> 1850 | Q56: =O56+P56 -> 2220
A57: FAA | B57: 4320 | C57: FS | D57: Muhammad Waleed Abdullah | E57: Muhammad Waleed Abdullah | F57: 4700I764077 | G57: 36601-1635702-5 | I57: 37647 | J57: 45355 | L57: 31 | M57: 45505 | N57: 45535 | O57: =ROUNDUP(L57/31*370,0) -> 370 | P57: =O57*5 -> 1850 | Q57: =O57+P57 -> 2220
A58: FAA | B58: 4320 | C58: FS | D58: Muhammad Zahab Ahmed | E58: Muhammad Zahab Ahmad Khan | F58: 3600G329844 | G58: 31102-2135283-9 | I58: 34300 | J58: 45183 | L58: 31 | M58: 45505 | N58: 45535 | O58: =ROUNDUP(L58/31*370,0) -> 370 | P58: =O58*5 -> 1850 | Q58: =O58+P58 -> 2220
A59: FAA | B59: 4320 | C59: FS | D59: Muiz Hussain | E59: Muiz Hussain | F59: 4600F352555 | G59: 42301-8666708-3 | I59: 36412 | J59: 45355 | L59: 31 | M59: 45505 | N59: 45535 | O59: =ROUNDUP(L59/31*370,0) -> 370 | P59: =O59*5 -> 1850 | Q59: =O59+P59 -> 2220
A60: FAA | B60: 4320 | C60: FS | D60: Musa Chughtai | E60: Musa Chughtai | G60: 37405-0493023-7 | I60: 36907 | J60: 45446 | L60: 31 | M60: 45505 | N60: 45535 | O60: =ROUNDUP(L60/31*370,0) -> 370 | P60: =O60*5 -> 1850 | Q60: =O60+P60 -> 2220
A61: FAA | B61: 4320 | C61: FS | D61: Myda Abbas | E61: Myda Abbas | F61: 4700F764101 | G61: 37405-3363346-0 | I61: 36655 | J61: 45418 | L61: 31 | M61: 45505 | N61: 45535 | O61: =ROUNDUP(L61/31*370,0) -> 370 | P61: =O61*5 -> 1850 | Q61: =O61+P61 -> 2220
A62: FAA | B62: 4320 | C62: FS | D62: Naveed Ahmed | E62: Naveed Ahmed | F62: 4700H679736 | G62: 42201-5462974-9 | I62: 31014 | J62: 44805 | L62: 31 | M62: 45505 | N62: 45535 | O62: =ROUNDUP(L62/31*370,0) -> 370 | P62: =O62*5 -> 1850 | Q62: =O62+P62 -> 2220
A63: FAA | B63: 4320 | C63: FS | D63: Nimra Zahid | E63: Nimra Zahid | F63: 4700G537391 | G63: 42201-1439506-4 | I63: 34522 | J63: 45292 | L63: 31 | M63: 45505 | N63: 45535 | O63: =ROUNDUP(L63/31*370,0) -> 370 | P63: =O63*5 -> 1850 | Q63: =O63+P63 -> 2220
A64: FAA | B64: 4320 | C64: FS | D64: Qazi Maaz Sajjad | E64: Qazi Maaz Sajjad | G64: 35102-2075551-3 | I64: 37415 | J64: 45441 | L64: 31 | M64: 45505 | N64: 45535 | O64: =ROUNDUP(L64/31*370,0) -> 370 | P64: =O64*5 -> 1850 | Q64: =O64+P64 -> 2220
A65: FAA | B65: 4320 | C65: FS | D65: Rashid Iqbal | E65: Rashid Iqbal | F65: 4700I703314 | G65: 37405-6880780-7 | I65: 34732 | J65: 44986 | L65: 31 | M65: 45505 | N65: 45535 | O65: =ROUNDUP(L65/31*370,0) -> 370 | P65: =O65*5 -> 1850 | Q65: =O65+P65 -> 2220
A66: FAA | B66: 4320 | C66: FS | D66: Sabdezar Irfan | E66: Sabdezar Irfan | F66: 3600G465789 | G66: 35201-1547140-8 | I66: 35395 | J66: 45376 | L66: 31 | M66: 45505 | N66: 45535 | O66: =ROUNDUP(L66/31*370,0) -> 370 | P66: =O66*5 -> 1850 | Q66: =O66+P66 -> 2220
A67: FAA | B67: 4320 | C67: FS | D67: Shaharyar Haque | E67: Shaharyar Haque | G67: 37405-6028477-3 | I67: 36289 | J67: 45476 | L67: 31 | M67: 45505 | N67: 45535 | O67: =ROUNDUP(L67/31*370,0) -> 370 | P67: =O67*5 -> 1850 | Q67: =O67+P67 -> 2220
A68: FAA | B68: 4320 | C68: FS | D68: Shahzad Farooq | E68: Shahzad Farooq | F68: 4700G690432 | G68: 42501-8133748-7 | I68: 36979 | J68: 44907 | L68: 31 | M68: 45505 | N68: 45535 | O68: =ROUNDUP(L68/31*370,0) -> 370 | P68: =O68*5 -> 1850 | Q68: =O68+P68 -> 2220
A69: FAA | B69: 4320 | C69: FS | D69: Shaiq Habib | E69: Shaiq Habib | F69: 0400C579124 | G69: 61101-1388832-7 | I69: 36421 | J69: 45208 | K69: 45535 | L69: 31 | M69: 45505 | N69: 45535 | O69: =ROUNDUP(L69/31*370,0) -> 370 | P69: =O69*5 -> 1850 | Q69: =O69+P69 -> 2220
A70: FAA | B70: 4320 | C70: FS | D70: Shan Ahmad | E70: Shan Ahmad | F70: 4700C748360 | G70: 35202-9717455-5 | I70: 35447 | J70: 45273 | L70: 31 | M70: 45505 | N70: 45535 | O70: =ROUNDUP(L70/31*370,0) -> 370 | P70: =O70*5 -> 1850 | Q70: =O70+P70 -> 2220
A71: FAA | B71: 4320 | C71: FS | D71: Subhana Yasin | E71: Subhana Yasin | F71: 4700E723960 | G71: 36502-1828819-0 | I71: 36574 | J71: 45187 | L71: 31 | M71: 45505 | N71: 45535 | O71: =ROUNDUP(L71/31*370,0) -> 370 | P71: =O71*5 -> 1850 | Q71: =O71+P71 -> 2220
